
{"nodes":[{"id":-1,"name":"default","type":"root","type_id":10,"reweight":-1,"kb":785309065216,"kb_used":316880884324,"kb_used_data":316088744636,"kb_used_omap":5606116,"kb_used_meta":786460310,"kb_avail":468428180892,"utilization":40.351104852818885,"var":1,"pgs":0,"children":[-77,-118,-110,-83,-4,-16,-10]},{"id":-10,"name":"01-01","type":"rack","type_id":3,"pool_weights":{},"reweight":-1,"kb":228560097280,"kb_used":88085286428,"kb_used_data":87865361476,"kb_used_omap":1812448,"kb_used_meta":218080057,"kb_avail":140474810852,"utilization":38.53922337112509,"var":0.9550971035786342,"pgs":0,"children":[-13,-25,-45,-37,-31,-9,-29]},{"id":-29,"name":"sf-sby001-hyperconverge001-rack001","type":"host","type_id":1,"pool_weights":{},"reweight":-1,"kb":35163095040,"kb_used":12856406592,"kb_used_data":12821854608,"kb_used_omap":80461,"kb_used_meta":34463789,"kb_avail":22306688448,"utilization":36.56221551992256,"var":0.9061019680448319,"pgs":0,"children":[90,71,50,40,31,11]},{"id":11,"device_class":"general","name":"osd.11","type":"osd","type_id":0,"crush_weight":5.4579925537109375,"depth":3,"pool_weights":{},"reweight":1,"kb":5860515840,"kb_used":2224842240,"kb_used_data":2219113360,"kb_used_omap":14963,"kb_used_meta":5713228,"kb_avail":3635673600,"utilization":37.963249323800142,"var":0.94082304467923561,"pgs":89,"status":"up"},{"id":31,"device_class":"general","name":"osd.31","type":"osd","type_id":0,"crush_weight":5.4579925537109375,"depth":3,"pool_weights":{},"reweight":1,"kb":5860515840,"kb_used":2269567088,"kb_used_data":2263737552,"kb_used_omap":13152,"kb_used_meta":5816351,"kb_avail":3590948752,"utilization":38.726404807396612,"var":0.95973592169660815,"pgs":85,"status":"up"},{"id":40,"device_class":"general","name":"osd.40","type":"osd","type_id":0,"crush_weight":5.4579925537109375,"depth":3,"pool_weights":{},"reweight":1,"kb":5860515840,"kb_used":1705814192,"kb_used_data":1700382432,"kb_used_omap":25086,"kb_used_meta":5406657,"kb_avail":4154701648,"utilization":29.106894999877689,"var":0.72134071931971677,"pgs":82,"status":"up"},{"id":50,"device_class":"general","name":"osd.50","type":"osd","type_id":0,"crush_weight":5.4579925537109375,"depth":3,"pool_weights":{},"reweight":1,"kb":5860515840,"kb_used":1855055920,"kb_used_data":1849209744,"kb_used_omap":9852,"kb_used_meta":5829635,"kb_avail":4005459920,"utilization":31.653458000038441,"var":0.7844508376039464,"pgs":81,"status":"up"},{"id":71,"device_class":"general","name":"osd.71","type":"osd","type_id":0,"crush_weight":5.4579925537109375,"depth":3,"pool_weights":{},"reweight":1,"kb":5860515840,"kb_used":2527028720,"kb_used_data":2521073248,"kb_used_omap":9001,"kb_used_meta":5946326,"kb_avail":3333487120,"utilization":43.119561297866916,"var":1.0686091856752375,"pgs":93,"status":"up"},{"id":90,"device_class":"general","name":"osd.90","type":"osd","type_id":0,"crush_weight":5.4579925537109375,"depth":3,"pool_weights":{},"reweight":1,"kb":5860515840,"kb_used":2274098432,"kb_used_data":2268338272,"kb_used_omap":8407,"kb_used_meta":5751592,"kb_avail":3586417408,"utilization":38.803724690555569,"var":0.96165209929424722,"pgs":100,"status":"up"},{"id":-9,"name":"sf-sby001-hyperconverge002-rack001","type":"host","type_id":1,"pool_weights":{},"reweight":-1,"kb":35163090944,"kb_used":13720337952,"kb_used_data":13686814352,"kb_used_omap":494842,"kb_used_meta":33026496,"kb_avail":21442752992,"utilization":39.01914645060846,"var":0.96699078235729208,"pgs":0,"children":[123,78,56,35,15,2]},{"id":2,"device_class":"general","name":"osd.2","type":"osd","type_id":0,"crush_weight":5.4579925537109375,"depth":3,"pool_weights":{},"reweight":1,"kb":5860515840,"kb_used":2878294400,"kb_used_data":2871650496,"kb_used_omap":75069,"kb_used_meta":6567746,"kb_avail":2982221440,"utilization":49.113328563241289,"var":1.2171495363604719,"pgs":99,"status":"up"},{"id":15,"device_class":"general","name":"osd.15","type":"osd","type_id":0,"crush_weight":5.4579925537109375,"depth":3,"pool_weights":{},"reweight":1,"kb":5860515840,"kb_used":2726941280,"kb_used_data":2720478944,"kb_used_omap":80274,"kb_used_meta":6381997,"kb_avail":3133574560,"utilization":46.530738154271418,"var":1.1531465699388608,"pgs":95,"status":"up"},{"id":35,"device_class":"general","name":"osd.35","type":"osd","type_id":0,"crush_weight":5.4579925537109375,"depth":3,"pool_weights":{},"reweight":1,"kb":5860515840,"kb_used":1754572096,"kb_used_data":1749671520,"kb_used_omap":100112,"kb_used_meta":4800431,"kb_avail":4105943744,"utilization":29.9388679068906,"var":0.74195906199081696,"pgs":75,"status":"up"},{"id":56,"device_class":"general","name":"osd.56","type":"osd","type_id":0,"crush_weight":5.4579925537109375,"depth":3,"pool_weights":{},"reweight":1,"kb":5860515840,"kb_used":2172052496,"kb_used_data":2166833184,"kb_used_omap":120219,"kb_used_meta":5099044,"kb_avail":3688463344,"utilization":37.062479742397556,"var":0.91849975056651789,"pgs":94,"status":"up"},{"id":78,"device_class":"general","name":"osd.78","type":"osd","type_id":0,"crush_weight":5.4579925537109375,"depth":3,"pool_weights":{},"reweight":1,"kb":5860515840,"kb_used":2276160576,"kb_used_data":2270667504,"kb_used_omap":52882,"kb_used_meta":5439213,"kb_avail":3584355264,"utilization":38.83891176378085,"var":0.96252412184117941,"pgs":85,"status":"up"},{"id":123,"device_class":"general","name":"osd.123","type":"osd","type_id":0,"crush_weight":5.4579925537109375,"depth":3,"pool_weights":{},"reweight":1,"kb":5860511744,"kb_used":1912317104,"kb_used_data":1907512704,"kb_used_omap":66286,"kb_used_meta":4738065,"kb_avail":3948194640,"utilization":32.630548107984474,"var":0.8086655427900864,"pgs":72,"status":"up"},{"id":-31,"name":"sf-sby001-hyperconverge004-rack001","type":"host","type_id":1,"pool_weights":{},"reweight":-1,"kb":35163090944,"kb_used":13294063056,"kb_used_data":13262168016,"kb_used_omap":85571,"kb_used_meta":31796023,"kb_avail":21869027888,"utilization":37.806867084500183,"var":0.93694750670151816,"pgs":0,"children":[108,93,52,41,32,12]},{"id":12,"device_class":"general","name":"osd.12","type":"osd","type_id":0,"crush_weight":5.4579925537109375,"depth":3,"pool_weights":{},"reweight":1,"kb":5860511744,"kb_used":2619342576,"kb_used_data":2613359360,"kb_used_omap":9811,"kb_used_meta":5973356,"kb_avail":3241169168,"utilization":44.694775651318956,"var":1.1076468863577258,"pgs":88,"status":"up"},{"id":32,"device_class":"general","name":"osd.32","type":"osd","type_id":0,"crush_weight":5.4579925537109375,"depth":3,"pool_weights":{},"reweight":1,"kb":5860515840,"kb_used":2210909328,"kb_used_data":2205651200,"kb_used_omap":11836,"kb_used_meta":5246211,"kb_avail":3649606512,"utilization":37.725507248181074,"var":0.93493120909043981,"pgs":80,"status":"up"},{"id":41,"device_class":"general","name":"osd.41","type":"osd","type_id":0,"crush_weight":5.4579925537109375,"depth":3,"pool_weights":{},"reweight":1,"kb":5860515840,"kb_used":2319160624,"kb_used_data":2313634368,"kb_used_omap":26476,"kb_used_meta":5494291,"kb_avail":3541355216,"utilization":39.572636390997282,"var":0.98070762957641244,"pgs":101,"status":"up"},{"id":52,"device_class":"general","name":"osd.52","type":"osd","type_id":0,"crush_weight":5.4579925537109375,"depth":3,"pool_weights":{},"reweight":1,"kb":5860515840,"kb_used":1911456496,"kb_used_data":1906859008,"kb_used_omap":6501,"kb_used_meta":4584154,"kb_avail":3949059344,"utilization":32.615840451341569,"var":0.80830105074714109,"pgs":78,"status":"up"},{"id":93,"device_class":"general","name":"osd.93","type":"osd","type_id":0,"crush_weight":5.4579925537109375,"depth":3,"pool_weights":{},"reweight":1,"kb":5860515840,"kb_used":2369149376,"kb_used_data":2363317552,"kb_used_omap":14992,"kb_used_meta":5816815,"kb_avail":3491366464,"utilization":40.425611681308929,"var":1.0018464631578692,"pgs":93,"status":"up"},{"id":108,"device_class":"general","name":"osd.108","type":"osd","type_id":0,"crush_weight":5.4579925537109375,"depth":3,"pool_weights":{},"reweight":1,"kb":5860515840,"kb_used":1864044656,"kb_used_data":1859346528,"kb_used_omap":15955,"kb_used_meta":4681196,"kb_avail":3996471184,"utilization":31.806835897913039,"var":0.78825192058380644,"pgs":82,"status":"up"},{"id":-37,"name":"sf-sby001-hyperconverge005-rack001","type":"host","type_id":1,"pool_weights":{},"reweight":-1,"kb":29302579200,"kb_used":11398698788,"kb_used_data":11370554740,"kb_used_omap":184369,"kb_used_meta":27955402,"kb_avail":17903880412,"utilization":38.899984572006552,"var":0.9640376568100103,"pgs":0,"children":[65,44,23,22,20]},{"id":20,"device_class":"general","name":"osd.20","type":"osd","type_id":0,"crush_weight":5.4579925537109375,"depth":3,"pool_weights":{},"reweight":1,"kb":5860515840,"kb_used":2171924552,"kb_used_data":2166462080,"kb_used_omap":18363,"kb_used_meta":5440004,"kb_avail":3688591288,"utilization":37.060296589864691,"var":0.91844564665682749,"pgs":87,"status":"up"},{"id":22,"device_class":"general","name":"osd.22","type":"osd","type_id":0,"crush_weight":5.4579925537109375,"depth":3,"pool_weights":{},"reweight":1,"kb":5860515840,"kb_used":1807797420,"kb_used_data":1803035736,"kb_used_omap":80304,"kb_used_meta":4681359,"kb_avail":4052718420,"utilization":30.847069939836558,"var":0.76446655060255719,"pgs":81,"status":"up"},{"id":23,"device_class":"general","name":"osd.23","type":"osd","type_id":0,"crush_weight":5.4579925537109375,"depth":3,"pool_weights":{},"reweight":1,"kb":5860515840,"kb_used":2111637948,"kb_used_data":2107026664,"kb_used_omap":9505,"kb_used_meta":4601758,"kb_avail":3748877892,"utilization":36.031605504542071,"var":0.89295214185504368,"pgs":95,"status":"up"},{"id":44,"device_class":"general","name":"osd.44","type":"osd","type_id":0,"crush_weight":5.4579925537109375,"depth":3,"pool_weights":{},"reweight":1,"kb":5860515840,"kb_used":2833664052,"kb_used_data":2827012484,"kb_used_omap":22846,"kb_used_meta":6628673,"kb_avail":3026851788,"utilization":48.35178556568836,"var":1.1982766207282811,"pgs":95,"status":"up"},{"id":65,"device_class":"general","name":"osd.65","type":"osd","type_id":0,"crush_weight":5.4579925537109375,"depth":3,"pool_weights":{},"reweight":1,"kb":5860515840,"kb_used":2473674816,"kb_used_data":2467017776,"kb_used_omap":53351,"kb_used_meta":6603608,"kb_avail":3386841024,"utilization":42.209165260101067,"var":1.0460473242073416,"pgs":93,"status":"up"},{"id":-45,"name":"sf-sby001-hyperconverge006-rack001","type":"host","type_id":1,"pool_weights":{},"reweight":-1,"kb":29302575104,"kb_used":10376434860,"kb_used_data":10351210176,"kb_used_omap":240588,"kb_used_meta":24980015,"kb_avail":18926140244,"utilization":35.41134123254426,"var":0.87758046184131833,"pgs":0,"children":[111,94,89,69,46,26]},{"id":26,"device_class":"general","name":"osd.26","type":"osd","type_id":0,"crush_weight":5.4579925537109375,"depth":3,"pool_weights":{},"reweight":1,"kb":5860511744,"kb_used":2317600016,"kb_used_data":2311621680,"kb_used_omap":80968,"kb_used_meta":5897271,"kb_avail":3542911728,"utilization":39.54603483855761,"var":0.98004837743110684,"pgs":98,"status":"up"},{"id":46,"device_class":"general","name":"osd.46","type":"osd","type_id":0,"crush_weight":5.4579925537109375,"depth":3,"pool_weights":{},"reweight":1,"kb":5860515840,"kb_used":1553888144,"kb_used_data":1549758912,"kb_used_omap":34564,"kb_used_meta":4094651,"kb_avail":4306627696,"utilization":26.514528523141063,"var":0.65709547780297739,"pgs":87,"status":"up"},{"id":69,"device_class":"general","name":"osd.69","type":"osd","type_id":0,"crush_weight":5.4579925537109375,"depth":3,"pool_weights":{},"reweight":1,"kb":5860515840,"kb_used":2481261248,"kb_used_data":2475356784,"kb_used_omap":14255,"kb_used_meta":5890192,"kb_avail":3379254592,"utilization":42.338615161903562,"var":1.0492554123693549,"pgs":85,"status":"up"},{"id":89,"device_class":"general","name":"osd.89","type":"osd","type_id":0,"crush_weight":5.4579925537109375,"depth":3,"pool_weights":{},"reweight":0,"kb":0,"kb_used":0,"kb_used_data":0,"kb_used_omap":0,"kb_used_meta":0,"kb_avail":0,"utilization":0,"var":0,"pgs":0,"status":"up"},{"id":94,"device_class":"general","name":"osd.94","type":"osd","type_id":0,"crush_weight":5.4579925537109375,"depth":3,"pool_weights":{},"reweight":1,"kb":5860515840,"kb_used":2370204812,"kb_used_data":2364970368,"kb_used_omap":70159,"kb_used_meta":5164272,"kb_avail":3490311028,"utilization":40.44362094924395,"var":1.0022927772798915,"pgs":94,"status":"up"},{"id":111,"device_class":"general","name":"osd.111","type":"osd","type_id":0,"crush_weight":5.4579925537109375,"depth":3,"pool_weights":{},"reweight":1,"kb":5860515840,"kb_used":1653480640,"kb_used_data":1649502432,"kb_used_omap":40642,"kb_used_meta":3933629,"kb_avail":4207035200,"utilization":28.213909579672769,"var":0.69921033593958148,"pgs":71,"status":"up"},{"id":-25,"name":"sf-sby001-hyperconverge007-rack001","type":"host","type_id":1,"pool_weights":{},"reweight":-1,"kb":29302575104,"kb_used":11549114652,"kb_used_data":11518057488,"kb_used_omap":216400,"kb_used_meta":30840491,"kb_avail":17753460452,"utilization":39.413309618728583,"var":0.97675911880205213,"pgs":0,"children":[85,84,64,21,8]},{"id":8,"device_class":"general","name":"osd.8","type":"osd","type_id":0,"crush_weight":5.4579925537109375,"depth":3,"pool_weights":{},"reweight":1,"kb":5860511744,"kb_used":2574566240,"kb_used_data":2568120640,"kb_used_omap":92496,"kb_used_meta":6353071,"kb_avail":3285945504,"utilization":43.930741076252332,"var":1.0887122232833577,"pgs":97,"status":"up"},{"id":21,"device_class":"general","name":"osd.21","type":"osd","type_id":0,"crush_weight":5.4579925537109375,"depth":3,"pool_weights":{},"reweight":1,"kb":5860515840,"kb_used":2122493816,"kb_used_data":2115501360,"kb_used_omap":48731,"kb_used_meta":6943716,"kb_avail":3738022024,"utilization":36.216842918728467,"var":0.89754278230620488,"pgs":86,"status":"up"},{"id":64,"device_class":"general","name":"osd.64","type":"osd","type_id":0,"crush_weight":5.4579925537109375,"depth":3,"pool_weights":{},"reweight":1,"kb":5860515840,"kb_used":1799122492,"kb_used_data":1794462068,"kb_used_omap":29535,"kb_used_meta":4630880,"kb_avail":4061393348,"utilization":30.699046655933959,"var":0.76079816817678425,"pgs":67,"status":"up"},{"id":84,"device_class":"general","name":"osd.84","type":"osd","type_id":0,"crush_weight":5.4579925537109375,"depth":3,"pool_weights":{},"reweight":1,"kb":5860515840,"kb_used":2472899096,"kb_used_data":2466471096,"kb_used_omap":26257,"kb_used_meta":6401710,"kb_avail":3387616744,"utilization":42.195928882601571,"var":1.045719294093971,"pgs":81,"status":"up"},{"id":85,"device_class":"general","name":"osd.85","type":"osd","type_id":0,"crush_weight":5.4579925537109375,"depth":3,"pool_weights":{},"reweight":1,"kb":5860515840,"kb_used":2580033008,"kb_used_data":2573502324,"kb_used_omap":19381,"kb_used_meta":6511114,"kb_avail":3280482832,"utilization":44.023991717425339,"var":1.0910232043956007,"pgs":100,"status":"up"},{"id":-13,"name":"sf-sby001-hyperconverge008-rack001","type":"host","type_id":1,"pool_weights":{},"reweight":-1,"kb":35163090944,"kb_used":14890230528,"kb_used_data":14854702096,"kb_used_omap":510217,"kb_used_meta":35017841,"kb_avail":20272860416,"utilization":42.3461934894002,"var":1.0494432220346488,"pgs":0,"children":[98,81,60,38,16,6]},{"id":6,"device_class":"general","name":"osd.6","type":"osd","type_id":0,"crush_weight":5.4579925537109375,"depth":3,"pool_weights":{},"reweight":1,"kb":5860511744,"kb_used":2419268672,"kb_used_data":2413126512,"kb_used_omap":99619,"kb_used_meta":6042396,"kb_avail":3441243072,"utilization":41.280843340632337,"var":1.0230412151341255,"pgs":97,"status":"up"},{"id":16,"device_class":"general","name":"osd.16","type":"osd","type_id":0,"crush_weight":5.4579925537109375,"depth":3,"pool_weights":{},"reweight":1,"kb":5860515840,"kb_used":2473649584,"kb_used_data":2467748272,"kb_used_omap":80702,"kb_used_meta":5820545,"kb_avail":3386866256,"utilization":42.208734717795764,"var":1.046036654306062,"pgs":90,"status":"up"},{"id":38,"device_class":"general","name":"osd.38","type":"osd","type_id":0,"crush_weight":5.4579925537109375,"depth":3,"pool_weights":{},"reweight":1,"kb":5860515840,"kb_used":2424582768,"kb_used_data":2418484864,"kb_used_omap":75516,"kb_used_meta":6022339,"kb_avail":3435933072,"utilization":41.371490738944921,"var":1.0252876814612117,"pgs":98,"status":"up"},{"id":60,"device_class":"general","name":"osd.60","type":"osd","type_id":0,"crush_weight":5.4579925537109375,"depth":3,"pool_weights":{},"reweight":1,"kb":5860515840,"kb_used":2734406096,"kb_used_data":2728070400,"kb_used_omap":77464,"kb_used_meta":6258215,"kb_avail":3126109744,"utilization":46.658112880384266,"var":1.15630323012394,"pgs":103,"status":"up"},{"id":81,"device_class":"general","name":"osd.81","type":"osd","type_id":0,"crush_weight":5.4579925537109375,"depth":3,"pool_weights":{},"reweight":1,"kb":5860515840,"kb_used":2362772128,"kb_used_data":2357327824,"kb_used_omap":77604,"kb_used_meta":5366619,"kb_avail":3497743712,"utilization":40.3167945025126,"var":0.99914970481151799,"pgs":99,"status":"up"},{"id":98,"device_class":"general","name":"osd.98","type":"osd","type_id":0,"crush_weight":5.4579925537109375,"depth":3,"pool_weights":{},"reweight":1,"kb":5860515840,"kb_used":2475551280,"kb_used_data":2469944224,"kb_used_omap":99312,"kb_used_meta":5507727,"kb_avail":3384964560,"utilization":42.241184011542572,"var":1.0468408279182881,"pgs":93,"status":"up"},{"id":-16,"name":"01-02","type":"rack","type_id":3,"pool_weights":{},"reweight":-1,"kb":240281124864,"kb_used":87811477752,"kb_used_data":87588658960,"kb_used_omap":2159601,"kb_used_meta":220642662,"kb_avail":152469647112,"utilization":36.545308251616362,"var":0.90568296419430872,"pgs":0,"children":[-47,-19,-41,-23,-15,-33,-27]},{"id":-27,"name":"sf-sby001-hyperconverge009-rack002","type":"host","type_id":1,"pool_weights":{},"reweight":-1,"kb":29302575104,"kb_used":10761658304,"kb_used_data":10735371056,"kb_used_omap":252630,"kb_used_meta":26030565,"kb_avail":18540916800,"utilization":36.725981473658813,"var":0.91016049269573285,"pgs":0,"children":[124,88,70,49,29,9]},{"id":9,"device_class":"general","name":"osd.9","type":"osd","type_id":0,"crush_weight":5.4579925537109375,"depth":3,"pool_weights":{},"reweight":1,"kb":5860515840,"kb_used":2060126176,"kb_used_data":2054999632,"kb_used_omap":32478,"kb_used_meta":5094049,"kb_avail":3800389664,"utilization":35.152642399478609,"var":0.87116926606342682,"pgs":87,"status":"up"},{"id":29,"device_class":"general","name":"osd.29","type":"osd","type_id":0,"crush_weight":5.4579925537109375,"depth":3,"pool_weights":{},"reweight":1,"kb":5860515840,"kb_used":1648847792,"kb_used_data":1643933552,"kb_used_omap":101798,"kb_used_meta":4812377,"kb_avail":4211668048,"utilization":28.134857698806254,"var":0.69725123516266696,"pgs":79,"status":"up"},{"id":49,"device_class":"general","name":"osd.49","type":"osd","type_id":0,"crush_weight":5.4579925537109375,"depth":3,"pool_weights":{},"reweight":0,"kb":0,"kb_used":0,"kb_used_data":0,"kb_used_omap":0,"kb_used_meta":0,"kb_avail":0,"utilization":0,"var":0,"pgs":0,"status":"down"},{"id":70,"device_class":"general","name":"osd.70","type":"osd","type_id":0,"crush_weight":5.4579925537109375,"depth":3,"pool_weights":{},"reweight":1,"kb":5860515840,"kb_used":2885320656,"kb_used_data":2878806848,"kb_used_omap":11605,"kb_used_meta":6502186,"kb_avail":2975195184,"utilization":49.233219989044514,"var":1.2201207418885616,"pgs":99,"status":"up"},{"id":88,"device_class":"general","name":"osd.88","type":"osd","type_id":0,"crush_weight":5.4579925537109375,"depth":3,"pool_weights":{},"reweight":1,"kb":5860515840,"kb_used":1853209200,"kb_used_data":1849051936,"kb_used_omap":51193,"kb_used_meta":4106054,"kb_avail":4007306640,"utilization":31.621946780712054,"var":0.78366991179184475,"pgs":80,"status":"up"},{"id":124,"device_class":"general","name":"osd.124","type":"osd","type_id":0,"crush_weight":5.4579925537109375,"depth":3,"pool_weights":{},"reweight":1,"kb":5860511744,"kb_used":2314154480,"kb_used_data":2308579088,"kb_used_omap":55556,"kb_used_meta":5515899,"kb_avail":3546357264,"utilization":39.487242430138195,"var":0.97859135639949291,"pgs":85,"status":"up"},{"id":-33,"name":"sf-sby001-hyperconverge010-rack002","type":"host","type_id":1,"pool_weights":{},"reweight":-1,"kb":35163090944,"kb_used":12962085952,"kb_used_data":12928189916,"kb_used_omap":397222,"kb_used_meta":33494868,"kb_avail":22201004992,"utilization":36.862760366098492,"var":0.91355021134008174,"pgs":0,"children":[125,120,72,51,33,10]},{"id":10,"device_class":"general","name":"osd.10","type":"osd","type_id":0,"crush_weight":5.4579925537109375,"depth":3,"pool_weights":{},"reweight":1,"kb":5860515840,"kb_used":1751951344,"kb_used_data":1746969968,"kb_used_omap":97274,"kb_used_meta":4880389,"kb_avail":4108564496,"utilization":29.894149112990025,"var":0.74085081987294465,"pgs":80,"status":"up"},{"id":33,"device_class":"general","name":"osd.33","type":"osd","type_id":0,"crush_weight":5.4579925537109375,"depth":3,"pool_weights":{},"reweight":1,"kb":5860515840,"kb_used":2369385968,"kb_used_data":2363187744,"kb_used_omap":26440,"kb_used_meta":6171703,"kb_avail":3491129872,"utilization":40.429648732081574,"var":1.0019465112429804,"pgs":88,"status":"up"},{"id":51,"device_class":"general","name":"osd.51","type":"osd","type_id":0,"crush_weight":5.4579925537109375,"depth":3,"pool_weights":{},"reweight":1,"kb":5860515840,"kb_used":2017939312,"kb_used_data":2012768864,"kb_used_omap":42274,"kb_used_meta":5128157,"kb_avail":3842576528,"utilization":34.432793410895378,"var":0.85332963091071201,"pgs":86,"status":"up"},{"id":72,"device_class":"general","name":"osd.72","type":"osd","type_id":0,"crush_weight":5.4579925537109375,"depth":3,"pool_weights":{},"reweight":1,"kb":5860515840,"kb_used":2484084368,"kb_used_data":2478249280,"kb_used_omap":121479,"kb_used_meta":5713592,"kb_avail":3376431472,"utilization":42.386787030678853,"var":1.0504492302078257,"pgs":97,"status":"up"},{"id":120,"device_class":"general","name":"osd.120","type":"osd","type_id":0,"crush_weight":5.4579925537109375,"depth":3,"pool_weights":{},"reweight":1,"kb":5860511744,"kb_used":2374682096,"kb_used_data":2368935520,"kb_used_omap":51603,"kb_used_meta":5694956,"kb_avail":3485829648,"utilization":40.520046708057585,"var":1.0041867962687743,"pgs":89,"status":"up"},{"id":125,"device_class":"general","name":"osd.125","type":"osd","type_id":0,"crush_weight":5.4579925537109375,"depth":3,"pool_weights":{},"reweight":1,"kb":5860515840,"kb_used":1964042864,"kb_used_data":1958078540,"kb_used_omap":58152,"kb_used_meta":5906071,"kb_avail":3896472976,"utilization":33.513139758018298,"var":0.83053834288448503,"pgs":77,"status":"up"},{"id":-15,"name":"sf-sby001-hyperconverge011-rack002","type":"host","type_id":1,"pool_weights":{},"reweight":-1,"kb":35163095040,"kb_used":13893931104,"kb_used_data":13859104220,"kb_used_omap":279966,"kb_used_meta":34546652,"kb_avail":21269163936,"utilization":39.512821861087232,"var":0.97922527785077262,"pgs":0,"children":[100,99,79,58,37,17]},{"id":17,"device_class":"general","name":"osd.17","type":"osd","type_id":0,"crush_weight":5.4579925537109375,"depth":3,"pool_weights":{},"reweight":1,"kb":5860515840,"kb_used":2209312064,"kb_used_data":2203911360,"kb_used_omap":59563,"kb_used_meta":5341076,"kb_avail":3651203776,"utilization":37.698252582489395,"var":0.93425577118629588,"pgs":81,"status":"up"},{"id":37,"device_class":"general","name":"osd.37","type":"osd","type_id":0,"crush_weight":5.4579925537109375,"depth":3,"pool_weights":{},"reweight":1,"kb":5860515840,"kb_used":2371641776,"kb_used_data":2365740656,"kb_used_omap":38472,"kb_used_meta":5862583,"kb_avail":3488874064,"utilization":40.46814036083213,"var":1.0029004288343562,"pgs":99,"status":"up"},{"id":58,"device_class":"general","name":"osd.58","type":"osd","type_id":0,"crush_weight":5.4579925537109375,"depth":3,"pool_weights":{},"reweight":1,"kb":5860515840,"kb_used":2937719520,"kb_used_data":2930542688,"kb_used_omap":40291,"kb_used_meta":7136476,"kb_avail":2922796320,"utilization":50.127319850397335,"var":1.2422787438717553,"pgs":108,"status":"up"},{"id":79,"device_class":"general","name":"osd.79","type":"osd","type_id":0,"crush_weight":5.4579925537109375,"depth":3,"pool_weights":{},"reweight":1,"kb":5860515840,"kb_used":2164251568,"kb_used_data":2159332432,"kb_used_omap":48768,"kb_used_meta":4870335,"kb_avail":3696264272,"utilization":36.929369821479739,"var":0.91520095809470492,"pgs":78,"status":"up"},{"id":99,"device_class":"general","name":"osd.99","type":"osd","type_id":0,"crush_weight":5.4579925537109375,"depth":3,"pool_weights":{},"reweight":1,"kb":5860515840,"kb_used":2258790992,"kb_used_data":2253115584,"kb_used_omap":78367,"kb_used_meta":5597024,"kb_avail":3601724848,"utilization":38.542528570317799,"var":0.95517901457474608,"pgs":84,"status":"up"},{"id":100,"device_class":"general","name":"osd.100","type":"osd","type_id":0,"crush_weight":5.4579925537109375,"depth":3,"pool_weights":{},"reweight":1,"kb":5860515840,"kb_used":1952215184,"kb_used_data":1946461500,"kb_used_omap":14505,"kb_used_meta":5739158,"kb_avail":3908300656,"utilization":33.311319981006996,"var":0.82553675054277731,"pgs":76,"status":"up"},{"id":-23,"name":"sf-sby001-hyperconverge013-rack002","type":"host","type_id":1,"pool_weights":{},"reweight":-1,"kb":35163090944,"kb_used":12324067700,"kb_used_data":12291721752,"kb_used_omap":170186,"kb_used_meta":32171568,"kb_avail":22839023244,"utilization":35.048305962712583,"var":0.86858355156696898,"pgs":0,"children":[97,80,39,19,4,3]},{"id":3,"device_class":"general","name":"osd.3","type":"osd","type_id":0,"crush_weight":5.4579925537109375,"depth":3,"pool_weights":{},"reweight":1,"kb":5860515840,"kb_used":2262063364,"kb_used_data":2255390440,"kb_used_omap":37711,"kb_used_meta":6635184,"kb_avail":3598452476,"utilization":38.598366180680777,"var":0.95656280841550079,"pgs":75,"status":"up"},{"id":4,"device_class":"general","name":"osd.4","type":"osd","type_id":0,"crush_weight":5.4579925537109375,"depth":3,"pool_weights":{},"reweight":1,"kb":5860511744,"kb_used":1652954944,"kb_used_data":1648689008,"kb_used_omap":26187,"kb_used_meta":4239732,"kb_avail":4207556800,"utilization":28.204959160644933,"var":0.69898852245862519,"pgs":74,"status":"up"},{"id":19,"device_class":"general","name":"osd.19","type":"osd","type_id":0,"crush_weight":5.4579925537109375,"depth":3,"pool_weights":{},"reweight":0.95001220703125,"kb":5860515840,"kb_used":2518371728,"kb_used_data":2512272576,"kb_used_omap":7191,"kb_used_meta":6091944,"kb_avail":3342144112,"utilization":42.971844062109042,"var":1.064948387878085,"pgs":85,"status":"up"},{"id":39,"device_class":"general","name":"osd.39","type":"osd","type_id":0,"crush_weight":5.4579925537109375,"depth":3,"pool_weights":{},"reweight":1,"kb":5860515840,"kb_used":2219320992,"kb_used_data":2213859152,"kb_used_omap":12958,"kb_used_meta":5448865,"kb_avail":3641194848,"utilization":37.86903836778982,"var":0.93848826459442858,"pgs":84,"status":"up"},{"id":80,"device_class":"general","name":"osd.80","type":"osd","type_id":0,"crush_weight":5.4579925537109375,"depth":3,"pool_weights":{},"reweight":1,"kb":5860515840,"kb_used":1759826704,"kb_used_data":1754697808,"kb_used_omap":71295,"kb_used_meta":5053504,"kb_avail":4100689136,"utilization":30.02852909275645,"var":0.74418108753863998,"pgs":85,"status":"up"},{"id":97,"device_class":"general","name":"osd.97","type":"osd","type_id":0,"crush_weight":5.4579925537109375,"depth":3,"pool_weights":{},"reweight":1,"kb":5860515840,"kb_used":1911529968,"kb_used_data":1906812768,"kb_used_omap":14844,"kb_used_meta":4702339,"kb_avail":3948985872,"utilization":32.617094129379574,"var":0.80833211998409449,"pgs":85,"status":"up"},{"id":-41,"name":"sf-sby001-hyperconverge014-rack002","type":"host","type_id":1,"pool_weights":{},"reweight":-1,"kb":35163090944,"kb_used":11606742208,"kb_used_data":11578112624,"kb_used_omap":502679,"kb_used_meta":28124771,"kb_avail":23556348736,"utilization":33.008310408446896,"var":0.81802742524263172,"pgs":0,"children":[118,110,96,76,54,24]},{"id":24,"device_class":"general","name":"osd.24","type":"osd","type_id":0,"crush_weight":5.4579925537109375,"depth":3,"pool_weights":{},"reweight":1,"kb":5860511744,"kb_used":2367660128,"kb_used_data":2361830272,"kb_used_omap":64412,"kb_used_meta":5765411,"kb_avail":3492851616,"utilization":40.400228366132254,"var":1.0012174019396134,"pgs":92,"status":"up"},{"id":54,"device_class":"general","name":"osd.54","type":"osd","type_id":0,"crush_weight":5.4579925537109375,"depth":3,"pool_weights":{},"reweight":1,"kb":5860515840,"kb_used":2212758048,"kb_used_data":2207372464,"kb_used_omap":131233,"kb_used_meta":5252318,"kb_avail":3647757792,"utilization":37.75705259419621,"var":0.93571298064614317,"pgs":88,"status":"up"},{"id":76,"device_class":"general","name":"osd.76","type":"osd","type_id":0,"crush_weight":5.4579925537109375,"depth":3,"pool_weights":{},"reweight":1,"kb":5860515840,"kb_used":1244559248,"kb_used_data":1241791872,"kb_used_omap":55827,"kb_used_meta":2711532,"kb_avail":4615956592,"utilization":21.236343045188324,"var":0.52628901049049659,"pgs":69,"status":"up"},{"id":96,"device_class":"general","name":"osd.96","type":"osd","type_id":0,"crush_weight":5.4579925537109375,"depth":3,"pool_weights":{},"reweight":1,"kb":5860515840,"kb_used":1858136336,"kb_used_data":1853412672,"kb_used_omap":60984,"kb_used_meta":4662663,"kb_avail":4002379504,"utilization":31.706020199068348,"var":0.78575345866529356,"pgs":72,"status":"up"},{"id":110,"device_class":"general","name":"osd.110","type":"osd","type_id":0,"crush_weight":5.4579925537109375,"depth":3,"pool_weights":{},"reweight":1,"kb":5860515840,"kb_used":2114802624,"kb_used_data":2109595696,"kb_used_omap":74963,"kb_used_meta":5131948,"kb_avail":3745713216,"utilization":36.085605460969113,"var":0.89429039409433198,"pgs":72,"status":"up"},{"id":118,"device_class":"general","name":"osd.118","type":"osd","type_id":0,"crush_weight":5.4579925537109375,"depth":3,"pool_weights":{},"reweight":1,"kb":5860515840,"kb_used":1808825824,"kb_used_data":1804109648,"kb_used_omap":115260,"kb_used_meta":4600899,"kb_avail":4051690016,"utilization":30.864617951446405,"var":0.7649014336540586,"pgs":83,"status":"up"},{"id":-19,"name":"sf-sby001-hyperconverge015-rack002","type":"host","type_id":1,"pool_weights":{},"reweight":-1,"kb":35163090944,"kb_used":12963521852,"kb_used_data":12929467528,"kb_used_omap":148454,"kb_used_meta":33904596,"kb_avail":22199569092,"utilization":36.866843909272461,"var":0.91365141162168162,"pgs":0,"children":[361,360,113,82,61,7]},{"id":7,"device_class":"general","name":"osd.7","type":"osd","type_id":0,"crush_weight":5.4579925537109375,"depth":3,"pool_weights":{},"reweight":1,"kb":5860511744,"kb_used":2016925488,"kb_used_data":2011532304,"kb_used_omap":20846,"kb_used_meta":5371345,"kb_avail":3843586256,"utilization":34.41551823635421,"var":0.85290150943537246,"pgs":89,"status":"up"},{"id":61,"device_class":"general","name":"osd.61","type":"osd","type_id":0,"crush_weight":5.4579925537109375,"depth":3,"pool_weights":{},"reweight":1,"kb":5860515840,"kb_used":2007624528,"kb_used_data":2002421824,"kb_used_omap":10814,"kb_used_meta":5191873,"kb_avail":3852891312,"utilization":34.256788699337427,"var":0.84896779962505253,"pgs":82,"status":"up"},{"id":82,"device_class":"general","name":"osd.82","type":"osd","type_id":0,"crush_weight":5.4579925537109375,"depth":3,"pool_weights":{},"reweight":1,"kb":5860515840,"kb_used":2479088848,"kb_used_data":2473264128,"kb_used_omap":49857,"kb_used_meta":5774846,"kb_avail":3381426992,"utilization":42.301546752580741,"var":1.0483367656691462,"pgs":106,"status":"up"},{"id":113,"device_class":"general","name":"osd.113","type":"osd","type_id":0,"crush_weight":5.4579925537109375,"depth":3,"pool_weights":{},"reweight":1,"kb":5860515840,"kb_used":1664777156,"kb_used_data":1659284820,"kb_used_omap":13786,"kb_used_meta":5478373,"kb_avail":4195738684,"utilization":28.406665922431838,"var":0.70398731400405212,"pgs":83,"status":"up"},{"id":360,"device_class":"general","name":"osd.360","type":"osd","type_id":0,"crush_weight":5.4579925537109375,"depth":3,"pool_weights":{},"reweight":1,"kb":5860515840,"kb_used":1914735872,"kb_used_data":1909715384,"kb_used_omap":16080,"kb_used_meta":5004399,"kb_avail":3945779968,"utilization":32.671797573368558,"var":0.80968780638198912,"pgs":80,"status":"up"},{"id":361,"device_class":"general","name":"osd.361","type":"osd","type_id":0,"crush_weight":5.4579925537109375,"depth":3,"pool_weights":{},"reweight":1,"kb":5860515840,"kb_used":2880369960,"kb_used_data":2873249068,"kb_used_omap":37071,"kb_used_meta":7083760,"kb_avail":2980145880,"utilization":49.148744558294716,"var":1.2180272321554844,"pgs":99,"status":"up"},{"id":-47,"name":"sf-sby001-hyperconverge016-rack002","type":"host","type_id":1,"pool_weights":{},"reweight":-1,"kb":35163090944,"kb_used":13299470632,"kb_used_data":13266691864,"kb_used_omap":408464,"kb_used_meta":32369642,"kb_avail":21863620312,"utilization":37.822245641546296,"var":0.93732862531282268,"pgs":0,"children":[116,104,92,74,53,34]},{"id":34,"device_class":"general","name":"osd.34","type":"osd","type_id":0,"crush_weight":5.4579925537109375,"depth":3,"pool_weights":{},"reweight":1,"kb":5860511744,"kb_used":1808269968,"kb_used_data":1803796992,"kb_used_omap":79628,"kb_used_meta":4393331,"kb_avail":4052241776,"utilization":30.855154754212535,"var":0.76466691226317252,"pgs":82,"status":"up"},{"id":53,"device_class":"general","name":"osd.53","type":"osd","type_id":0,"crush_weight":5.4579925537109375,"depth":3,"pool_weights":{},"reweight":0.95001220703125,"kb":5860515840,"kb_used":2264464784,"kb_used_data":2258406272,"kb_used_omap":52725,"kb_used_meta":6005770,"kb_avail":3596051056,"utilization":38.639342437132633,"var":0.95757830121554477,"pgs":79,"status":"up"},{"id":74,"device_class":"general","name":"osd.74","type":"osd","type_id":0,"crush_weight":5.4579925537109375,"depth":3,"pool_weights":{},"reweight":1,"kb":5860515840,"kb_used":2528259392,"kb_used_data":2522148992,"kb_used_omap":61219,"kb_used_meta":6048668,"kb_avail":3332256448,"utilization":43.140560678017039,"var":1.0691296021601571,"pgs":98,"status":"up"},{"id":92,"device_class":"general","name":"osd.92","type":"osd","type_id":0,"crush_weight":5.4579925537109375,"depth":3,"pool_weights":{},"reweight":1,"kb":5860515840,"kb_used":2162776528,"kb_used_data":2157164080,"kb_used_omap":76317,"kb_used_meta":5536098,"kb_avail":3697739312,"utilization":36.904200705991094,"var":0.91457720527355046,"pgs":93,"status":"up"},{"id":104,"device_class":"general","name":"osd.104","type":"osd","type_id":0,"crush_weight":5.4579925537109375,"depth":3,"pool_weights":{},"reweight":1,"kb":5860515840,"kb_used":2324379240,"kb_used_data":2319413480,"kb_used_omap":67854,"kb_used_meta":4897841,"kb_avail":3536136600,"utilization":39.661683432972346,"var":0.98291443512237864,"pgs":89,"status":"up"},{"id":116,"device_class":"general","name":"osd.116","type":"osd","type_id":0,"crush_weight":5.4579925537109375,"depth":3,"pool_weights":{},"reweight":0.95001220703125,"kb":5860515840,"kb_used":2211320720,"kb_used_data":2205762048,"kb_used_omap":70721,"kb_used_meta":5487934,"kb_avail":3649195120,"utilization":37.732526971550683,"var":0.93510517516634317,"pgs":81,"status":"up"},{"id":-4,"name":"01-03","type":"rack","type_id":3,"pool_weights":{},"reweight":-1,"kb":210978557952,"kb_used":85054196500,"kb_used_data":84850728340,"kb_used_omap":1277716,"kb_used_meta":202167368,"kb_avail":125924361452,"utilization":40.31414250132034,"var":0.99908398167452006,"pgs":0,"children":[-49,-35,-21,-3,-7,-39,-43]},{"id":-43,"name":"sf-sby001-hyperconverge003-rack001","type":"host","type_id":1,"pool_weights":{},"reweight":-1,"kb":35163090944,"kb_used":15047011472,"kb_used_data":15011838048,"kb_used_omap":118869,"kb_used_meta":35052453,"kb_avail":20116079472,"utilization":42.792061414519999,"var":1.0604929300103314,"pgs":0,"children":[114,105,87,67,45,27]},{"id":27,"device_class":"general","name":"osd.27","type":"osd","type_id":0,"crush_weight":5.4579925537109375,"depth":3,"pool_weights":{},"reweight":1,"kb":5860511744,"kb_used":2680244000,"kb_used_data":2674488512,"kb_used_omap":25079,"kb_used_meta":5728712,"kb_avail":3180267744,"utilization":45.733958348330887,"var":1.133400399199626,"pgs":105,"status":"up"},{"id":45,"device_class":"general","name":"osd.45","type":"osd","type_id":0,"crush_weight":5.4579925537109375,"depth":3,"pool_weights":{},"reweight":1,"kb":5860515840,"kb_used":2266470624,"kb_used_data":2261282416,"kb_used_omap":6762,"kb_used_meta":5181397,"kb_avail":3594045216,"utilization":38.673568775816157,"var":0.95842651438860071,"pgs":83,"status":"up"},{"id":67,"device_class":"general","name":"osd.67","type":"osd","type_id":0,"crush_weight":5.4579925537109375,"depth":3,"pool_weights":{},"reweight":1,"kb":5860515840,"kb_used":2525471328,"kb_used_data":2519432464,"kb_used_omap":16890,"kb_used_meta":6021701,"kb_avail":3335044512,"utilization":43.092986981842202,"var":1.0679506085155379,"pgs":85,"status":"up"},{"id":87,"device_class":"general","name":"osd.87","type":"osd","type_id":0,"crush_weight":5.4579925537109375,"depth":3,"pool_weights":{},"reweight":1,"kb":5860515840,"kb_used":2374941408,"kb_used_data":2369067056,"kb_used_omap":18772,"kb_used_meta":5855531,"kb_avail":3485574432,"utilization":40.524443117962804,"var":1.0042957501604026,"pgs":87,"status":"up"},{"id":105,"device_class":"general","name":"osd.105","type":"osd","type_id":0,"crush_weight":5.4579925537109375,"depth":3,"pool_weights":{},"reweight":1,"kb":5860515840,"kb_used":2420218352,"kb_used_data":2414310688,"kb_used_omap":35765,"kb_used_meta":5871882,"kb_avail":3440297488,"utilization":41.297019205735992,"var":1.0234420930075481,"pgs":101,"status":"up"},{"id":114,"device_class":"general","name":"osd.114","type":"osd","type_id":0,"crush_weight":5.4579925537109375,"depth":3,"pool_weights":{},"reweight":1,"kb":5860515840,"kb_used":2779665760,"kb_used_data":2773256912,"kb_used_omap":15601,"kb_used_meta":6393230,"kb_avail":3080850080,"utilization":47.430394113566628,"var":1.1754422657463663,"pgs":110,"status":"up"},{"id":-39,"name":"sf-sby001-hyperconverge012-rack002","type":"host","type_id":1,"pool_weights":{},"reweight":-1,"kb":35163090944,"kb_used":13182719632,"kb_used_data":13150019712,"kb_used_omap":199644,"kb_used_meta":32491870,"kb_avail":21980371312,"utilization":37.490218516325889,"var":0.92910017341710693,"pgs":0,"children":[117,109,95,75,55,25]},{"id":25,"device_class":"general","name":"osd.25","type":"osd","type_id":0,"crush_weight":5.4579925537109375,"depth":3,"pool_weights":{},"reweight":1,"kb":5860511744,"kb_used":2332865632,"kb_used_data":2326479168,"kb_used_omap":16570,"kb_used_meta":6369861,"kb_avail":3527646112,"utilization":39.806517483535309,"var":0.98650378047218368,"pgs":101,"status":"up"},{"id":55,"device_class":"general","name":"osd.55","type":"osd","type_id":0,"crush_weight":5.4579925537109375,"depth":3,"pool_weights":{},"reweight":1,"kb":5860515840,"kb_used":2272545344,"kb_used_data":2266966768,"kb_used_omap":22789,"kb_used_meta":5555706,"kb_avail":3587970496,"utilization":38.777223815165051,"var":0.96099534217477856,"pgs":99,"status":"up"},{"id":75,"device_class":"general","name":"osd.75","type":"osd","type_id":0,"crush_weight":5.4579925537109375,"depth":3,"pool_weights":{},"reweight":1,"kb":5860515840,"kb_used":1660053120,"kb_used_data":1655917168,"kb_used_omap":7965,"kb_used_meta":4127970,"kb_avail":4200462720,"utilization":28.32605806931835,"var":0.70198965239335998,"pgs":93,"status":"up"},{"id":95,"device_class":"general","name":"osd.95","type":"osd","type_id":0,"crush_weight":5.4579925537109375,"depth":3,"pool_weights":{},"reweight":1,"kb":5860515840,"kb_used":1708134800,"kb_used_data":1704067904,"kb_used_omap":118626,"kb_used_meta":3948253,"kb_avail":4152381040,"utilization":29.146492333343819,"var":0.72232203900378888,"pgs":79,"status":"up"},{"id":109,"device_class":"general","name":"osd.109","type":"osd","type_id":0,"crush_weight":5.4579925537109375,"depth":3,"pool_weights":{},"reweight":1,"kb":5860515840,"kb_used":2633332240,"kb_used_data":2627322304,"kb_used_omap":25040,"kb_used_meta":5984879,"kb_avail":3227183600,"utilization":44.933454868027454,"var":1.1135619466163997,"pgs":97,"status":"up"},{"id":117,"device_class":"general","name":"osd.117","type":"osd","type_id":0,"crush_weight":5.4579925537109375,"depth":3,"pool_weights":{},"reweight":1,"kb":5860515840,"kb_used":2575788496,"kb_used_data":2569266400,"kb_used_omap":8654,"kb_used_meta":6505201,"kb_avail":3284727344,"utilization":43.951566147460497,"var":1.0892283199623489,"pgs":93,"status":"up"},{"id":-7,"name":"sf-sby001-hyperconverge017-rack003","type":"host","type_id":1,"pool_weights":{},"reweight":-1,"kb":0,"kb_used":0,"kb_used_data":0,"kb_used_omap":0,"kb_used_meta":0,"kb_avail":0,"utilization":0,"var":0,"pgs":0,"children":[66,47,28,13]},{"id":13,"device_class":"general","name":"osd.13","type":"osd","type_id":0,"crush_weight":5.4579925537109375,"depth":3,"pool_weights":{},"reweight":0,"kb":0,"kb_used":0,"kb_used_data":0,"kb_used_omap":0,"kb_used_meta":0,"kb_avail":0,"utilization":0,"var":0,"pgs":0,"status":"down"},{"id":28,"device_class":"general","name":"osd.28","type":"osd","type_id":0,"crush_weight":5.4579925537109375,"depth":3,"pool_weights":{},"reweight":0,"kb":0,"kb_used":0,"kb_used_data":0,"kb_used_omap":0,"kb_used_meta":0,"kb_avail":0,"utilization":0,"var":0,"pgs":0,"status":"down"},{"id":47,"device_class":"general","name":"osd.47","type":"osd","type_id":0,"crush_weight":5.4579925537109375,"depth":3,"pool_weights":{},"reweight":0,"kb":0,"kb_used":0,"kb_used_data":0,"kb_used_omap":0,"kb_used_meta":0,"kb_avail":0,"utilization":0,"var":0,"pgs":0,"status":"down"},{"id":66,"device_class":"general","name":"osd.66","type":"osd","type_id":0,"crush_weight":5.4579925537109375,"depth":3,"pool_weights":{},"reweight":0,"kb":0,"kb_used":0,"kb_used_data":0,"kb_used_omap":0,"kb_used_meta":0,"kb_avail":0,"utilization":0,"var":0,"pgs":0,"status":"down"},{"id":-3,"name":"sf-sby001-hyperconverge018-rack003","type":"host","type_id":1,"pool_weights":{},"reweight":-1,"kb":35163090944,"kb_used":14584127680,"kb_used_data":14548844896,"kb_used_omap":471884,"kb_used_meta":34810606,"kb_avail":20578963264,"utilization":41.475670336337544,"var":1.0278695090907801,"pgs":0,"children":[122,68,48,30,14,1]},{"id":1,"device_class":"general","name":"osd.1","type":"osd","type_id":0,"crush_weight":5.4579925537109375,"depth":3,"pool_weights":{},"reweight":1,"kb":5860515840,"kb_used":2837600608,"kb_used_data":2830644528,"kb_used_omap":73319,"kb_used_meta":6882584,"kb_avail":3022915232,"utilization":48.418956376372492,"var":1.1999412792532247,"pgs":118,"status":"up"},{"id":14,"device_class":"general","name":"osd.14","type":"osd","type_id":0,"crush_weight":5.4579925537109375,"depth":3,"pool_weights":{},"reweight":1,"kb":5860515840,"kb_used":1910686112,"kb_used_data":1905848272,"kb_used_omap":79833,"kb_used_meta":4757990,"kb_avail":3949829728,"utilization":32.602695123847667,"var":0.80797527707770012,"pgs":86,"status":"up"},{"id":30,"device_class":"general","name":"osd.30","type":"osd","type_id":0,"crush_weight":5.4579925537109375,"depth":3,"pool_weights":{},"reweight":1,"kb":5860515840,"kb_used":2318188192,"kb_used_data":2312456336,"kb_used_omap":45344,"kb_used_meta":5686495,"kb_avail":3542327648,"utilization":39.556043448898862,"var":0.98029641550534941,"pgs":83,"status":"up"},{"id":48,"device_class":"general","name":"osd.48","type":"osd","type_id":0,"crush_weight":5.4579925537109375,"depth":3,"pool_weights":{},"reweight":1,"kb":5860515840,"kb_used":1802195424,"kb_used_data":1797756304,"kb_used_omap":109373,"kb_used_meta":4329730,"kb_avail":4058320416,"utilization":30.751481152894556,"var":0.76209762446557372,"pgs":95,"status":"up"},{"id":68,"device_class":"general","name":"osd.68","type":"osd","type_id":0,"crush_weight":5.4579925537109375,"depth":3,"pool_weights":{},"reweight":1,"kb":5860515840,"kb_used":3091200816,"kb_used_data":3084254864,"kb_used_omap":58812,"kb_used_meta":6887107,"kb_avail":2769315024,"utilization":52.746224059348329,"var":1.3071816559110534,"pgs":96,"status":"up"},{"id":122,"device_class":"general","name":"osd.122","type":"osd","type_id":0,"crush_weight":5.4579925537109375,"depth":3,"pool_weights":{},"reweight":1,"kb":5860511744,"kb_used":2624256528,"kb_used_data":2617884592,"kb_used_omap":105203,"kb_used_meta":6266700,"kb_avail":3236255216,"utilization":44.778624165145942,"var":1.1097248595416775,"pgs":90,"status":"up"},{"id":-21,"name":"sf-sby001-hyperconverge019-rack003","type":"host","type_id":1,"pool_weights":{},"reweight":-1,"kb":35163095040,"kb_used":13037811680,"kb_used_data":13006409184,"kb_used_omap":276575,"kb_used_meta":31125275,"kb_avail":22125283360,"utilization":37.078111767945217,"var":0.91888715075307237,"pgs":0,"children":[102,83,73,62,18,5]},{"id":5,"device_class":"general","name":"osd.5","type":"osd","type_id":0,"crush_weight":5.4579925537109375,"depth":3,"pool_weights":{},"reweight":1,"kb":5860515840,"kb_used":2061199632,"kb_used_data":2056529984,"kb_used_omap":22358,"kb_used_meta":4647273,"kb_avail":3799316208,"utilization":35.170959148879291,"var":0.87162320033530094,"pgs":86,"status":"up"},{"id":18,"device_class":"general","name":"osd.18","type":"osd","type_id":0,"crush_weight":5.4579925537109375,"depth":3,"pool_weights":{},"reweight":1,"kb":5860515840,"kb_used":2161107296,"kb_used_data":2155974928,"kb_used_omap":77001,"kb_used_meta":5055350,"kb_avail":3699408544,"utilization":36.875718025531349,"var":0.91387133413164146,"pgs":85,"status":"up"},{"id":62,"device_class":"general","name":"osd.62","type":"osd","type_id":0,"crush_weight":5.4579925537109375,"depth":3,"pool_weights":{},"reweight":1,"kb":5860515840,"kb_used":1952828608,"kb_used_data":1947770448,"kb_used_omap":50717,"kb_used_meta":5006882,"kb_avail":3907687232,"utilization":33.321787045967611,"var":0.82579615025435382,"pgs":90,"status":"up"},{"id":73,"device_class":"general","name":"osd.73","type":"osd","type_id":0,"crush_weight":5.4579925537109375,"depth":3,"pool_weights":{},"reweight":1,"kb":5860515840,"kb_used":1964051008,"kb_used_data":1959057328,"kb_used_omap":12880,"kb_used_meta":4980783,"kb_avail":3896464832,"utilization":33.513278721894899,"var":0.83054178675243129,"pgs":70,"status":"up"},{"id":83,"device_class":"general","name":"osd.83","type":"osd","type_id":0,"crush_weight":5.4579925537109375,"depth":3,"pool_weights":{},"reweight":1,"kb":5860515840,"kb_used":1765701600,"kb_used_data":1761224208,"kb_used_omap":53737,"kb_used_meta":4423638,"kb_avail":4094814240,"utilization":30.128774466378715,"var":0.74666541539008069,"pgs":91,"status":"up"},{"id":102,"device_class":"general","name":"osd.102","type":"osd","type_id":0,"crush_weight":5.4579925537109375,"depth":3,"pool_weights":{},"reweight":1,"kb":5860515840,"kb_used":3132923536,"kb_used_data":3125852288,"kb_used_omap":59882,"kb_used_meta":7011349,"kb_avail":2727592304,"utilization":53.458153199019421,"var":1.3248250176546255,"pgs":108,"status":"up"},{"id":-35,"name":"sf-sby001-hyperconverge020-rack003","type":"host","type_id":1,"pool_weights":{},"reweight":-1,"kb":35163095040,"kb_used":14411306036,"kb_used_data":14379154024,"kb_used_omap":109960,"kb_used_meta":32038642,"kb_avail":20751789004,"utilization":40.984179633807344,"var":1.0156891560540313,"pgs":0,"children":[115,112,107,106,42,36]},{"id":36,"device_class":"general","name":"osd.36","type":"osd","type_id":0,"crush_weight":5.4579925537109375,"depth":3,"pool_weights":{},"reweight":1,"kb":5860515840,"kb_used":2428420596,"kb_used_data":2421089728,"kb_used_omap":32969,"kb_used_meta":7297846,"kb_avail":3432095244,"utilization":41.436976919765478,"var":1.0269105906989988,"pgs":98,"status":"up"},{"id":42,"device_class":"general","name":"osd.42","type":"osd","type_id":0,"crush_weight":5.4579925537109375,"depth":3,"pool_weights":{},"reweight":1,"kb":5860515840,"kb_used":2214802940,"kb_used_data":2210347568,"kb_used_omap":17254,"kb_used_meta":4438105,"kb_avail":3645712900,"utilization":37.791945290604318,"var":0.93657770780876681,"pgs":93,"status":"up"},{"id":106,"device_class":"general","name":"osd.106","type":"osd","type_id":0,"crush_weight":5.4579925537109375,"depth":3,"pool_weights":{},"reweight":1,"kb":5860515840,"kb_used":2420091152,"kb_used_data":2413170556,"kb_used_omap":30597,"kb_used_meta":6889978,"kb_avail":3440424688,"utilization":41.29484874833134,"var":1.0233883037144775,"pgs":94,"status":"up"},{"id":107,"device_class":"general","name":"osd.107","type":"osd","type_id":0,"crush_weight":5.4579925537109375,"depth":3,"pool_weights":{},"reweight":1,"kb":5860515840,"kb_used":2534293704,"kb_used_data":2529376000,"kb_used_omap":12721,"kb_used_meta":4904910,"kb_avail":3326222136,"utilization":43.243526221746379,"var":1.0716813425426053,"pgs":98,"status":"up"},{"id":112,"device_class":"general","name":"osd.112","type":"osd","type_id":0,"crush_weight":5.4579925537109375,"depth":3,"pool_weights":{},"reweight":1,"kb":5860515840,"kb_used":2634816916,"kb_used_data":2630183116,"kb_used_omap":5859,"kb_used_meta":4627932,"kb_avail":3225698924,"utilization":44.95878840590251,"var":1.1141897742302276,"pgs":103,"status":"up"},{"id":115,"device_class":"general","name":"osd.115","type":"osd","type_id":0,"crush_weight":5.4579925537109375,"depth":3,"pool_weights":{},"reweight":1,"kb":5860515840,"kb_used":2178880728,"kb_used_data":2174987056,"kb_used_omap":10560,"kb_used_meta":3879871,"kb_avail":3681635112,"utilization":37.178992216494038,"var":0.92138721732911244,"pgs":100,"status":"up"},{"id":-49,"name":"sf-sby001-hyperconverge021-rack003","type":"host","type_id":1,"pool_weights":{},"reweight":-1,"kb":35163095040,"kb_used":14791220000,"kb_used_data":14754462476,"kb_used_omap":100784,"kb_used_meta":36648522,"kb_avail":20371875040,"utilization":42.064613433982856,"var":1.0424649730760536,"pgs":0,"children":[101,86,77,63,57,43]},{"id":43,"device_class":"general","name":"osd.43","type":"osd","type_id":0,"crush_weight":5.4579925537109375,"depth":3,"pool_weights":{},"reweight":1,"kb":5860515840,"kb_used":2524259720,"kb_used_data":2517833316,"kb_used_omap":14449,"kb_used_meta":6404174,"kb_avail":3336256120,"utilization":43.072312897289258,"var":1.06743825365863,"pgs":94,"status":"up"},{"id":57,"device_class":"general","name":"osd.57","type":"osd","type_id":0,"crush_weight":5.4579925537109375,"depth":3,"pool_weights":{},"reweight":1,"kb":5860515840,"kb_used":2435048796,"kb_used_data":2428089588,"kb_used_omap":19722,"kb_used_meta":6939445,"kb_avail":3425467044,"utilization":41.550076178959699,"var":1.0297134695695218,"pgs":101,"status":"up"},{"id":63,"device_class":"general","name":"osd.63","type":"osd","type_id":0,"crush_weight":5.4579925537109375,"depth":3,"pool_weights":{},"reweight":1,"kb":5860515840,"kb_used":2465520148,"kb_used_data":2461187596,"kb_used_omap":7459,"kb_used_meta":4325084,"kb_avail":3394995692,"utilization":42.070019351743618,"var":1.0425989450646889,"pgs":91,"status":"up"},{"id":77,"device_class":"general","name":"osd.77","type":"osd","type_id":0,"crush_weight":5.4579925537109375,"depth":3,"pool_weights":{},"reweight":1,"kb":5860515840,"kb_used":2324110280,"kb_used_data":2318021700,"kb_used_omap":14790,"kb_used_meta":6073465,"kb_avail":3536405560,"utilization":39.657094075868926,"var":0.98280069952281679,"pgs":90,"status":"up"},{"id":86,"device_class":"general","name":"osd.86","type":"osd","type_id":0,"crush_weight":5.4579925537109375,"depth":3,"pool_weights":{},"reweight":1,"kb":5860515840,"kb_used":2777214988,"kb_used_data":2769955320,"kb_used_omap":14004,"kb_used_meta":7245643,"kb_avail":3083300852,"utilization":47.388575746943125,"var":1.1744059033772061,"pgs":97,"status":"up"},{"id":101,"device_class":"general","name":"osd.101","type":"osd","type_id":0,"crush_weight":5.4579925537109375,"depth":3,"pool_weights":{},"reweight":1,"kb":5860515840,"kb_used":2265066068,"kb_used_data":2259374956,"kb_used_omap":30360,"kb_used_meta":5660711,"kb_avail":3595449772,"utilization":38.649602353092526,"var":0.95783256726345889,"pgs":78,"status":"up"},{"id":-83,"name":"default-rack","type":"rack","type_id":3,"pool_weights":{},"reweight":-1,"kb":105489285120,"kb_used":55929923644,"kb_used_data":55783995860,"kb_used_omap":356351,"kb_used_meta":145570223,"kb_avail":49559361476,"utilization":53.019530448402001,"var":1.3139548629905264,"pgs":0,"children":[-485,-481,-82,-477,-385,-393,-401,-413,-421,-425,-433,-437,-445,-453,-461,-465,-469,-473,-457,-449,-441,-429,-417,-409,-405,-397,-389,-381,-377,-373,-369,-365,-361,-357,-353,-349,-345,-341,-337,-333,-321,-317,-313,-329,-325,-301,-297,-293,-289,-285,-281,-277,-273,-269,-229,-257,-253,-249,-245,-241,-237,-233]},{"id":-233,"name":"sf-sby001-hc0062-rack004","type":"host","type_id":1,"pool_weights":{},"reweight":-1,"kb":0,"kb_used":0,"kb_used_data":0,"kb_used_omap":0,"kb_used_meta":0,"kb_avail":0,"utilization":0,"var":0,"pgs":0,"children":[363,362]},{"id":-237,"name":"sf-sby001-hc0063-rack004","type":"host","type_id":1,"pool_weights":{},"reweight":-1,"kb":0,"kb_used":0,"kb_used_data":0,"kb_used_omap":0,"kb_used_meta":0,"kb_avail":0,"utilization":0,"var":0,"pgs":0,"children":[365,364]},{"id":-241,"name":"sf-sby001-hc0064-rack004","type":"host","type_id":1,"pool_weights":{},"reweight":-1,"kb":0,"kb_used":0,"kb_used_data":0,"kb_used_omap":0,"kb_used_meta":0,"kb_avail":0,"utilization":0,"var":0,"pgs":0,"children":[367,366]},{"id":-245,"name":"sf-sby001-hc0065-rack004","type":"host","type_id":1,"pool_weights":{},"reweight":-1,"kb":0,"kb_used":0,"kb_used_data":0,"kb_used_omap":0,"kb_used_meta":0,"kb_avail":0,"utilization":0,"var":0,"pgs":0,"children":[369,368]},{"id":-249,"name":"sf-sby001-hc0066-rack004","type":"host","type_id":1,"pool_weights":{},"reweight":-1,"kb":0,"kb_used":0,"kb_used_data":0,"kb_used_omap":0,"kb_used_meta":0,"kb_avail":0,"utilization":0,"var":0,"pgs":0,"children":[371,370]},{"id":-253,"name":"sf-sby001-hc0067-rack004","type":"host","type_id":1,"pool_weights":{},"reweight":-1,"kb":0,"kb_used":0,"kb_used_data":0,"kb_used_omap":0,"kb_used_meta":0,"kb_avail":0,"utilization":0,"var":0,"pgs":0,"children":[373,372]},{"id":-257,"name":"sf-sby001-hc0068-rack004","type":"host","type_id":1,"pool_weights":{},"reweight":-1,"kb":0,"kb_used":0,"kb_used_data":0,"kb_used_omap":0,"kb_used_meta":0,"kb_avail":0,"utilization":0,"var":0,"pgs":0,"children":[375,374]},{"id":-229,"name":"sf-sby001-hc0069-rack004","type":"host","type_id":1,"pool_weights":{},"reweight":-1,"kb":0,"kb_used":0,"kb_used_data":0,"kb_used_omap":0,"kb_used_meta":0,"kb_avail":0,"utilization":0,"var":0,"pgs":0,"children":[382,381,380,379,378,377,376,91]},{"id":-269,"name":"sf-sby001-hc0072-rack006","type":"host","type_id":1,"pool_weights":{},"reweight":-1,"kb":0,"kb_used":0,"kb_used_data":0,"kb_used_omap":0,"kb_used_meta":0,"kb_avail":0,"utilization":0,"var":0,"pgs":0,"children":[406,405,404,403,402,401,400,399]},{"id":-273,"name":"sf-sby001-hc0073-rack006","type":"host","type_id":1,"pool_weights":{},"reweight":-1,"kb":0,"kb_used":0,"kb_used_data":0,"kb_used_omap":0,"kb_used_meta":0,"kb_avail":0,"utilization":0,"var":0,"pgs":0,"children":[414,413,412,411,410,409,408,407]},{"id":-277,"name":"sf-sby001-hc0074-rack006","type":"host","type_id":1,"pool_weights":{},"reweight":-1,"kb":0,"kb_used":0,"kb_used_data":0,"kb_used_omap":0,"kb_used_meta":0,"kb_avail":0,"utilization":0,"var":0,"pgs":0,"children":[422,421,420,419,418,417,416,415]},{"id":-281,"name":"sf-sby001-hc0075-rack006","type":"host","type_id":1,"pool_weights":{},"reweight":-1,"kb":0,"kb_used":0,"kb_used_data":0,"kb_used_omap":0,"kb_used_meta":0,"kb_avail":0,"utilization":0,"var":0,"pgs":0,"children":[430,429,428,427,426,425,424,423]},{"id":-285,"name":"sf-sby001-hc0076-rack006","type":"host","type_id":1,"pool_weights":{},"reweight":-1,"kb":0,"kb_used":0,"kb_used_data":0,"kb_used_omap":0,"kb_used_meta":0,"kb_avail":0,"utilization":0,"var":0,"pgs":0,"children":[438,437,436,435,434,433,432,431]},{"id":-289,"name":"sf-sby001-hc0077-rack006","type":"host","type_id":1,"pool_weights":{},"reweight":-1,"kb":0,"kb_used":0,"kb_used_data":0,"kb_used_omap":0,"kb_used_meta":0,"kb_avail":0,"utilization":0,"var":0,"pgs":0,"children":[446,445,444,443,442,441,440,439]},{"id":-293,"name":"sf-sby001-hc0078-rack006","type":"host","type_id":1,"pool_weights":{},"reweight":-1,"kb":0,"kb_used":0,"kb_used_data":0,"kb_used_omap":0,"kb_used_meta":0,"kb_avail":0,"utilization":0,"var":0,"pgs":0,"children":[454,453,452,451,450,449,448,447]},{"id":-297,"name":"sf-sby001-hc0079-rack006","type":"host","type_id":1,"pool_weights":{},"reweight":-1,"kb":0,"kb_used":0,"kb_used_data":0,"kb_used_omap":0,"kb_used_meta":0,"kb_avail":0,"utilization":0,"var":0,"pgs":0,"children":[462,461,460,459,458,457,456,455]},{"id":-301,"name":"sf-sby001-hc0080-rack006","type":"host","type_id":1,"pool_weights":{},"reweight":-1,"kb":0,"kb_used":0,"kb_used_data":0,"kb_used_omap":0,"kb_used_meta":0,"kb_avail":0,"utilization":0,"var":0,"pgs":0,"children":[470,469,468,467,466,465,464,463]},{"id":-325,"name":"sf-sby001-hc0083-rack010","type":"host","type_id":1,"pool_weights":{},"reweight":-1,"kb":0,"kb_used":0,"kb_used_data":0,"kb_used_omap":0,"kb_used_meta":0,"kb_avail":0,"utilization":0,"var":0,"pgs":0,"children":[548,547,546,545,544,543,542,541,540,539,538,537,536,535,534,533,532,531,530,529]},{"id":-329,"name":"sf-sby001-hc0084-rack010","type":"host","type_id":1,"pool_weights":{},"reweight":-1,"kb":0,"kb_used":0,"kb_used_data":0,"kb_used_omap":0,"kb_used_meta":0,"kb_avail":0,"utilization":0,"var":0,"pgs":0,"children":[568,567,566,565,564,563,562,561,560,559,558,557,556,555,554,553,552,551,550,549]},{"id":-313,"name":"sf-sby001-hc0085-rack010","type":"host","type_id":1,"pool_weights":{},"reweight":-1,"kb":0,"kb_used":0,"kb_used_data":0,"kb_used_omap":0,"kb_used_meta":0,"kb_avail":0,"utilization":0,"var":0,"pgs":0,"children":[500,499,498,497,496,495,494,493,492,491,490,489,488,487]},{"id":-317,"name":"sf-sby001-hc0086-rack010","type":"host","type_id":1,"pool_weights":{},"reweight":-1,"kb":0,"kb_used":0,"kb_used_data":0,"kb_used_omap":0,"kb_used_meta":0,"kb_avail":0,"utilization":0,"var":0,"pgs":0,"children":[514,513,512,511,510,509,508,507,506,505,504,503,502,501]},{"id":-321,"name":"sf-sby001-hc0087-rack010","type":"host","type_id":1,"pool_weights":{},"reweight":-1,"kb":0,"kb_used":0,"kb_used_data":0,"kb_used_omap":0,"kb_used_meta":0,"kb_avail":0,"utilization":0,"var":0,"pgs":0,"children":[528,527,526,525,524,523,522,521,520,519,518,517,516,515]},{"id":-333,"name":"sf-sby001-hc0088-rack010","type":"host","type_id":1,"pool_weights":{},"reweight":-1,"kb":0,"kb_used":0,"kb_used_data":0,"kb_used_omap":0,"kb_used_meta":0,"kb_avail":0,"utilization":0,"var":0,"pgs":0,"children":[570,569]},{"id":-337,"name":"sf-sby001-hc0089-rack010","type":"host","type_id":1,"pool_weights":{},"reweight":-1,"kb":0,"kb_used":0,"kb_used_data":0,"kb_used_omap":0,"kb_used_meta":0,"kb_avail":0,"utilization":0,"var":0,"pgs":0,"children":[572,571]},{"id":-341,"name":"sf-sby001-hc0090-rack010","type":"host","type_id":1,"pool_weights":{},"reweight":-1,"kb":0,"kb_used":0,"kb_used_data":0,"kb_used_omap":0,"kb_used_meta":0,"kb_avail":0,"utilization":0,"var":0,"pgs":0,"children":[574,573]},{"id":-345,"name":"sf-sby001-hc0091-rack011","type":"host","type_id":1,"pool_weights":{},"reweight":-1,"kb":0,"kb_used":0,"kb_used_data":0,"kb_used_omap":0,"kb_used_meta":0,"kb_avail":0,"utilization":0,"var":0,"pgs":0,"children":[582,581,580,579,578,577,576,575]},{"id":-349,"name":"sf-sby001-hc0092-rack011","type":"host","type_id":1,"pool_weights":{},"reweight":-1,"kb":0,"kb_used":0,"kb_used_data":0,"kb_used_omap":0,"kb_used_meta":0,"kb_avail":0,"utilization":0,"var":0,"pgs":0,"children":[590,589,588,587,586,585,584,583]},{"id":-353,"name":"sf-sby001-hc0093-rack011","type":"host","type_id":1,"pool_weights":{},"reweight":-1,"kb":0,"kb_used":0,"kb_used_data":0,"kb_used_omap":0,"kb_used_meta":0,"kb_avail":0,"utilization":0,"var":0,"pgs":0,"children":[598,597,596,595,594,593,592,591]},{"id":-357,"name":"sf-sby001-hc0094-rack011","type":"host","type_id":1,"pool_weights":{},"reweight":-1,"kb":0,"kb_used":0,"kb_used_data":0,"kb_used_omap":0,"kb_used_meta":0,"kb_avail":0,"utilization":0,"var":0,"pgs":0,"children":[606,605,604,603,602,601,600,599]},{"id":-361,"name":"sf-sby001-hc0095-rack011","type":"host","type_id":1,"pool_weights":{},"reweight":-1,"kb":0,"kb_used":0,"kb_used_data":0,"kb_used_omap":0,"kb_used_meta":0,"kb_avail":0,"utilization":0,"var":0,"pgs":0,"children":[614,613,612,611,610,609,608,607]},{"id":-365,"name":"sf-sby001-hc0096-rack011","type":"host","type_id":1,"pool_weights":{},"reweight":-1,"kb":0,"kb_used":0,"kb_used_data":0,"kb_used_omap":0,"kb_used_meta":0,"kb_avail":0,"utilization":0,"var":0,"pgs":0,"children":[622,621,620,619,618,617,616,615]},{"id":-369,"name":"sf-sby001-hc0097-rack011","type":"host","type_id":1,"pool_weights":{},"reweight":-1,"kb":0,"kb_used":0,"kb_used_data":0,"kb_used_omap":0,"kb_used_meta":0,"kb_avail":0,"utilization":0,"var":0,"pgs":0,"children":[630,629,628,627,626,625,624,623]},{"id":-373,"name":"sf-sby001-hc0098-rack011","type":"host","type_id":1,"pool_weights":{},"reweight":-1,"kb":0,"kb_used":0,"kb_used_data":0,"kb_used_omap":0,"kb_used_meta":0,"kb_avail":0,"utilization":0,"var":0,"pgs":0,"children":[638,637,636,635,634,633,632,631]},{"id":-377,"name":"sf-sby001-hc0099-rack011","type":"host","type_id":1,"pool_weights":{},"reweight":-1,"kb":0,"kb_used":0,"kb_used_data":0,"kb_used_omap":0,"kb_used_meta":0,"kb_avail":0,"utilization":0,"var":0,"pgs":0,"children":[646,645,644,643,642,641,640,639]},{"id":-381,"name":"sf-sby001-hc0100-rack011","type":"host","type_id":1,"pool_weights":{},"reweight":-1,"kb":0,"kb_used":0,"kb_used_data":0,"kb_used_omap":0,"kb_used_meta":0,"kb_avail":0,"utilization":0,"var":0,"pgs":0,"children":[654,653,652,651,650,649,648,647]},{"id":-389,"name":"sf-sby001-hc0101-rack011","type":"host","type_id":1,"pool_weights":{},"reweight":-1,"kb":0,"kb_used":0,"kb_used_data":0,"kb_used_omap":0,"kb_used_meta":0,"kb_avail":0,"utilization":0,"var":0,"pgs":0,"children":[670,669,668,667,666,665,664,663]},{"id":-397,"name":"sf-sby001-hc0102-rack011","type":"host","type_id":1,"pool_weights":{},"reweight":-1,"kb":0,"kb_used":0,"kb_used_data":0,"kb_used_omap":0,"kb_used_meta":0,"kb_avail":0,"utilization":0,"var":0,"pgs":0,"children":[686,685,684,683,682,681,680,679]},{"id":-405,"name":"sf-sby001-hc0103-rack012","type":"host","type_id":1,"pool_weights":{},"reweight":-1,"kb":0,"kb_used":0,"kb_used_data":0,"kb_used_omap":0,"kb_used_meta":0,"kb_avail":0,"utilization":0,"var":0,"pgs":0,"children":[702,701,700,699,698,697,696,695]},{"id":-409,"name":"sf-sby001-hc0104-rack012","type":"host","type_id":1,"pool_weights":{},"reweight":-1,"kb":0,"kb_used":0,"kb_used_data":0,"kb_used_omap":0,"kb_used_meta":0,"kb_avail":0,"utilization":0,"var":0,"pgs":0,"children":[713,711,709,707,706,705,704,703]},{"id":-417,"name":"sf-sby001-hc0105-rack012","type":"host","type_id":1,"pool_weights":{},"reweight":-1,"kb":0,"kb_used":0,"kb_used_data":0,"kb_used_omap":0,"kb_used_meta":0,"kb_avail":0,"utilization":0,"var":0,"pgs":0,"children":[726,725,724,723,722,721,719,717]},{"id":-429,"name":"sf-sby001-hc0106-rack012","type":"host","type_id":1,"pool_weights":{},"reweight":-1,"kb":0,"kb_used":0,"kb_used_data":0,"kb_used_omap":0,"kb_used_meta":0,"kb_avail":0,"utilization":0,"var":0,"pgs":0,"children":[760,759,756,755,753,750,748,741]},{"id":-441,"name":"sf-sby001-hc0107-rack012","type":"host","type_id":1,"pool_weights":{},"reweight":-1,"kb":0,"kb_used":0,"kb_used_data":0,"kb_used_omap":0,"kb_used_meta":0,"kb_avail":0,"utilization":0,"var":0,"pgs":0,"children":[774,773,772,769,768,766,764,762]},{"id":-449,"name":"sf-sby001-hc0108-rack012","type":"host","type_id":1,"pool_weights":{},"reweight":-1,"kb":0,"kb_used":0,"kb_used_data":0,"kb_used_omap":0,"kb_used_meta":0,"kb_avail":0,"utilization":0,"var":0,"pgs":0,"children":[790,788,787,786,783,781,779,778]},{"id":-457,"name":"sf-sby001-hc0109-rack012","type":"host","type_id":1,"pool_weights":{},"reweight":-1,"kb":0,"kb_used":0,"kb_used_data":0,"kb_used_omap":0,"kb_used_meta":0,"kb_avail":0,"utilization":0,"var":0,"pgs":0,"children":[812,809,807,805,802,801,798,796]},{"id":-473,"name":"sf-sby001-hc0110-rack012","type":"host","type_id":1,"pool_weights":{},"reweight":-1,"kb":0,"kb_used":0,"kb_used_data":0,"kb_used_omap":0,"kb_used_meta":0,"kb_avail":0,"utilization":0,"var":0,"pgs":0,"children":[838,837,836,835,834,833,832,831]},{"id":-469,"name":"sf-sby001-hc0111-rack012","type":"host","type_id":1,"pool_weights":{},"reweight":-1,"kb":0,"kb_used":0,"kb_used_data":0,"kb_used_omap":0,"kb_used_meta":0,"kb_avail":0,"utilization":0,"var":0,"pgs":0,"children":[830,829,827,826,825,822,821,820]},{"id":-465,"name":"sf-sby001-hc0112-rack012","type":"host","type_id":1,"pool_weights":{},"reweight":-1,"kb":0,"kb_used":0,"kb_used_data":0,"kb_used_omap":0,"kb_used_meta":0,"kb_avail":0,"utilization":0,"var":0,"pgs":0,"children":[828,824,823,819,818,817,816,815]},{"id":-461,"name":"sf-sby001-hc0113-rack012","type":"host","type_id":1,"pool_weights":{},"reweight":-1,"kb":0,"kb_used":0,"kb_used_data":0,"kb_used_omap":0,"kb_used_meta":0,"kb_avail":0,"utilization":0,"var":0,"pgs":0,"children":[814,813,811,810,808,806,804,803]},{"id":-453,"name":"sf-sby001-hc0114-rack013","type":"host","type_id":1,"pool_weights":{},"reweight":-1,"kb":0,"kb_used":0,"kb_used_data":0,"kb_used_omap":0,"kb_used_meta":0,"kb_avail":0,"utilization":0,"var":0,"pgs":0,"children":[800,799,797,795,794,793,792,791]},{"id":-445,"name":"sf-sby001-hc0115-rack013","type":"host","type_id":1,"pool_weights":{},"reweight":-1,"kb":0,"kb_used":0,"kb_used_data":0,"kb_used_omap":0,"kb_used_meta":0,"kb_avail":0,"utilization":0,"var":0,"pgs":0,"children":[789,785,784,782,780,777,776,775]},{"id":-437,"name":"sf-sby001-hc0116-rack013","type":"host","type_id":1,"pool_weights":{},"reweight":-1,"kb":0,"kb_used":0,"kb_used_data":0,"kb_used_omap":0,"kb_used_meta":0,"kb_avail":0,"utilization":0,"var":0,"pgs":0,"children":[771,770,767,765,763,761,758,757]},{"id":-433,"name":"sf-sby001-hc0117-rack013","type":"host","type_id":1,"pool_weights":{},"reweight":-1,"kb":0,"kb_used":0,"kb_used_data":0,"kb_used_omap":0,"kb_used_meta":0,"kb_avail":0,"utilization":0,"var":0,"pgs":0,"children":[754,752,751,749,747,746,744,742]},{"id":-425,"name":"sf-sby001-hc0118-rack013","type":"host","type_id":1,"pool_weights":{},"reweight":-1,"kb":0,"kb_used":0,"kb_used_data":0,"kb_used_omap":0,"kb_used_meta":0,"kb_avail":0,"utilization":0,"var":0,"pgs":0,"children":[745,743,740,739,738,737,736,735]},{"id":-421,"name":"sf-sby001-hc0119-rack013","type":"host","type_id":1,"pool_weights":{},"reweight":-1,"kb":0,"kb_used":0,"kb_used_data":0,"kb_used_omap":0,"kb_used_meta":0,"kb_avail":0,"utilization":0,"var":0,"pgs":0,"children":[734,733,732,731,730,729,728,727]},{"id":-413,"name":"sf-sby001-hc0120-rack013","type":"host","type_id":1,"pool_weights":{},"reweight":-1,"kb":0,"kb_used":0,"kb_used_data":0,"kb_used_omap":0,"kb_used_meta":0,"kb_avail":0,"utilization":0,"var":0,"pgs":0,"children":[720,718,716,715,714,712,710,708]},{"id":-401,"name":"sf-sby001-hc0121-rack013","type":"host","type_id":1,"pool_weights":{},"reweight":-1,"kb":0,"kb_used":0,"kb_used_data":0,"kb_used_omap":0,"kb_used_meta":0,"kb_avail":0,"utilization":0,"var":0,"pgs":0,"children":[694,693,692,691,690,689,688,687]},{"id":-393,"name":"sf-sby001-hc0122-rack013","type":"host","type_id":1,"pool_weights":{},"reweight":-1,"kb":0,"kb_used":0,"kb_used_data":0,"kb_used_omap":0,"kb_used_meta":0,"kb_avail":0,"utilization":0,"var":0,"pgs":0,"children":[678,677,676,675,674,673,672,671]},{"id":-385,"name":"sf-sby001-hc0123-rack013","type":"host","type_id":1,"pool_weights":{},"reweight":-1,"kb":0,"kb_used":0,"kb_used_data":0,"kb_used_omap":0,"kb_used_meta":0,"kb_avail":0,"utilization":0,"var":0,"pgs":0,"children":[662,661,660,659,658,657,656,655]},{"id":-477,"name":"sf-sby001-hc0124-rack013","type":"host","type_id":1,"pool_weights":{},"reweight":-1,"kb":0,"kb_used":0,"kb_used_data":0,"kb_used_omap":0,"kb_used_meta":0,"kb_avail":0,"utilization":0,"var":0,"pgs":0,"children":[846,845,844,843,842,841,840,839]},{"id":-82,"name":"sf-sby001-hyperconverge024-rack004","type":"host","type_id":1,"pool_weights":{},"reweight":-1,"kb":35163095040,"kb_used":18344147484,"kb_used_data":18295183988,"kb_used_omap":134720,"kb_used_meta":48828026,"kb_avail":16818947556,"utilization":52.168750967832892,"var":1.2928704469956649,"pgs":0,"children":[851,850,849,848,847,59]},{"id":59,"device_class":"general","name":"osd.59","type":"osd","type_id":0,"crush_weight":5.4579925537109375,"depth":3,"pool_weights":{},"reweight":1,"kb":5860515840,"kb_used":3346657476,"kb_used_data":3337709072,"kb_used_omap":21194,"kb_used_meta":8927157,"kb_avail":2513858364,"utilization":57.105169022118027,"var":1.4152070737693498,"pgs":125,"status":"up"},{"id":847,"device_class":"general","name":"osd.847","type":"osd","type_id":0,"crush_weight":5.4579925537109375,"depth":3,"pool_weights":{},"reweight":1,"kb":5860515840,"kb_used":2736982648,"kb_used_data":2729250352,"kb_used_omap":24711,"kb_used_meta":7707576,"kb_avail":3123533192,"utilization":46.702077474463408,"var":1.1573927813082137,"pgs":102,"status":"up"},{"id":848,"device_class":"general","name":"osd.848","type":"osd","type_id":0,"crush_weight":5.4579925537109375,"depth":3,"pool_weights":{},"reweight":1,"kb":5860515840,"kb_used":3392917216,"kb_used_data":3384354732,"kb_used_omap":14948,"kb_used_meta":8547419,"kb_avail":2467598624,"utilization":57.894514896490747,"var":1.4347690133309026,"pgs":121,"status":"up"},{"id":849,"device_class":"general","name":"osd.849","type":"osd","type_id":0,"crush_weight":5.4579925537109375,"depth":3,"pool_weights":{},"reweight":1,"kb":5860515840,"kb_used":2524588512,"kb_used_data":2517451724,"kb_used_omap":38245,"kb_used_meta":7098522,"kb_avail":3335927328,"utilization":43.077923188413394,"var":1.0675772905237815,"pgs":108,"status":"up"},{"id":850,"device_class":"general","name":"osd.850","type":"osd","type_id":0,"crush_weight":5.4579925537109375,"depth":3,"pool_weights":{},"reweight":1,"kb":5860515840,"kb_used":3456100672,"kb_used_data":3447232676,"kb_used_omap":11172,"kb_used_meta":8856283,"kb_avail":2404415168,"utilization":58.972635965096202,"var":1.4614875151547786,"pgs":129,"status":"up"},{"id":851,"device_class":"general","name":"osd.851","type":"osd","type_id":0,"crush_weight":5.4579925537109375,"depth":3,"pool_weights":{},"reweight":1,"kb":5860515840,"kb_used":2886900960,"kb_used_data":2879185432,"kb_used_omap":24450,"kb_used_meta":7691069,"kb_avail":2973614880,"utilization":49.260185260415575,"var":1.2207890078869628,"pgs":116,"status":"up"},{"id":-481,"name":"sf-sby001-hyperconverge025-rack004","type":"host","type_id":1,"pool_weights":{},"reweight":-1,"kb":35163095040,"kb_used":19329209992,"kb_used_data":19278679868,"kb_used_omap":89641,"kb_used_meta":50440209,"kb_avail":15833885048,"utilization":54.97016110217811,"var":1.3622963064501554,"pgs":0,"children":[857,856,855,854,853,852]},{"id":852,"device_class":"general","name":"osd.852","type":"osd","type_id":0,"crush_weight":5.4579925537109375,"depth":3,"pool_weights":{},"reweight":1,"kb":5860515840,"kb_used":3348937884,"kb_used_data":3340007604,"kb_used_omap":11138,"kb_used_meta":8918973,"kb_avail":2511577956,"utilization":57.14408040914023,"var":1.4161713940070269,"pgs":122,"status":"up"},{"id":853,"device_class":"general","name":"osd.853","type":"osd","type_id":0,"crush_weight":5.4579925537109375,"depth":3,"pool_weights":{},"reweight":1,"kb":5860515840,"kb_used":3449405808,"kb_used_data":3440321692,"kb_used_omap":16936,"kb_used_meta":9067159,"kb_avail":2411110032,"utilization":58.85839919511249,"var":1.4586564459585227,"pgs":126,"status":"up"},{"id":854,"device_class":"general","name":"osd.854","type":"osd","type_id":0,"crush_weight":5.4579925537109375,"depth":3,"pool_weights":{},"reweight":1,"kb":5860515840,"kb_used":3046366060,"kb_used_data":3038375396,"kb_used_omap":17430,"kb_used_meta":7973225,"kb_avail":2814149780,"utilization":51.98119317769816,"var":1.2882223018997907,"pgs":121,"status":"up"},{"id":855,"device_class":"general","name":"osd.855","type":"osd","type_id":0,"crush_weight":5.4579925537109375,"depth":3,"pool_weights":{},"reweight":1,"kb":5860515840,"kb_used":2839018276,"kb_used_data":2831056560,"kb_used_omap":11238,"kb_used_meta":7950425,"kb_avail":3021497564,"utilization":48.443146533667587,"var":1.2005407710734195,"pgs":118,"status":"up"},{"id":856,"device_class":"general","name":"osd.856","type":"osd","type_id":0,"crush_weight":5.4579925537109375,"depth":3,"pool_weights":{},"reweight":1,"kb":5860515840,"kb_used":3149083940,"kb_used_data":3140669276,"kb_used_omap":23107,"kb_used_meta":8391548,"kb_avail":2711431900,"utilization":53.733903737729683,"var":1.3316587967968836,"pgs":131,"status":"up"},{"id":857,"device_class":"general","name":"osd.857","type":"osd","type_id":0,"crush_weight":5.4579925537109375,"depth":3,"pool_weights":{},"reweight":1,"kb":5860515840,"kb_used":3496398024,"kb_used_data":3488249340,"kb_used_omap":9792,"kb_used_meta":8138879,"kb_avail":2364117816,"utilization":59.660243559720506,"var":1.4785281289652892,"pgs":129,"status":"up"},{"id":-485,"name":"sf-sby001-hyperconverge026-rack004","type":"host","type_id":1,"pool_weights":{},"reweight":-1,"kb":35163095040,"kb_used":18256566168,"kb_used_data":18210132004,"kb_used_omap":131990,"kb_used_meta":46301988,"kb_avail":16906528872,"utilization":51.919679275194994,"var":1.2866978355257586,"pgs":0,"children":[863,862,861,860,859,858]},{"id":858,"device_class":"general","name":"osd.858","type":"osd","type_id":0,"crush_weight":5.4579925537109375,"depth":3,"pool_weights":{},"reweight":1,"kb":5860515840,"kb_used":3301481208,"kb_used_data":3292906216,"kb_used_omap":18994,"kb_used_meta":8555981,"kb_avail":2559034632,"utilization":56.334310803603252,"var":1.3961033039636286,"pgs":132,"status":"up"},{"id":859,"device_class":"general","name":"osd.859","type":"osd","type_id":0,"crush_weight":5.4579925537109375,"depth":3,"pool_weights":{},"reweight":1,"kb":5860515840,"kb_used":3141791920,"kb_used_data":3133429016,"kb_used_omap":16460,"kb_used_meta":8346419,"kb_avail":2718723920,"utilization":53.609477489271661,"var":1.3285752071675074,"pgs":133,"status":"up"},{"id":860,"device_class":"general","name":"osd.860","type":"osd","type_id":0,"crush_weight":5.4579925537109375,"depth":3,"pool_weights":{},"reweight":1,"kb":5860515840,"kb_used":3364731904,"kb_used_data":3356681128,"kb_used_omap":17175,"kb_used_meta":8033576,"kb_avail":2495783936,"utilization":57.413579211484567,"var":1.4228502396873952,"pgs":143,"status":"up"},{"id":861,"device_class":"general","name":"osd.861","type":"osd","type_id":0,"crush_weight":5.4579925537109375,"depth":3,"pool_weights":{},"reweight":1,"kb":5860515840,"kb_used":2732077020,"kb_used_data":2724756820,"kb_used_omap":26873,"kb_used_meta":7293318,"kb_avail":3128438820,"utilization":46.618371054517958,"var":1.155318329561458,"pgs":114,"status":"up"},{"id":862,"device_class":"general","name":"osd.862","type":"osd","type_id":0,"crush_weight":5.4579925537109375,"depth":3,"pool_weights":{},"reweight":1,"kb":5860515840,"kb_used":2377682936,"kb_used_data":2371580180,"kb_used_omap":22209,"kb_used_meta":6080510,"kb_avail":3482832904,"utilization":40.571222754343751,"var":1.0054550650428966,"pgs":110,"status":"up"},{"id":863,"device_class":"general","name":"osd.863","type":"osd","type_id":0,"crush_weight":5.4579925537109375,"depth":3,"pool_weights":{},"reweight":1,"kb":5860515840,"kb_used":3338801180,"kb_used_data":3330778644,"kb_used_omap":30279,"kb_used_meta":7992184,"kb_avail":2521714660,"utilization":56.971114337948791,"var":1.4118848677316662,"pgs":113,"status":"up"},{"id":-110,"name":"rack005","type":"rack","type_id":3,"pool_weights":{},"reweight":-1,"kb":0,"kb_used":0,"kb_used_data":0,"kb_used_omap":0,"kb_used_meta":0,"kb_avail":0,"utilization":0,"var":0,"pgs":0,"children":[-197,-169,-177,-189,-153,-185,-173,-109,-157]},{"id":-157,"name":"sf-sby001-hc0035-rack005","type":"host","type_id":1,"pool_weights":{},"reweight":-1,"kb":0,"kb_used":0,"kb_used_data":0,"kb_used_omap":0,"kb_used_meta":0,"kb_avail":0,"utilization":0,"var":0,"pgs":0,"children":[254,249,243,236,229,222,215,208]},{"id":-109,"name":"sf-sby001-hc0036-rack005","type":"host","type_id":1,"pool_weights":{},"reweight":-1,"kb":0,"kb_used":0,"kb_used_data":0,"kb_used_omap":0,"kb_used_meta":0,"kb_avail":0,"utilization":0,"var":0,"pgs":0,"children":[154,152,150,148,146,144,142,140]},{"id":-173,"name":"sf-sby001-hc0037-rack005","type":"host","type_id":1,"pool_weights":{},"reweight":-1,"kb":0,"kb_used":0,"kb_used_data":0,"kb_used_omap":0,"kb_used_meta":0,"kb_avail":0,"utilization":0,"var":0,"pgs":0,"children":[341,337,333,329,325,321,317,313,308,303,298,292,286,281]},{"id":-185,"name":"sf-sby001-hc0038-rack005","type":"host","type_id":1,"pool_weights":{},"reweight":-1,"kb":0,"kb_used":0,"kb_used_data":0,"kb_used_omap":0,"kb_used_meta":0,"kb_avail":0,"utilization":0,"var":0,"pgs":0,"children":[344,340,336,332,328,324,320,316,312,307,302,297,293,287]},{"id":-153,"name":"sf-sby001-hc0039-rack005","type":"host","type_id":1,"pool_weights":{},"reweight":-1,"kb":0,"kb_used":0,"kb_used_data":0,"kb_used_omap":0,"kb_used_meta":0,"kb_avail":0,"utilization":0,"var":0,"pgs":0,"children":[275,271,267,263,259,255,250,244,237,230,223,216,209,203]},{"id":-189,"name":"sf-sby001-hc0040-rack005","type":"host","type_id":1,"pool_weights":{},"reweight":-1,"kb":0,"kb_used":0,"kb_used_data":0,"kb_used_omap":0,"kb_used_meta":0,"kb_avail":0,"utilization":0,"var":0,"pgs":0,"children":[345,342,338,334,330,326,322,318,314,309,304,299,294,288]},{"id":-177,"name":"sf-sby001-hc0041-rack005","type":"host","type_id":1,"pool_weights":{},"reweight":-1,"kb":0,"kb_used":0,"kb_used_data":0,"kb_used_omap":0,"kb_used_meta":0,"kb_avail":0,"utilization":0,"var":0,"pgs":0,"children":[289,283]},{"id":-169,"name":"sf-sby001-hc0042-rack005","type":"host","type_id":1,"pool_weights":{},"reweight":-1,"kb":0,"kb_used":0,"kb_used_data":0,"kb_used_omap":0,"kb_used_meta":0,"kb_avail":0,"utilization":0,"var":0,"pgs":0,"children":[282,279]},{"id":-197,"name":"sf-sby001-hc0043-rack005","type":"host","type_id":1,"pool_weights":{},"reweight":-1,"kb":0,"kb_used":0,"kb_used_data":0,"kb_used_omap":0,"kb_used_meta":0,"kb_avail":0,"utilization":0,"var":0,"pgs":0,"children":[349,347]},{"id":-118,"name":"rack006","type":"rack","type_id":3,"pool_weights":{},"reweight":-1,"kb":0,"kb_used":0,"kb_used_data":0,"kb_used_omap":0,"kb_used_meta":0,"kb_avail":0,"utilization":0,"var":0,"pgs":0,"children":[-309,-305,-265,-261,-201,-205,-193,-145,-141,-117,-129,-165,-137]},{"id":-137,"name":"sf-sby001-hc0044-rack006","type":"host","type_id":1,"pool_weights":{},"reweight":-1,"kb":0,"kb_used":0,"kb_used_data":0,"kb_used_omap":0,"kb_used_meta":0,"kb_avail":0,"utilization":0,"var":0,"pgs":0,"children":[239,232,225,218,212,206,201,198]},{"id":-165,"name":"sf-sby001-hc0045-rack006","type":"host","type_id":1,"pool_weights":{},"reweight":-1,"kb":0,"kb_used":0,"kb_used_data":0,"kb_used_omap":0,"kb_used_meta":0,"kb_avail":0,"utilization":0,"var":0,"pgs":0,"children":[310,305,300,295,290,284,280,278]},{"id":-129,"name":"sf-sby001-hc0046-rack006","type":"host","type_id":1,"pool_weights":{},"reweight":-1,"kb":0,"kb_used":0,"kb_used_data":0,"kb_used_omap":0,"kb_used_meta":0,"kb_avail":0,"utilization":0,"var":0,"pgs":0,"children":[183,182,181,180,179,178,177,176,173,171,169,167,165,163]},{"id":-117,"name":"sf-sby001-hc0047-rack006","type":"host","type_id":1,"pool_weights":{},"reweight":-1,"kb":0,"kb_used":0,"kb_used_data":0,"kb_used_omap":0,"kb_used_meta":0,"kb_avail":0,"utilization":0,"var":0,"pgs":0,"children":[161,160,159,158,157,156,155,153,151,149,147,145,143,141]},{"id":-141,"name":"sf-sby001-hc0048-rack006","type":"host","type_id":1,"pool_weights":{},"reweight":-1,"kb":0,"kb_used":0,"kb_used_data":0,"kb_used_omap":0,"kb_used_meta":0,"kb_avail":0,"utilization":0,"var":0,"pgs":0,"children":[274,270,266,262,258,253,248,241,233,226,219,211,205,200]},{"id":-145,"name":"sf-sby001-hc0049-rack006","type":"host","type_id":1,"pool_weights":{},"reweight":-1,"kb":0,"kb_used":0,"kb_used_data":0,"kb_used_omap":0,"kb_used_meta":0,"kb_avail":0,"utilization":0,"var":0,"pgs":0,"children":[273,269,265,261,256,251,245,238,231,224,217,210,204,199]},{"id":-193,"name":"sf-sby001-hc0050-rack006","type":"host","type_id":1,"pool_weights":{},"reweight":-1,"kb":0,"kb_used":0,"kb_used_data":0,"kb_used_omap":0,"kb_used_meta":0,"kb_avail":0,"utilization":0,"var":0,"pgs":0,"children":[348,346]},{"id":-205,"name":"sf-sby001-hc0051-rack006","type":"host","type_id":1,"pool_weights":{},"reweight":-1,"kb":0,"kb_used":0,"kb_used_data":0,"kb_used_omap":0,"kb_used_meta":0,"kb_avail":0,"utilization":0,"var":0,"pgs":0,"children":[353,352]},{"id":-201,"name":"sf-sby001-hc0052-rack006","type":"host","type_id":1,"pool_weights":{},"reweight":-1,"kb":0,"kb_used":0,"kb_used_data":0,"kb_used_omap":0,"kb_used_meta":0,"kb_avail":0,"utilization":0,"var":0,"pgs":0,"children":[351,350]},{"id":-261,"name":"sf-sby001-hc0070-rack004","type":"host","type_id":1,"pool_weights":{},"reweight":-1,"kb":0,"kb_used":0,"kb_used_data":0,"kb_used_omap":0,"kb_used_meta":0,"kb_avail":0,"utilization":0,"var":0,"pgs":0,"children":[390,389,388,387,386,385,384,383]},{"id":-265,"name":"sf-sby001-hc0071-rack006","type":"host","type_id":1,"pool_weights":{},"reweight":-1,"kb":0,"kb_used":0,"kb_used_data":0,"kb_used_omap":0,"kb_used_meta":0,"kb_avail":0,"utilization":0,"var":0,"pgs":0,"children":[398,397,396,395,394,393,392,391]},{"id":-305,"name":"sf-sby001-hc0081-rack006","type":"host","type_id":1,"pool_weights":{},"reweight":-1,"kb":0,"kb_used":0,"kb_used_data":0,"kb_used_omap":0,"kb_used_meta":0,"kb_avail":0,"utilization":0,"var":0,"pgs":0,"children":[478,477,476,475,474,473,472,471]},{"id":-309,"name":"sf-sby001-hc0082-rack006","type":"host","type_id":1,"pool_weights":{},"reweight":-1,"kb":0,"kb_used":0,"kb_used_data":0,"kb_used_omap":0,"kb_used_meta":0,"kb_avail":0,"utilization":0,"var":0,"pgs":0,"children":[486,485,484,483,482,481,480,479]},{"id":-77,"name":"rack007","type":"rack","type_id":3,"pool_weights":{},"reweight":-1,"kb":0,"kb_used":0,"kb_used_data":0,"kb_used_omap":0,"kb_used_meta":0,"kb_avail":0,"utilization":0,"var":0,"pgs":0,"children":[-217,-209,-213,-76,-161,-133,-181,-125,-149]},{"id":-149,"name":"sf-sby001-hc0053-rack007","type":"host","type_id":1,"pool_weights":{},"reweight":-1,"kb":0,"kb_used":0,"kb_used_data":0,"kb_used_omap":0,"kb_used_meta":0,"kb_avail":0,"utilization":0,"var":0,"pgs":0,"children":[246,240,234,227,220,213,207,202]},{"id":-125,"name":"sf-sby001-hc0054-rack007","type":"host","type_id":1,"pool_weights":{},"reweight":-1,"kb":0,"kb_used":0,"kb_used_data":0,"kb_used_omap":0,"kb_used_meta":0,"kb_avail":0,"utilization":0,"var":0,"pgs":0,"children":[175,174,172,170,168,166,164,162]},{"id":-181,"name":"sf-sby001-hc0055-rack007","type":"host","type_id":1,"pool_weights":{},"reweight":-1,"kb":0,"kb_used":0,"kb_used_data":0,"kb_used_omap":0,"kb_used_meta":0,"kb_avail":0,"utilization":0,"var":0,"pgs":0,"children":[343,339,335,331,327,323,319,315,311,306,301,296,291,285]},{"id":-133,"name":"sf-sby001-hc0056-rack007","type":"host","type_id":1,"pool_weights":{},"reweight":-1,"kb":0,"kb_used":0,"kb_used_data":0,"kb_used_omap":0,"kb_used_meta":0,"kb_avail":0,"utilization":0,"var":0,"pgs":0,"children":[197,196,195,194,193,192,191,190,189,188,187,186,185,184]},{"id":-161,"name":"sf-sby001-hc0057-rack007","type":"host","type_id":1,"pool_weights":{},"reweight":-1,"kb":0,"kb_used":0,"kb_used_data":0,"kb_used_omap":0,"kb_used_meta":0,"kb_avail":0,"utilization":0,"var":0,"pgs":0,"children":[277,276,272,268,264,260,257,252,247,242,235,228,221,214]},{"id":-76,"name":"sf-sby001-hc0058-rack007","type":"host","type_id":1,"pool_weights":{},"reweight":-1,"kb":0,"kb_used":0,"kb_used_data":0,"kb_used_omap":0,"kb_used_meta":0,"kb_avail":0,"utilization":0,"var":0,"pgs":0,"children":[139,138,137,136,135,134,133,132,131,130,129,128,127,126]},{"id":-213,"name":"sf-sby001-hc0059-rack007","type":"host","type_id":1,"pool_weights":{},"reweight":-1,"kb":0,"kb_used":0,"kb_used_data":0,"kb_used_omap":0,"kb_used_meta":0,"kb_avail":0,"utilization":0,"var":0,"pgs":0,"children":[357,356]},{"id":-209,"name":"sf-sby001-hc0060-rack007","type":"host","type_id":1,"pool_weights":{},"reweight":-1,"kb":0,"kb_used":0,"kb_used_data":0,"kb_used_omap":0,"kb_used_meta":0,"kb_avail":0,"utilization":0,"var":0,"pgs":0,"children":[355,354]},{"id":-217,"name":"sf-sby001-hc0061-rack007","type":"host","type_id":1,"pool_weights":{},"reweight":-1,"kb":0,"kb_used":0,"kb_used_data":0,"kb_used_omap":0,"kb_used_meta":0,"kb_avail":0,"utilization":0,"var":0,"pgs":0,"children":[359,358]}],"stray":[],"summary":{"total_kb":785309065216,"total_kb_used":316880884324,"total_kb_used_data":316088744636,"total_kb_used_omap":5606184,"total_kb_used_meta":786460375,"total_kb_avail":468428180892,"average_utilization":40.351104852818885,"min_var":0.52628901049049659,"max_var":1.4785281289652892,"dev":7.8458332053916946}}
