
{"nodes":[{"id":-1,"name":"default","type":"root","type_id":10,"reweight":-1,"kb":832193175552,"kb_used":300991865560,"kb_used_data":300215105980,"kb_used_omap":6776504,"kb_used_meta":769921979,"kb_avail":531201309992,"utilization":36.168509235893438,"var":1,"pgs":0,"children":[-77,-118,-110,-83,-4,-16,-10]},{"id":-10,"name":"01-01","type":"rack","type_id":3,"pool_weights":{},"reweight":-1,"kb":240281124864,"kb_used":83968069644,"kb_used_data":83754872240,"kb_used_omap":2143746,"kb_used_meta":211035285,"kb_avail":156313055220,"utilization":34.945761841062726,"var":0.96619303862219286,"pgs":0,"children":[-13,-25,-45,-37,-31,-9,-29]},{"id":-29,"name":"sf-sby001-hyperconverge001-rack001","type":"host","type_id":1,"pool_weights":{},"reweight":-1,"kb":35163095040,"kb_used":11672936860,"kb_used_data":11639944220,"kb_used_omap":53336,"kb_used_meta":32938914,"kb_avail":23490158180,"utilization":33.196556920604905,"var":0.91783038952738527,"pgs":0,"children":[90,71,50,40,31,11]},{"id":11,"device_class":"general","name":"osd.11","type":"osd","type_id":0,"crush_weight":5.4579925537109375,"depth":3,"pool_weights":{},"reweight":1,"kb":5860515840,"kb_used":1963096032,"kb_used_data":1957524000,"kb_used_omap":6936,"kb_used_meta":5565031,"kb_avail":3897419808,"utilization":33.496983637535905,"var":0.9261366958495949,"pgs":81,"status":"up"},{"id":31,"device_class":"general","name":"osd.31","type":"osd","type_id":0,"crush_weight":5.4579925537109375,"depth":3,"pool_weights":{},"reweight":1,"kb":5860515840,"kb_used":2108442528,"kb_used_data":2102781408,"kb_used_omap":4948,"kb_used_meta":5656107,"kb_avail":3752073312,"utilization":35.977080952655527,"var":0.99470732172041143,"pgs":80,"status":"up"},{"id":40,"device_class":"general","name":"osd.40","type":"osd","type_id":0,"crush_weight":5.4579925537109375,"depth":3,"pool_weights":{},"reweight":1,"kb":5860515840,"kb_used":1569659324,"kb_used_data":1564648812,"kb_used_omap":16523,"kb_used_meta":4993780,"kb_avail":4290856516,"utilization":26.783637598699844,"var":0.74052368108442534,"pgs":77,"status":"up"},{"id":50,"device_class":"general","name":"osd.50","type":"osd","type_id":0,"crush_weight":5.4579925537109375,"depth":3,"pool_weights":{},"reweight":1,"kb":5860515840,"kb_used":1713182160,"kb_used_data":1708169728,"kb_used_omap":7457,"kb_used_meta":5004958,"kb_avail":4147333680,"utilization":29.232617175214394,"var":0.80823395248494501,"pgs":77,"status":"up"},{"id":71,"device_class":"general","name":"osd.71","type":"osd","type_id":0,"crush_weight":5.4579925537109375,"depth":3,"pool_weights":{},"reweight":1,"kb":5860515840,"kb_used":2253559504,"kb_used_data":2247476672,"kb_used_omap":6479,"kb_used_meta":6076336,"kb_avail":3606956336,"utilization":38.453261888973927,"var":1.0631696661363392,"pgs":90,"status":"up"},{"id":90,"device_class":"general","name":"osd.90","type":"osd","type_id":0,"crush_weight":5.4579925537109375,"depth":3,"pool_weights":{},"reweight":1,"kb":5860515840,"kb_used":2064997312,"kb_used_data":2059343600,"kb_used_omap":10993,"kb_used_meta":5642702,"kb_avail":3795518528,"utilization":35.235760270549839,"var":0.97421101988859571,"pgs":92,"status":"up"},{"id":-9,"name":"sf-sby001-hyperconverge002-rack001","type":"host","type_id":1,"pool_weights":{},"reweight":-1,"kb":35163090944,"kb_used":12251743280,"kb_used_data":12221550784,"kb_used_omap":531218,"kb_used_meta":29656040,"kb_avail":22911347664,"utilization":34.842623191208844,"var":0.96334142399850997,"pgs":0,"children":[123,78,56,35,15,2]},{"id":2,"device_class":"general","name":"osd.2","type":"osd","type_id":0,"crush_weight":5.4579925537109375,"depth":3,"pool_weights":{},"reweight":1,"kb":5860515840,"kb_used":2341872528,"kb_used_data":2336136000,"kb_used_omap":102460,"kb_used_meta":5634051,"kb_avail":3518643312,"utilization":39.960177430388107,"var":1.1048334110141271,"pgs":85,"status":"up"},{"id":15,"device_class":"general","name":"osd.15","type":"osd","type_id":0,"crush_weight":5.4579925537109375,"depth":3,"pool_weights":{},"reweight":1,"kb":5860515840,"kb_used":2495891920,"kb_used_data":2489942656,"kb_used_omap":104298,"kb_used_meta":5844949,"kb_avail":3364623920,"utilization":42.588263356694554,"var":1.1774956794301654,"pgs":95,"status":"up"},{"id":35,"device_class":"general","name":"osd.35","type":"osd","type_id":0,"crush_weight":5.4579925537109375,"depth":3,"pool_weights":{},"reweight":1,"kb":5860515840,"kb_used":1666693728,"kb_used_data":1661944912,"kb_used_omap":90506,"kb_used_meta":4657333,"kb_avail":4193822112,"utilization":28.439369050489589,"var":0.7863019419740559,"pgs":75,"status":"up"},{"id":56,"device_class":"general","name":"osd.56","type":"osd","type_id":0,"crush_weight":5.4579925537109375,"depth":3,"pool_weights":{},"reweight":1,"kb":5860515840,"kb_used":1869039744,"kb_used_data":1864729888,"kb_used_omap":53109,"kb_used_meta":4256714,"kb_avail":3991476096,"utilization":31.892068804646385,"var":0.88176343118385603,"pgs":88,"status":"up"},{"id":78,"device_class":"general","name":"osd.78","type":"osd","type_id":0,"crush_weight":5.4579925537109375,"depth":3,"pool_weights":{},"reweight":1,"kb":5860515840,"kb_used":2111665696,"kb_used_data":2106477776,"kb_used_omap":100393,"kb_used_meta":5083350,"kb_avail":3748850144,"utilization":36.032078978221818,"var":0.99622792698527296,"pgs":80,"status":"up"},{"id":123,"device_class":"general","name":"osd.123","type":"osd","type_id":0,"crush_weight":5.4579925537109375,"depth":3,"pool_weights":{},"reweight":1,"kb":5860511744,"kb_used":1766579664,"kb_used_data":1762319552,"kb_used_omap":80452,"kb_used_meta":4179643,"kb_avail":4093932080,"utilization":30.143778242721325,"var":0.833426062603841,"pgs":68,"status":"up"},{"id":-31,"name":"sf-sby001-hyperconverge004-rack001","type":"host","type_id":1,"pool_weights":{},"reweight":-1,"kb":35163090944,"kb_used":12242529376,"kb_used_data":12212758320,"kb_used_omap":41904,"kb_used_meta":29725898,"kb_avail":22920561568,"utilization":34.816419851989679,"var":0.9626169446165076,"pgs":0,"children":[108,93,52,41,32,12]},{"id":12,"device_class":"general","name":"osd.12","type":"osd","type_id":0,"crush_weight":5.4579925537109375,"depth":3,"pool_weights":{},"reweight":1,"kb":5860511744,"kb_used":2490371552,"kb_used_data":2484476384,"kb_used_omap":9639,"kb_used_meta":5885272,"kb_avail":3370140192,"utilization":42.494097116171567,"var":1.1748921372186567,"pgs":82,"status":"up"},{"id":32,"device_class":"general","name":"osd.32","type":"osd","type_id":0,"crush_weight":5.4579925537109375,"depth":3,"pool_weights":{},"reweight":1,"kb":5860515840,"kb_used":2199230992,"kb_used_data":2194009280,"kb_used_omap":10291,"kb_used_meta":5211404,"kb_avail":3661284848,"utilization":37.526235779272291,"var":1.0375389136036453,"pgs":80,"status":"up"},{"id":41,"device_class":"general","name":"osd.41","type":"osd","type_id":0,"crush_weight":5.4579925537109375,"depth":3,"pool_weights":{},"reweight":1,"kb":5860515840,"kb_used":1961331920,"kb_used_data":1956451504,"kb_used_omap":6690,"kb_used_meta":4873693,"kb_avail":3899183920,"utilization":33.466881986961745,"var":0.92530443454797928,"pgs":97,"status":"up"},{"id":52,"device_class":"general","name":"osd.52","type":"osd","type_id":0,"crush_weight":5.4579925537109375,"depth":3,"pool_weights":{},"reweight":1,"kb":5860515840,"kb_used":1670054752,"kb_used_data":1665676016,"kb_used_omap":5760,"kb_used_meta":4372927,"kb_avail":4190461088,"utilization":28.496719360458208,"var":0.78788758404723558,"pgs":75,"status":"up"},{"id":93,"device_class":"general","name":"osd.93","type":"osd","type_id":0,"crush_weight":5.4579925537109375,"depth":3,"pool_weights":{},"reweight":1,"kb":5860515840,"kb_used":2299044704,"kb_used_data":2293390544,"kb_used_omap":4955,"kb_used_meta":5649188,"kb_avail":3561471136,"utilization":39.229391520593516,"var":1.0846283783701671,"pgs":90,"status":"up"},{"id":108,"device_class":"general","name":"osd.108","type":"osd","type_id":0,"crush_weight":5.4579925537109375,"depth":3,"pool_weights":{},"reweight":1,"kb":5860515840,"kb_used":1622495456,"kb_used_data":1618754592,"kb_used_omap":4569,"kb_used_meta":3733414,"kb_avail":4238020384,"utilization":27.685198714521349,"var":0.76545036827358925,"pgs":78,"status":"up"},{"id":-37,"name":"sf-sby001-hyperconverge005-rack001","type":"host","type_id":1,"pool_weights":{},"reweight":-1,"kb":29302575104,"kb_used":9947739316,"kb_used_data":9923699312,"kb_used_omap":226110,"kb_used_meta":23812861,"kb_avail":19354835788,"utilization":33.948345088080899,"var":0.93861610017342767,"pgs":0,"children":[104,86,65,44,22,20]},{"id":20,"device_class":"general","name":"osd.20","type":"osd","type_id":0,"crush_weight":5.4579925537109375,"depth":3,"pool_weights":{},"reweight":1,"kb":5860515840,"kb_used":1717581412,"kb_used_data":1714009856,"kb_used_omap":8863,"kb_used_meta":3562656,"kb_avail":4142934428,"utilization":29.307683127088008,"var":0.8103094030207697,"pgs":86,"status":"up"},{"id":22,"device_class":"general","name":"osd.22","type":"osd","type_id":0,"crush_weight":5.4579925537109375,"depth":3,"pool_weights":{},"reweight":1,"kb":5860511744,"kb_used":1622068880,"kb_used_data":1618532352,"kb_used_omap":27178,"kb_used_meta":3509333,"kb_avail":4238442864,"utilization":27.677939245846172,"var":0.76524965586302718,"pgs":71,"status":"up"},{"id":44,"device_class":"general","name":"osd.44","type":"osd","type_id":0,"crush_weight":5.4579925537109375,"depth":3,"pool_weights":{},"reweight":1,"kb":5860515840,"kb_used":2344441760,"kb_used_data":2338664064,"kb_used_omap":82837,"kb_used_meta":5693930,"kb_avail":3516074080,"utilization":40.004017120786422,"var":1.1060455066001627,"pgs":87,"status":"up"},{"id":65,"device_class":"general","name":"osd.65","type":"osd","type_id":0,"crush_weight":5.4579925537109375,"depth":3,"pool_weights":{},"reweight":1,"kb":5860515840,"kb_used":2299670128,"kb_used_data":2293744736,"kb_used_omap":57919,"kb_used_meta":5867456,"kb_avail":3560845712,"utilization":39.24006334568665,"var":1.0849234368428162,"pgs":97,"status":"up"},{"id":86,"device_class":"general","name":"osd.86","type":"osd","type_id":0,"crush_weight":5.4579925537109375,"depth":3,"pool_weights":{},"reweight":0,"kb":0,"kb_used":0,"kb_used_data":0,"kb_used_omap":0,"kb_used_meta":0,"kb_avail":0,"utilization":0,"var":0,"pgs":0,"status":"down"},{"id":104,"device_class":"general","name":"osd.104","type":"osd","type_id":0,"crush_weight":5.4579925537109375,"depth":3,"pool_weights":{},"reweight":1,"kb":5860515840,"kb_used":1963977136,"kb_used_data":1958748304,"kb_used_omap":49313,"kb_used_meta":5179486,"kb_avail":3896538704,"utilization":33.512018218519138,"var":0.92655237737202578,"pgs":82,"status":"up"},{"id":-45,"name":"sf-sby001-hyperconverge006-rack001","type":"host","type_id":1,"pool_weights":{},"reweight":-1,"kb":35163090944,"kb_used":12051067040,"kb_used_data":12021602544,"kb_used_omap":335854,"kb_used_meta":29125580,"kb_avail":23112023904,"utilization":34.271921826190642,"var":0.94756246663822596,"pgs":0,"children":[119,111,89,69,46,26]},{"id":26,"device_class":"general","name":"osd.26","type":"osd","type_id":0,"crush_weight":5.4579925537109375,"depth":3,"pool_weights":{},"reweight":1,"kb":5860511744,"kb_used":2346257312,"kb_used_data":2340325664,"kb_used_omap":96335,"kb_used_meta":5833072,"kb_avail":3514254432,"utilization":40.035024490857843,"var":1.1069028095613986,"pgs":99,"status":"up"},{"id":46,"device_class":"general","name":"osd.46","type":"osd","type_id":0,"crush_weight":5.4579925537109375,"depth":3,"pool_weights":{},"reweight":1,"kb":5860515840,"kb_used":1623893984,"kb_used_data":1619797904,"kb_used_omap":65055,"kb_used_meta":4031008,"kb_avail":4236621856,"utilization":27.709062279405085,"var":0.76611015673011917,"pgs":88,"status":"up"},{"id":69,"device_class":"general","name":"osd.69","type":"osd","type_id":0,"crush_weight":5.4579925537109375,"depth":3,"pool_weights":{},"reweight":1,"kb":5860515840,"kb_used":2297940128,"kb_used_data":2292607936,"kb_used_omap":8398,"kb_used_meta":5323761,"kb_avail":3562575712,"utilization":39.210543759915851,"var":1.0841072686790063,"pgs":86,"status":"up"},{"id":89,"device_class":"general","name":"osd.89","type":"osd","type_id":0,"crush_weight":5.4579925537109375,"depth":3,"pool_weights":{},"reweight":1,"kb":5860515840,"kb_used":2203573504,"kb_used_data":2198231152,"kb_used_omap":51184,"kb_used_meta":5291151,"kb_avail":3656942336,"utilization":37.600333556986001,"var":1.0395875957107912,"pgs":88,"status":"up"},{"id":111,"device_class":"general","name":"osd.111","type":"osd","type_id":0,"crush_weight":5.4579925537109375,"depth":3,"pool_weights":{},"reweight":1,"kb":5860515840,"kb_used":1667253904,"kb_used_data":1663567472,"kb_used_omap":42282,"kb_used_meta":3643413,"kb_avail":4193261936,"utilization":28.448927526488863,"var":0.7865662181690446,"pgs":73,"status":"up"},{"id":119,"device_class":"general","name":"osd.119","type":"osd","type_id":0,"crush_weight":5.4579925537109375,"depth":3,"pool_weights":{},"reweight":1,"kb":5860515840,"kb_used":1912148208,"kb_used_data":1907072416,"kb_used_omap":72600,"kb_used_meta":5003175,"kb_avail":3948367632,"utilization":32.627643371406705,"var":0.90210086234428499,"pgs":87,"status":"up"},{"id":-25,"name":"sf-sby001-hyperconverge007-rack001","type":"host","type_id":1,"pool_weights":{},"reweight":-1,"kb":35163090944,"kb_used":12723259628,"kb_used_data":12688716900,"kb_used_omap":438873,"kb_used_meta":34099873,"kb_avail":22439831316,"utilization":36.183564318230147,"var":1.0004162483512526,"pgs":0,"children":[101,84,63,42,21,8]},{"id":8,"device_class":"general","name":"osd.8","type":"osd","type_id":0,"crush_weight":5.4579925537109375,"depth":3,"pool_weights":{},"reweight":1,"kb":5860511744,"kb_used":2394825904,"kb_used_data":2388999760,"kb_used_omap":106350,"kb_used_meta":5719249,"kb_avail":3465685840,"utilization":40.863767681240908,"var":1.1298162004611436,"pgs":78,"status":"up"},{"id":21,"device_class":"general","name":"osd.21","type":"osd","type_id":0,"crush_weight":5.4579925537109375,"depth":3,"pool_weights":{},"reweight":1,"kb":5860515840,"kb_used":2059928412,"kb_used_data":2053686740,"kb_used_omap":8690,"kb_used_meta":6232973,"kb_avail":3800587428,"utilization":35.149267884241397,"var":0.97181964716863278,"pgs":84,"status":"up"},{"id":42,"device_class":"general","name":"osd.42","type":"osd","type_id":0,"crush_weight":5.4579925537109375,"depth":3,"pool_weights":{},"reweight":1,"kb":5860515840,"kb_used":2441045184,"kb_used_data":2435194592,"kb_used_omap":55919,"kb_used_meta":5794640,"kb_avail":3419470656,"utilization":41.65239461241692,"var":1.1516204425445686,"pgs":87,"status":"up"},{"id":63,"device_class":"general","name":"osd.63","type":"osd","type_id":0,"crush_weight":5.4579925537109375,"depth":3,"pool_weights":{},"reweight":1,"kb":5860515840,"kb_used":1963754656,"kb_used_data":1958635952,"kb_used_omap":80952,"kb_used_meta":5037703,"kb_avail":3896761184,"utilization":33.508221965662329,"var":0.92644741720261303,"pgs":88,"status":"up"},{"id":84,"device_class":"general","name":"osd.84","type":"osd","type_id":0,"crush_weight":5.4579925537109375,"depth":3,"pool_weights":{},"reweight":1,"kb":5860515840,"kb_used":1770003520,"kb_used_data":1764031008,"kb_used_omap":57756,"kb_used_meta":5914339,"kb_avail":4090512320,"utilization":30.202179608817506,"var":0.83504076465626131,"pgs":74,"status":"up"},{"id":101,"device_class":"general","name":"osd.101","type":"osd","type_id":0,"crush_weight":5.4579925537109375,"depth":3,"pool_weights":{},"reweight":1,"kb":5860515840,"kb_used":2093701952,"kb_used_data":2088168848,"kb_used_omap":129206,"kb_used_meta":5400969,"kb_avail":3766813888,"utilization":35.725557428064214,"var":0.9877531085138106,"pgs":76,"status":"up"},{"id":-13,"name":"sf-sby001-hyperconverge008-rack001","type":"host","type_id":1,"pool_weights":{},"reweight":-1,"kb":35163090944,"kb_used":13078794144,"kb_used_data":13046600160,"kb_used_omap":516451,"kb_used_meta":31676119,"kb_avail":22084296800,"utilization":37.194665750030374,"var":1.0283715457400877,"pgs":0,"children":[98,81,60,38,16,6]},{"id":6,"device_class":"general","name":"osd.6","type":"osd","type_id":0,"crush_weight":5.4579925537109375,"depth":3,"pool_weights":{},"reweight":1,"kb":5860511744,"kb_used":2154901952,"kb_used_data":2148761136,"kb_used_omap":78644,"kb_used_meta":6062155,"kb_avail":3705609792,"utilization":36.769859802877995,"var":1.0166263575604544,"pgs":91,"status":"up"},{"id":16,"device_class":"general","name":"osd.16","type":"osd","type_id":0,"crush_weight":5.4579925537109375,"depth":3,"pool_weights":{},"reweight":1,"kb":5860515840,"kb_used":2398977056,"kb_used_data":2393140000,"kb_used_omap":83343,"kb_used_meta":5753584,"kb_avail":3461538784,"utilization":40.934571657091539,"var":1.1317738143453335,"pgs":90,"status":"up"},{"id":38,"device_class":"general","name":"osd.38","type":"osd","type_id":0,"crush_weight":5.4579925537109375,"depth":3,"pool_weights":{},"reweight":1,"kb":5860515840,"kb_used":2252488640,"kb_used_data":2247358528,"kb_used_omap":116440,"kb_used_meta":5013479,"kb_avail":3608027200,"utilization":38.434989367761865,"var":1.0626644608735818,"pgs":94,"status":"up"},{"id":60,"device_class":"general","name":"osd.60","type":"osd","type_id":0,"crush_weight":5.4579925537109375,"depth":3,"pool_weights":{},"reweight":1,"kb":5860515840,"kb_used":2355619984,"kb_used_data":2350256016,"kb_used_omap":70524,"kb_used_meta":5292867,"kb_avail":3504895856,"utilization":40.194755006412542,"var":1.1113190965173505,"pgs":98,"status":"up"},{"id":81,"device_class":"general","name":"osd.81","type":"osd","type_id":0,"crush_weight":5.4579925537109375,"depth":3,"pool_weights":{},"reweight":1,"kb":5860515840,"kb_used":1906009264,"kb_used_data":1901139280,"kb_used_omap":59006,"kb_used_meta":4810497,"kb_avail":3954506576,"utilization":32.522892455828597,"var":0.89920467121583902,"pgs":92,"status":"up"},{"id":98,"device_class":"general","name":"osd.98","type":"osd","type_id":0,"crush_weight":5.4579925537109375,"depth":3,"pool_weights":{},"reweight":1,"kb":5860515840,"kb_used":2010797248,"kb_used_data":2005945200,"kb_used_omap":108494,"kb_used_meta":4743537,"kb_avail":3849718592,"utilization":34.310925913306633,"var":0.9486408657190839,"pgs":84,"status":"up"},{"id":-16,"name":"01-02","type":"rack","type_id":3,"pool_weights":{},"reweight":-1,"kb":240281124864,"kb_used":82500250640,"kb_used_data":82285909688,"kb_used_omap":2115218,"kb_used_meta":212212741,"kb_avail":157780874224,"utilization":34.334886140846663,"var":0.94930332673962969,"pgs":0,"children":[-47,-19,-41,-23,-15,-33,-27]},{"id":-27,"name":"sf-sby001-hyperconverge009-rack002","type":"host","type_id":1,"pool_weights":{},"reweight":-1,"kb":35163090944,"kb_used":12233141600,"kb_used_data":12202236320,"kb_used_omap":223982,"kb_used_meta":30676428,"kb_avail":22929949344,"utilization":34.789722039744014,"var":0.96187879386576647,"pgs":0,"children":[124,88,70,49,29,9]},{"id":9,"device_class":"general","name":"osd.9","type":"osd","type_id":0,"crush_weight":5.4579925537109375,"depth":3,"pool_weights":{},"reweight":1,"kb":5860515840,"kb_used":1762559920,"kb_used_data":1757742160,"kb_used_omap":49407,"kb_used_meta":4768320,"kb_avail":4097955920,"utilization":30.075166898618946,"var":0.83152907139375565,"pgs":81,"status":"up"},{"id":29,"device_class":"general","name":"osd.29","type":"osd","type_id":0,"crush_weight":5.4579925537109375,"depth":3,"pool_weights":{},"reweight":1,"kb":5860515840,"kb_used":1567693952,"kb_used_data":1563035504,"kb_used_omap":44045,"kb_used_meta":4613746,"kb_avail":4292821888,"utilization":26.750101779436534,"var":0.73959647064717482,"pgs":77,"status":"up"},{"id":49,"device_class":"general","name":"osd.49","type":"osd","type_id":0,"crush_weight":5.4579925537109375,"depth":3,"pool_weights":{},"reweight":1,"kb":5860515840,"kb_used":2296003520,"kb_used_data":2290095040,"kb_used_omap":45094,"kb_used_meta":5859289,"kb_avail":3564512320,"utilization":39.177498750690177,"var":1.0831936283348564,"pgs":85,"status":"up"},{"id":70,"device_class":"general","name":"osd.70","type":"osd","type_id":0,"crush_weight":5.4579925537109375,"depth":3,"pool_weights":{},"reweight":1,"kb":5860515840,"kb_used":2596494960,"kb_used_data":2590401568,"kb_used_omap":9847,"kb_used_meta":6083528,"kb_avail":3264020880,"utilization":44.304887673505547,"var":1.2249575282339149,"pgs":99,"status":"up"},{"id":88,"device_class":"general","name":"osd.88","type":"osd","type_id":0,"crush_weight":5.4579925537109375,"depth":3,"pool_weights":{},"reweight":1,"kb":5860515840,"kb_used":1761304432,"kb_used_data":1757419200,"kb_used_omap":42598,"kb_used_meta":3842585,"kb_avail":4099211408,"utilization":30.053744074514778,"var":0.83093676541939421,"pgs":77,"status":"up"},{"id":124,"device_class":"general","name":"osd.124","type":"osd","type_id":0,"crush_weight":5.4579925537109375,"depth":3,"pool_weights":{},"reweight":1,"kb":5860511744,"kb_used":2249084816,"kb_used_data":2243542848,"kb_used_omap":32991,"kb_used_meta":5508960,"kb_avail":3611426928,"utilization":38.376935568853966,"var":1.0610593684842531,"pgs":89,"status":"up"},{"id":-33,"name":"sf-sby001-hyperconverge010-rack002","type":"host","type_id":1,"pool_weights":{},"reweight":-1,"kb":35163090944,"kb_used":11973896548,"kb_used_data":11942301824,"kb_used_omap":452267,"kb_used_meta":31141839,"kb_avail":23189194396,"utilization":34.052457353846897,"var":0.94149463368131903,"pgs":0,"children":[125,120,72,51,33,10]},{"id":10,"device_class":"general","name":"osd.10","type":"osd","type_id":0,"crush_weight":5.4579925537109375,"depth":3,"pool_weights":{},"reweight":1,"kb":5860515840,"kb_used":1810894624,"kb_used_data":1805900512,"kb_used_omap":57727,"kb_used_meta":4936128,"kb_avail":4049621216,"utilization":30.899918598291851,"var":0.85433210411743854,"pgs":82,"status":"up"},{"id":33,"device_class":"general","name":"osd.33","type":"osd","type_id":0,"crush_weight":5.4579925537109375,"depth":3,"pool_weights":{},"reweight":1,"kb":5860515840,"kb_used":2151359936,"kb_used_data":2145868336,"kb_used_omap":89342,"kb_used_meta":5402177,"kb_avail":3709155904,"utilization":36.709395465092712,"var":1.0149546177220514,"pgs":87,"status":"up"},{"id":51,"device_class":"general","name":"osd.51","type":"osd","type_id":0,"crush_weight":5.4579925537109375,"depth":3,"pool_weights":{},"reweight":1,"kb":5860515840,"kb_used":1773604896,"kb_used_data":1768906192,"kb_used_omap":78959,"kb_used_meta":4619728,"kb_avail":4086910944,"utilization":30.263631127733628,"var":0.83673979843493684,"pgs":85,"status":"up"},{"id":72,"device_class":"general","name":"osd.72","type":"osd","type_id":0,"crush_weight":5.4579925537109375,"depth":3,"pool_weights":{},"reweight":1,"kb":5860515840,"kb_used":2408902800,"kb_used_data":2403092288,"kb_used_omap":121620,"kb_used_meta":5688875,"kb_avail":3451613040,"utilization":41.103938045153377,"var":1.1364565173828631,"pgs":98,"status":"up"},{"id":120,"device_class":"general","name":"osd.120","type":"osd","type_id":0,"crush_weight":5.4579925537109375,"depth":3,"pool_weights":{},"reweight":1,"kb":5860511744,"kb_used":2157612064,"kb_used_data":2152515872,"kb_used_omap":89680,"kb_used_meta":5006447,"kb_avail":3702899680,"utilization":36.816103409552355,"var":1.0179049174914914,"pgs":84,"status":"up"},{"id":125,"device_class":"general","name":"osd.125","type":"osd","type_id":0,"crush_weight":5.4579925537109375,"depth":3,"pool_weights":{},"reweight":1,"kb":5860515840,"kb_used":1671522228,"kb_used_data":1666018624,"kb_used_omap":14939,"kb_used_meta":5488484,"kb_avail":4188993612,"utilization":28.521759408809991,"var":0.78857990034339454,"pgs":70,"status":"up"},{"id":-15,"name":"sf-sby001-hyperconverge011-rack002","type":"host","type_id":1,"pool_weights":{},"reweight":-1,"kb":35163095040,"kb_used":12666093144,"kb_used_data":12634090740,"kb_used_omap":345828,"kb_used_meta":31654230,"kb_avail":22497001896,"utilization":36.020984869482071,"var":0.99592119306192017,"pgs":0,"children":[100,99,79,58,37,17]},{"id":17,"device_class":"general","name":"osd.17","type":"osd","type_id":0,"crush_weight":5.4579925537109375,"depth":3,"pool_weights":{},"reweight":1,"kb":5860515840,"kb_used":2050882352,"kb_used_data":2045631504,"kb_used_omap":80012,"kb_used_meta":5169651,"kb_avail":3809633488,"utilization":34.994911847213778,"var":0.96755195573515684,"pgs":80,"status":"up"},{"id":37,"device_class":"general","name":"osd.37","type":"osd","type_id":0,"crush_weight":5.4579925537109375,"depth":3,"pool_weights":{},"reweight":1,"kb":5860515840,"kb_used":2203870848,"kb_used_data":2198453200,"kb_used_omap":49779,"kb_used_meta":5367820,"kb_avail":3656644992,"utilization":37.605407240056195,"var":1.0397278747318894,"pgs":97,"status":"up"},{"id":58,"device_class":"general","name":"osd.58","type":"osd","type_id":0,"crush_weight":5.4579925537109375,"depth":3,"pool_weights":{},"reweight":1,"kb":5860515840,"kb_used":2641777312,"kb_used_data":2635426704,"kb_used_omap":87025,"kb_used_meta":6263566,"kb_avail":3218738528,"utilization":45.07755603984512,"var":1.2463205421557821,"pgs":102,"status":"up"},{"id":79,"device_class":"general","name":"osd.79","type":"osd","type_id":0,"crush_weight":5.4579925537109375,"depth":3,"pool_weights":{},"reweight":1,"kb":5860515840,"kb_used":1911887584,"kb_used_data":1907526064,"kb_used_omap":41830,"kb_used_meta":4318681,"kb_avail":3948628256,"utilization":32.623196254342005,"var":0.90197790684629375,"pgs":74,"status":"up"},{"id":99,"device_class":"general","name":"osd.99","type":"osd","type_id":0,"crush_weight":5.4579925537109375,"depth":3,"pool_weights":{},"reweight":1,"kb":5860515840,"kb_used":2003115312,"kb_used_data":1997676304,"kb_used_omap":78702,"kb_used_meta":5360273,"kb_avail":3857400528,"utilization":34.179846393862832,"var":0.94501673184646862,"pgs":81,"status":"up"},{"id":100,"device_class":"general","name":"osd.100","type":"osd","type_id":0,"crush_weight":5.4579925537109375,"depth":3,"pool_weights":{},"reweight":1,"kb":5860515840,"kb_used":1854559736,"kb_used_data":1849376964,"kb_used_omap":8480,"kb_used_meta":5174239,"kb_avail":4005956104,"utilization":31.644991441572486,"var":0.87493214705593014,"pgs":75,"status":"up"},{"id":-23,"name":"sf-sby001-hyperconverge013-rack002","type":"host","type_id":1,"pool_weights":{},"reweight":-1,"kb":35163090944,"kb_used":11756845456,"kb_used_data":11725948520,"kb_used_omap":52630,"kb_used_meta":30842852,"kb_avail":23406245488,"utilization":33.435187693606643,"var":0.92442813928382039,"pgs":0,"children":[97,80,39,19,4,3]},{"id":3,"device_class":"general","name":"osd.3","type":"osd","type_id":0,"crush_weight":5.4579925537109375,"depth":3,"pool_weights":{},"reweight":1,"kb":5860515840,"kb_used":2195091056,"kb_used_data":2188916456,"kb_used_omap":7224,"kb_used_meta":6167367,"kb_avail":3665424784,"utilization":37.455594625608931,"var":1.0355858014860673,"pgs":75,"status":"up"},{"id":4,"device_class":"general","name":"osd.4","type":"osd","type_id":0,"crush_weight":5.4579925537109375,"depth":3,"pool_weights":{},"reweight":1,"kb":5860511744,"kb_used":1573117776,"kb_used_data":1568816768,"kb_used_omap":10945,"kb_used_meta":4290046,"kb_avail":4287393968,"utilization":26.84266911691731,"var":0.74215580581017659,"pgs":73,"status":"up"},{"id":19,"device_class":"general","name":"osd.19","type":"osd","type_id":0,"crush_weight":5.4579925537109375,"depth":3,"pool_weights":{},"reweight":0.95001220703125,"kb":5860515840,"kb_used":2439542000,"kb_used_data":2433538320,"kb_used_omap":9611,"kb_used_meta":5992948,"kb_avail":3420973840,"utilization":41.62674526616415,"var":1.1509112801600898,"pgs":89,"status":"up"},{"id":39,"device_class":"general","name":"osd.39","type":"osd","type_id":0,"crush_weight":5.4579925537109375,"depth":3,"pool_weights":{},"reweight":1,"kb":5860515840,"kb_used":2060160416,"kb_used_data":2055173136,"kb_used_omap":5851,"kb_used_meta":4981156,"kb_avail":3800355424,"utilization":35.153226648390053,"var":0.97192910050890835,"pgs":83,"status":"up"},{"id":80,"device_class":"general","name":"osd.80","type":"osd","type_id":0,"crush_weight":5.4579925537109375,"depth":3,"pool_weights":{},"reweight":1,"kb":5860515840,"kb_used":1721268496,"kb_used_data":1716824896,"kb_used_omap":6657,"kb_used_meta":4436926,"kb_avail":4139247344,"utilization":29.370597111123924,"var":0.81204887156301975,"pgs":88,"status":"up"},{"id":97,"device_class":"general","name":"osd.97","type":"osd","type_id":0,"crush_weight":5.4579925537109375,"depth":3,"pool_weights":{},"reweight":1,"kb":5860515840,"kb_used":1767665712,"kb_used_data":1762678944,"kb_used_omap":12342,"kb_used_meta":4974409,"kb_avail":4092850128,"utilization":30.16228878582811,"var":0.83393784878186838,"pgs":82,"status":"up"},{"id":-41,"name":"sf-sby001-hyperconverge014-rack002","type":"host","type_id":1,"pool_weights":{},"reweight":-1,"kb":35163090944,"kb_used":11074894128,"kb_used_data":11046565232,"kb_used_omap":406693,"kb_used_meta":27921813,"kb_avail":24088196816,"utilization":31.495792408118056,"var":0.8708070383188975,"pgs":0,"children":[118,110,96,76,54,24]},{"id":24,"device_class":"general","name":"osd.24","type":"osd","type_id":0,"crush_weight":5.4579925537109375,"depth":3,"pool_weights":{},"reweight":1,"kb":5860511744,"kb_used":2149518528,"kb_used_data":2143942384,"kb_used_omap":66422,"kb_used_meta":5509705,"kb_avail":3710993216,"utilization":36.678000521041184,"var":1.0140865989755012,"pgs":87,"status":"up"},{"id":54,"device_class":"general","name":"osd.54","type":"osd","type_id":0,"crush_weight":5.4579925537109375,"depth":3,"pool_weights":{},"reweight":1,"kb":5860515840,"kb_used":2056464208,"kb_used_data":2051287488,"kb_used_omap":109326,"kb_used_meta":5067377,"kb_avail":3804051632,"utilization":35.090156978400046,"var":0.97018532750519781,"pgs":88,"status":"up"},{"id":76,"device_class":"general","name":"osd.76","type":"osd","type_id":0,"crush_weight":5.4579925537109375,"depth":3,"pool_weights":{},"reweight":1,"kb":5860515840,"kb_used":1230328144,"kb_used_data":1227347840,"kb_used_omap":24971,"kb_used_meta":2955316,"kb_avail":4630187696,"utilization":20.993512816783035,"var":0.58043622090868996,"pgs":70,"status":"up"},{"id":96,"device_class":"general","name":"osd.96","type":"osd","type_id":0,"crush_weight":5.4579925537109375,"depth":3,"pool_weights":{},"reweight":1,"kb":5860515840,"kb_used":1812851728,"kb_used_data":1808173536,"kb_used_omap":87153,"kb_used_meta":4590798,"kb_avail":4047664112,"utilization":30.933313337823858,"var":0.85525541393134885,"pgs":71,"status":"up"},{"id":110,"device_class":"general","name":"osd.110","type":"osd","type_id":0,"crush_weight":5.4579925537109375,"depth":3,"pool_weights":{},"reweight":1,"kb":5860515840,"kb_used":1960297632,"kb_used_data":1955357584,"kb_used_omap":60943,"kb_used_meta":4879088,"kb_avail":3900218208,"utilization":33.449233574633595,"var":0.92481648487294443,"pgs":69,"status":"up"},{"id":118,"device_class":"general","name":"osd.118","type":"osd","type_id":0,"crush_weight":5.4579925537109375,"depth":3,"pool_weights":{},"reweight":1,"kb":5860515840,"kb_used":1865433888,"kb_used_data":1860456400,"kb_used_omap":57878,"kb_used_meta":4919529,"kb_avail":3995081952,"utilization":31.830540841947457,"var":0.88006228385987761,"pgs":85,"status":"up"},{"id":-19,"name":"sf-sby001-hyperconverge015-rack002","type":"host","type_id":1,"pool_weights":{},"reweight":-1,"kb":35163090944,"kb_used":12221454196,"kb_used_data":12187779164,"kb_used_omap":151066,"kb_used_meta":33520864,"kb_avail":22941636748,"utilization":34.756484335986364,"var":0.9609598258336346,"pgs":0,"children":[361,360,113,82,61,7]},{"id":7,"device_class":"general","name":"osd.7","type":"osd","type_id":0,"crush_weight":5.4579925537109375,"depth":3,"pool_weights":{},"reweight":1,"kb":5860511744,"kb_used":1964896544,"kb_used_data":1959394336,"kb_used_omap":45850,"kb_used_meta":5456101,"kb_avail":3895615200,"utilization":33.527729826864757,"var":0.92698677759137538,"pgs":88,"status":"up"},{"id":61,"device_class":"general","name":"osd.61","type":"osd","type_id":0,"crush_weight":5.4579925537109375,"depth":3,"pool_weights":{},"reweight":1,"kb":5860515840,"kb_used":2103597888,"kb_used_data":2097926416,"kb_used_omap":6626,"kb_used_meta":5662045,"kb_avail":3756917952,"utilization":35.894415191956888,"var":0.99242174892670054,"pgs":84,"status":"up"},{"id":82,"device_class":"general","name":"osd.82","type":"osd","type_id":0,"crush_weight":5.4579925537109375,"depth":3,"pool_weights":{},"reweight":1,"kb":5860515840,"kb_used":2160836496,"kb_used_data":2154992896,"kb_used_omap":70662,"kb_used_meta":5772921,"kb_avail":3699679344,"utilization":36.871097271874277,"var":1.0194254076494698,"pgs":99,"status":"up"},{"id":113,"device_class":"general","name":"osd.113","type":"osd","type_id":0,"crush_weight":5.4579925537109375,"depth":3,"pool_weights":{},"reweight":1,"kb":5860515840,"kb_used":1582956712,"kb_used_data":1577209760,"kb_used_omap":9607,"kb_used_meta":5737336,"kb_avail":4277559128,"utilization":27.010535509447578,"var":0.74679703642975881,"pgs":82,"status":"up"},{"id":360,"device_class":"general","name":"osd.360","type":"osd","type_id":0,"crush_weight":5.4579925537109375,"depth":3,"pool_weights":{},"reweight":1,"kb":5860515840,"kb_used":1867089552,"kb_used_data":1862669192,"kb_used_omap":5098,"kb_used_meta":4415253,"kb_avail":3993426288,"utilization":31.858792006950704,"var":0.88084338226841286,"pgs":81,"status":"up"},{"id":361,"device_class":"general","name":"osd.361","type":"osd","type_id":0,"crush_weight":5.4579925537109375,"depth":3,"pool_weights":{},"reweight":1,"kb":5860515840,"kb_used":2542077004,"kb_used_data":2535586564,"kb_used_omap":13223,"kb_used_meta":6477208,"kb_avail":3318438836,"utilization":43.376335350029528,"var":1.1992845783918316,"pgs":95,"status":"up"},{"id":-47,"name":"sf-sby001-hyperconverge016-rack002","type":"host","type_id":1,"pool_weights":{},"reweight":-1,"kb":29302575104,"kb_used":10573925568,"kb_used_data":10546987888,"kb_used_omap":482752,"kb_used_meta":26454715,"kb_avail":18728649536,"utilization":36.085311719093887,"var":0.99769972502164983,"pgs":0,"children":[116,106,92,74,53,34]},{"id":34,"device_class":"general","name":"osd.34","type":"osd","type_id":0,"crush_weight":5.4579925537109375,"depth":3,"pool_weights":{},"reweight":1,"kb":5860511744,"kb_used":1913538704,"kb_used_data":1908631808,"kb_used_omap":96275,"kb_used_meta":4810604,"kb_avail":3946973040,"utilization":32.651392704043012,"var":0.90275749246640058,"pgs":88,"status":"up"},{"id":53,"device_class":"general","name":"osd.53","type":"osd","type_id":0,"crush_weight":5.4579925537109375,"depth":3,"pool_weights":{},"reweight":0.95001220703125,"kb":5860515840,"kb_used":2342271056,"kb_used_data":2336586432,"kb_used_omap":88871,"kb_used_meta":5595736,"kb_avail":3518244784,"utilization":39.966977650895657,"var":1.1050214259655644,"pgs":81,"status":"up"},{"id":74,"device_class":"general","name":"osd.74","type":"osd","type_id":0,"crush_weight":5.4579925537109375,"depth":3,"pool_weights":{},"reweight":1,"kb":5860515840,"kb_used":2015238880,"kb_used_data":2009910880,"kb_used_omap":108486,"kb_used_meta":5219449,"kb_avail":3845276960,"utilization":34.386715009714912,"var":0.95073631001605441,"pgs":92,"status":"up"},{"id":92,"device_class":"general","name":"osd.92","type":"osd","type_id":0,"crush_weight":5.4579925537109375,"depth":3,"pool_weights":{},"reweight":1,"kb":5860515840,"kb_used":2005431712,"kb_used_data":2000163856,"kb_used_omap":85870,"kb_used_meta":5181969,"kb_avail":3855084128,"utilization":34.219371924775821,"var":0.94610954799366453,"pgs":92,"status":"up"},{"id":106,"device_class":"general","name":"osd.106","type":"osd","type_id":0,"crush_weight":5.4579925537109375,"depth":3,"pool_weights":{},"reweight":0,"kb":0,"kb_used":0,"kb_used_data":0,"kb_used_omap":0,"kb_used_meta":0,"kb_avail":0,"utilization":0,"var":0,"pgs":0,"status":"down"},{"id":116,"device_class":"general","name":"osd.116","type":"osd","type_id":0,"crush_weight":5.4579925537109375,"depth":3,"pool_weights":{},"reweight":0.95001220703125,"kb":5860515840,"kb_used":2297445216,"kb_used_data":2291694912,"kb_used_omap":103250,"kb_used_meta":5646957,"kb_avail":3563070624,"utilization":39.202098906023942,"var":1.0838737823100539,"pgs":88,"status":"up"},{"id":-4,"name":"01-03","type":"rack","type_id":3,"pool_weights":{},"reweight":-1,"kb":246141640704,"kb_used":84166951104,"kb_used_data":83953146848,"kb_used_omap":2308654,"kb_used_meta":211474921,"kb_avail":161974689600,"utilization":34.194519408934866,"var":0.94542241666406324,"pgs":0,"children":[-49,-35,-21,-3,-7,-39,-43]},{"id":-43,"name":"sf-sby001-hyperconverge003-rack001","type":"host","type_id":1,"pool_weights":{},"reweight":-1,"kb":35163090944,"kb_used":12592232512,"kb_used_data":12562377392,"kb_used_omap":85424,"kb_used_meta":29765322,"kb_avail":22570858432,"utilization":35.810937474336725,"var":0.99011372685491106,"pgs":0,"children":[114,105,87,67,45,27]},{"id":27,"device_class":"general","name":"osd.27","type":"osd","type_id":0,"crush_weight":5.4579925537109375,"depth":3,"pool_weights":{},"reweight":1,"kb":5860511744,"kb_used":2108415696,"kb_used_data":2103602752,"kb_used_omap":12514,"kb_used_meta":4800413,"kb_avail":3752096048,"utilization":35.976648253603429,"var":0.9946953583008169,"pgs":91,"status":"up"},{"id":45,"device_class":"general","name":"osd.45","type":"osd","type_id":0,"crush_weight":5.4579925537109375,"depth":3,"pool_weights":{},"reweight":1,"kb":5860515840,"kb_used":1859944368,"kb_used_data":1855122464,"kb_used_omap":12752,"kb_used_meta":4809135,"kb_avail":4000571472,"utilization":31.736871271727509,"var":0.87747247376820292,"pgs":70,"status":"up"},{"id":67,"device_class":"general","name":"osd.67","type":"osd","type_id":0,"crush_weight":5.4579925537109375,"depth":3,"pool_weights":{},"reweight":1,"kb":5860515840,"kb_used":2251551184,"kb_used_data":2246152416,"kb_used_omap":18969,"kb_used_meta":5379750,"kb_avail":3608964656,"utilization":38.418993233196346,"var":1.062222193970592,"pgs":79,"status":"up"},{"id":87,"device_class":"general","name":"osd.87","type":"osd","type_id":0,"crush_weight":5.4579925537109375,"depth":3,"pool_weights":{},"reweight":1,"kb":5860515840,"kb_used":2112132896,"kb_used_data":2107207760,"kb_used_omap":18069,"kb_used_meta":4902826,"kb_avail":3748382944,"utilization":36.040050972714376,"var":0.99644833956685219,"pgs":82,"status":"up"},{"id":105,"device_class":"general","name":"osd.105","type":"osd","type_id":0,"crush_weight":5.4579925537109375,"depth":3,"pool_weights":{},"reweight":1,"kb":5860515840,"kb_used":2008328912,"kb_used_data":2003724672,"kb_used_omap":7716,"kb_used_meta":4596507,"kb_avail":3852186928,"utilization":34.268807846102504,"var":0.94747637019261832,"pgs":90,"status":"up"},{"id":114,"device_class":"general","name":"osd.114","type":"osd","type_id":0,"crush_weight":5.4579925537109375,"depth":3,"pool_weights":{},"reweight":1,"kb":5860515840,"kb_used":2251859456,"kb_used_data":2246567328,"kb_used_omap":15404,"kb_used_meta":5276691,"kb_avail":3608656384,"utilization":38.424253384493881,"var":1.0623676285325538,"pgs":95,"status":"up"},{"id":-39,"name":"sf-sby001-hyperconverge012-rack002","type":"host","type_id":1,"pool_weights":{},"reweight":-1,"kb":35163090944,"kb_used":11291617776,"kb_used_data":11265005488,"kb_used_omap":90862,"kb_used_meta":26520908,"kb_avail":23871473168,"utilization":32.112130853293849,"var":0.88784778614613014,"pgs":0,"children":[117,109,95,75,55,25]},{"id":25,"device_class":"general","name":"osd.25","type":"osd","type_id":0,"crush_weight":5.4579925537109375,"depth":3,"pool_weights":{},"reweight":1,"kb":5860511744,"kb_used":2067309232,"kb_used_data":2062202336,"kb_used_omap":26572,"kb_used_meta":5080307,"kb_avail":3793202512,"utilization":35.275234012055584,"var":0.97530240414356439,"pgs":90,"status":"up"},{"id":55,"device_class":"general","name":"osd.55","type":"osd","type_id":0,"crush_weight":5.4579925537109375,"depth":3,"pool_weights":{},"reweight":1,"kb":5860515840,"kb_used":1964967664,"kb_used_data":1960057440,"kb_used_omap":18026,"kb_used_meta":4892181,"kb_avail":3895548176,"utilization":33.528919938897396,"var":0.92701968223847808,"pgs":87,"status":"up"},{"id":75,"device_class":"general","name":"osd.75","type":"osd","type_id":0,"crush_weight":5.4579925537109375,"depth":3,"pool_weights":{},"reweight":1,"kb":5860515840,"kb_used":1231899760,"kb_used_data":1229247568,"kb_used_omap":9934,"kb_used_meta":2642225,"kb_avail":4628616080,"utilization":21.020329841818157,"var":0.58117766769766921,"pgs":76,"status":"up"},{"id":95,"device_class":"general","name":"osd.95","type":"osd","type_id":0,"crush_weight":5.4579925537109375,"depth":3,"pool_weights":{},"reweight":1,"kb":5860515840,"kb_used":1378332576,"kb_used_data":1375133712,"kb_used_omap":7822,"kb_used_meta":3191025,"kb_avail":4482183264,"utilization":23.518963409200513,"var":0.65026079056253772,"pgs":71,"status":"up"},{"id":109,"device_class":"general","name":"osd.109","type":"osd","type_id":0,"crush_weight":5.4579925537109375,"depth":3,"pool_weights":{},"reweight":1,"kb":5860515840,"kb_used":2398892896,"kb_used_data":2393203024,"kb_used_omap":21477,"kb_used_meta":5668378,"kb_avail":3461622944,"utilization":40.933135606028834,"var":1.1317341098871447,"pgs":94,"status":"up"},{"id":117,"device_class":"general","name":"osd.117","type":"osd","type_id":0,"crush_weight":5.4579925537109375,"depth":3,"pool_weights":{},"reweight":1,"kb":5860515840,"kb_used":2250215648,"kb_used_data":2245161408,"kb_used_omap":7031,"kb_used_meta":5046792,"kb_avail":3610300192,"utilization":38.396204522501556,"var":1.0615921234706949,"pgs":86,"status":"up"},{"id":-7,"name":"sf-sby001-hyperconverge017-rack003","type":"host","type_id":1,"pool_weights":{},"reweight":-1,"kb":35163090944,"kb_used":11658662768,"kb_used_data":11626113424,"kb_used_omap":575945,"kb_used_meta":31972913,"kb_avail":23504428176,"utilization":33.155966824894151,"var":0.91670813990835831,"pgs":0,"children":[121,66,47,28,13,0]},{"id":0,"device_class":"general","name":"osd.0","type":"osd","type_id":0,"crush_weight":5.4579925537109375,"depth":3,"pool_weights":{},"reweight":1,"kb":5860515840,"kb_used":1958136416,"kb_used_data":1951843920,"kb_used_omap":68553,"kb_used_meta":6223926,"kb_avail":3902379424,"utilization":33.412356001754276,"var":0.92379688042536268,"pgs":76,"status":"up"},{"id":13,"device_class":"general","name":"osd.13","type":"osd","type_id":0,"crush_weight":5.4579925537109375,"depth":3,"pool_weights":{},"reweight":1,"kb":5860515840,"kb_used":2247889168,"kb_used_data":2242442432,"kb_used_omap":117795,"kb_used_meta":5328924,"kb_avail":3612626672,"utilization":38.356506993077254,"var":1.0604945518465676,"pgs":87,"status":"up"},{"id":28,"device_class":"general","name":"osd.28","type":"osd","type_id":0,"crush_weight":5.4579925537109375,"depth":3,"pool_weights":{},"reweight":1,"kb":5860515840,"kb_used":2206491328,"kb_used_data":2200613104,"kb_used_omap":109301,"kb_used_meta":5768522,"kb_avail":3654024512,"utilization":37.650121392727094,"var":1.0409641477665137,"pgs":95,"status":"up"},{"id":47,"device_class":"general","name":"osd.47","type":"osd","type_id":0,"crush_weight":5.4579925537109375,"depth":3,"pool_weights":{},"reweight":1,"kb":5860515840,"kb_used":1614336560,"kb_used_data":1609667168,"kb_used_omap":104938,"kb_used_meta":4564437,"kb_avail":4246179280,"utilization":27.545980662343879,"var":0.76160121730998509,"pgs":65,"status":"up"},{"id":66,"device_class":"general","name":"osd.66","type":"osd","type_id":0,"crush_weight":5.4579925537109375,"depth":3,"pool_weights":{},"reweight":1,"kb":5860515840,"kb_used":1871309712,"kb_used_data":1865878272,"kb_used_omap":93441,"kb_used_meta":5337982,"kb_avail":3989206128,"utilization":31.9308020503533,"var":0.8828343419436635,"pgs":81,"status":"up"},{"id":121,"device_class":"general","name":"osd.121","type":"osd","type_id":0,"crush_weight":5.4579925537109375,"depth":3,"pool_weights":{},"reweight":1,"kb":5860511744,"kb_used":1760499584,"kb_used_data":1755668528,"kb_used_omap":81917,"kb_used_meta":4749122,"kb_avail":4100012160,"utilization":30.040031671336585,"var":0.83055763994621645,"pgs":73,"status":"up"},{"id":-3,"name":"sf-sby001-hyperconverge018-rack003","type":"host","type_id":1,"pool_weights":{},"reweight":-1,"kb":35163090944,"kb_used":12337622208,"kb_used_data":12306835728,"kb_used_omap":504311,"kb_used_meta":30277315,"kb_avail":22825468736,"utilization":35.08685350684511,"var":0.97009399193111068,"pgs":0,"children":[122,68,48,30,14,1]},{"id":1,"device_class":"general","name":"osd.1","type":"osd","type_id":0,"crush_weight":5.4579925537109375,"depth":3,"pool_weights":{},"reweight":1,"kb":5860515840,"kb_used":2498598592,"kb_used_data":2492343072,"kb_used_omap":103067,"kb_used_meta":6152356,"kb_avail":3361917248,"utilization":42.634448233143928,"var":1.1787726155667408,"pgs":108,"status":"up"},{"id":14,"device_class":"general","name":"osd.14","type":"osd","type_id":0,"crush_weight":5.4579925537109375,"depth":3,"pool_weights":{},"reweight":1,"kb":5860515840,"kb_used":1571314992,"kb_used_data":1567911328,"kb_used_omap":52973,"kb_used_meta":3350674,"kb_avail":4289200848,"utilization":26.811888831956473,"var":0.74130478138005462,"pgs":79,"status":"up"},{"id":30,"device_class":"general","name":"osd.30","type":"osd","type_id":0,"crush_weight":5.4579925537109375,"depth":3,"pool_weights":{},"reweight":1,"kb":5860515840,"kb_used":2150872864,"kb_used_data":2145405376,"kb_used_omap":76174,"kb_used_meta":5391217,"kb_avail":3709642976,"utilization":36.701084387820714,"var":1.014724830057379,"pgs":78,"status":"up"},{"id":48,"device_class":"general","name":"osd.48","type":"osd","type_id":0,"crush_weight":5.4579925537109375,"depth":3,"pool_weights":{},"reweight":1,"kb":5860515840,"kb_used":1566795440,"kb_used_data":1562387360,"kb_used_omap":82227,"kb_used_meta":4325836,"kb_avail":4293720400,"utilization":26.734770159754401,"var":0.73917257649156731,"pgs":82,"status":"up"},{"id":68,"device_class":"general","name":"osd.68","type":"osd","type_id":0,"crush_weight":5.4579925537109375,"depth":3,"pool_weights":{},"reweight":1,"kb":5860515840,"kb_used":2399369168,"kb_used_data":2393547776,"kb_used_omap":73908,"kb_used_meta":5746955,"kb_avail":3461146672,"utilization":40.941262399181568,"var":1.1319588023979621,"pgs":81,"status":"up"},{"id":122,"device_class":"general","name":"osd.122","type":"osd","type_id":0,"crush_weight":5.4579925537109375,"depth":3,"pool_weights":{},"reweight":1,"kb":5860511744,"kb_used":2150671152,"kb_used_data":2145240816,"kb_used_omap":115962,"kb_used_meta":5310277,"kb_avail":3709840592,"utilization":36.697668155035437,"var":1.0146303768200893,"pgs":83,"status":"up"},{"id":-21,"name":"sf-sby001-hyperconverge019-rack003","type":"host","type_id":1,"pool_weights":{},"reweight":-1,"kb":35163095040,"kb_used":11160485984,"kb_used_data":11130275120,"kb_used_omap":254602,"kb_used_meta":29954352,"kb_avail":24002609056,"utilization":31.739202625094062,"var":0.877536931867688,"pgs":0,"children":[102,83,73,62,18,5]},{"id":5,"device_class":"general","name":"osd.5","type":"osd","type_id":0,"crush_weight":5.4579925537109375,"depth":3,"pool_weights":{},"reweight":1,"kb":5860515840,"kb_used":1763174320,"kb_used_data":1758449760,"kb_used_omap":6021,"kb_used_meta":4718522,"kb_avail":4097341520,"utilization":30.085650617403672,"var":0.83181892903528443,"pgs":81,"status":"up"},{"id":18,"device_class":"general","name":"osd.18","type":"osd","type_id":0,"crush_weight":5.4579925537109375,"depth":3,"pool_weights":{},"reweight":1,"kb":5860515840,"kb_used":1904287328,"kb_used_data":1899355120,"kb_used_omap":62165,"kb_used_meta":4868330,"kb_avail":3956228512,"utilization":32.493510468866852,"var":0.89839230743357434,"pgs":75,"status":"up"},{"id":62,"device_class":"general","name":"osd.62","type":"osd","type_id":0,"crush_weight":5.4579925537109375,"depth":3,"pool_weights":{},"reweight":1,"kb":5860515840,"kb_used":1611788256,"kb_used_data":1607030672,"kb_used_omap":44746,"kb_used_meta":4712821,"kb_avail":4248727584,"utilization":27.502498073616675,"var":0.76039899499986419,"pgs":81,"status":"up"},{"id":73,"device_class":"general","name":"osd.73","type":"osd","type_id":0,"crush_weight":5.4579925537109375,"depth":3,"pool_weights":{},"reweight":1,"kb":5860515840,"kb_used":1619084576,"kb_used_data":1614300080,"kb_used_omap":5732,"kb_used_meta":4778651,"kb_avail":4241431264,"utilization":27.626997694455511,"var":0.7638412054605398,"pgs":62,"status":"up"},{"id":83,"device_class":"general","name":"osd.83","type":"osd","type_id":0,"crush_weight":5.4579925537109375,"depth":3,"pool_weights":{},"reweight":1,"kb":5860515840,"kb_used":1577963568,"kb_used_data":1573569488,"kb_used_omap":43464,"kb_used_meta":4350583,"kb_avail":4282552272,"utilization":26.925335773855704,"var":0.74444140338344778,"pgs":83,"status":"up"},{"id":102,"device_class":"general","name":"osd.102","type":"osd","type_id":0,"crush_weight":5.4579925537109375,"depth":3,"pool_weights":{},"reweight":1,"kb":5860515840,"kb_used":2684187936,"kb_used_data":2677570000,"kb_used_omap":92474,"kb_used_meta":6525445,"kb_avail":3176327904,"utilization":45.801223122365968,"var":1.2663287508934173,"pgs":99,"status":"up"},{"id":-35,"name":"sf-sby001-hyperconverge020-rack003","type":"host","type_id":1,"pool_weights":{},"reweight":-1,"kb":35163090944,"kb_used":12685804960,"kb_used_data":12654530192,"kb_used_omap":485606,"kb_used_meta":30786517,"kb_avail":22477285984,"utilization":36.077047322725825,"var":0.99747122800746102,"pgs":0,"children":[112,103,85,64,43,23]},{"id":23,"device_class":"general","name":"osd.23","type":"osd","type_id":0,"crush_weight":5.4579925537109375,"depth":3,"pool_weights":{},"reweight":1,"kb":5860511744,"kb_used":2447411824,"kb_used_data":2441383840,"kb_used_omap":92956,"kb_used_meta":5935011,"kb_avail":3413099920,"utilization":41.761059970670026,"var":1.1546248615971866,"pgs":87,"status":"up"},{"id":43,"device_class":"general","name":"osd.43","type":"osd","type_id":0,"crush_weight":5.4579925537109375,"depth":3,"pool_weights":{},"reweight":1,"kb":5860515840,"kb_used":1862868768,"kb_used_data":1858094288,"kb_used_omap":47369,"kb_used_meta":4727094,"kb_avail":3997647072,"utilization":31.78677131602122,"var":0.87885212820649505,"pgs":84,"status":"up"},{"id":64,"device_class":"general","name":"osd.64","type":"osd","type_id":0,"crush_weight":5.4579925537109375,"depth":3,"pool_weights":{},"reweight":1,"kb":5860515840,"kb_used":1961057232,"kb_used_data":1956338096,"kb_used_omap":109423,"kb_used_meta":4609680,"kb_avail":3899458608,"utilization":33.462194891021745,"var":0.92517484402741268,"pgs":82,"status":"up"},{"id":85,"device_class":"general","name":"osd.85","type":"osd","type_id":0,"crush_weight":5.4579925537109375,"depth":3,"pool_weights":{},"reweight":1,"kb":5860515840,"kb_used":1815009632,"kb_used_data":1810493392,"kb_used_omap":77486,"kb_used_meta":4438481,"kb_avail":4045506208,"utilization":30.970134396906605,"var":0.85627345586508186,"pgs":82,"status":"up"},{"id":103,"device_class":"general","name":"osd.103","type":"osd","type_id":0,"crush_weight":5.4579925537109375,"depth":3,"pool_weights":{},"reweight":1,"kb":5860515840,"kb_used":2488626064,"kb_used_data":2482685984,"kb_used_omap":84850,"kb_used_meta":5852941,"kb_avail":3371889776,"utilization":42.464283553578795,"var":1.1740678410775489,"pgs":87,"status":"up"},{"id":112,"device_class":"general","name":"osd.112","type":"osd","type_id":0,"crush_weight":5.4579925537109375,"depth":3,"pool_weights":{},"reweight":1,"kb":5860515840,"kb_used":2110831440,"kb_used_data":2105534592,"kb_used_omap":73522,"kb_used_meta":5223310,"kb_avail":3749684400,"utilization":36.017843780795921,"var":0.99583434710800856,"pgs":107,"status":"up"},{"id":-49,"name":"sf-sby001-hyperconverge021-rack003","type":"host","type_id":1,"pool_weights":{},"reweight":-1,"kb":35163090944,"kb_used":12440524896,"kb_used_data":12408009504,"kb_used_omap":311904,"kb_used_meta":32197594,"kb_avail":22722566048,"utilization":35.379497541363811,"var":0.97818511984047674,"pgs":0,"children":[115,107,94,77,57,36]},{"id":36,"device_class":"general","name":"osd.36","type":"osd","type_id":0,"crush_weight":5.4579925537109375,"depth":3,"pool_weights":{},"reweight":1,"kb":5860511744,"kb_used":2347775600,"kb_used_data":2341747872,"kb_used_omap":79072,"kb_used_meta":5944543,"kb_avail":3512736144,"utilization":40.060931579970912,"var":1.1076190981135228,"pgs":89,"status":"up"},{"id":57,"device_class":"general","name":"osd.57","type":"osd","type_id":0,"crush_weight":5.4579925537109375,"depth":3,"pool_weights":{},"reweight":1,"kb":5860515840,"kb_used":1866660080,"kb_used_data":1861269984,"kb_used_omap":35278,"kb_used_meta":5354801,"kb_avail":3993855760,"utilization":31.851463778314777,"var":0.88064076875763386,"pgs":83,"status":"up"},{"id":77,"device_class":"general","name":"osd.77","type":"osd","type_id":0,"crush_weight":5.4579925537109375,"depth":3,"pool_weights":{},"reweight":1,"kb":5860515840,"kb_used":2009112528,"kb_used_data":2003948464,"kb_used_omap":64207,"kb_used_meta":5099824,"kb_avail":3851403312,"utilization":34.28217895576919,"var":0.94784605945958467,"pgs":84,"status":"up"},{"id":94,"device_class":"general","name":"osd.94","type":"osd","type_id":0,"crush_weight":5.4579925537109375,"depth":3,"pool_weights":{},"reweight":1,"kb":5860515840,"kb_used":1815494768,"kb_used_data":1810511968,"kb_used_omap":7905,"kb_used_meta":4974878,"kb_avail":4045021072,"utilization":30.978412439543888,"var":0.85650233017624833,"pgs":72,"status":"up"},{"id":107,"device_class":"general","name":"osd.107","type":"osd","type_id":0,"crush_weight":5.4579925537109375,"depth":3,"pool_weights":{},"reweight":1,"kb":5860515840,"kb_used":2440130464,"kb_used_data":2434276384,"kb_used_omap":65519,"kb_used_meta":5786896,"kb_avail":3420385376,"utilization":41.636786430049135,"var":1.1511889018839905,"pgs":92,"status":"up"},{"id":115,"device_class":"general","name":"osd.115","type":"osd","type_id":0,"crush_weight":5.4579925537109375,"depth":3,"pool_weights":{},"reweight":1,"kb":5860515840,"kb_used":1961351456,"kb_used_data":1956254832,"kb_used_omap":59923,"kb_used_meta":5036652,"kb_avail":3899164384,"utilization":33.467215336457478,"var":0.92531365111517483,"pgs":87,"status":"up"},{"id":-83,"name":"default-rack","type":"rack","type_id":3,"pool_weights":{},"reweight":-1,"kb":105489285120,"kb_used":50356594172,"kb_used_data":50221177204,"kb_used_omap":208886,"kb_used_meta":135199032,"kb_avail":55132690948,"utilization":47.736217109364745,"var":1.3198281631688478,"pgs":0,"children":[-485,-481,-82,-477,-385,-393,-401,-413,-421,-425,-433,-437,-445,-453,-461,-465,-469,-473,-457,-449,-441,-429,-417,-409,-405,-397,-389,-381,-377,-373,-369,-365,-361,-357,-353,-349,-345,-341,-337,-333,-321,-317,-313,-329,-325,-301,-297,-293,-289,-285,-281,-277,-273,-269,-229,-257,-253,-249,-245,-241,-237,-233]},{"id":-233,"name":"sf-sby001-hc0062-rack004","type":"host","type_id":1,"pool_weights":{},"reweight":-1,"kb":0,"kb_used":0,"kb_used_data":0,"kb_used_omap":0,"kb_used_meta":0,"kb_avail":0,"utilization":0,"var":0,"pgs":0,"children":[363,362]},{"id":-237,"name":"sf-sby001-hc0063-rack004","type":"host","type_id":1,"pool_weights":{},"reweight":-1,"kb":0,"kb_used":0,"kb_used_data":0,"kb_used_omap":0,"kb_used_meta":0,"kb_avail":0,"utilization":0,"var":0,"pgs":0,"children":[365,364]},{"id":-241,"name":"sf-sby001-hc0064-rack004","type":"host","type_id":1,"pool_weights":{},"reweight":-1,"kb":0,"kb_used":0,"kb_used_data":0,"kb_used_omap":0,"kb_used_meta":0,"kb_avail":0,"utilization":0,"var":0,"pgs":0,"children":[367,366]},{"id":-245,"name":"sf-sby001-hc0065-rack004","type":"host","type_id":1,"pool_weights":{},"reweight":-1,"kb":0,"kb_used":0,"kb_used_data":0,"kb_used_omap":0,"kb_used_meta":0,"kb_avail":0,"utilization":0,"var":0,"pgs":0,"children":[369,368]},{"id":-249,"name":"sf-sby001-hc0066-rack004","type":"host","type_id":1,"pool_weights":{},"reweight":-1,"kb":0,"kb_used":0,"kb_used_data":0,"kb_used_omap":0,"kb_used_meta":0,"kb_avail":0,"utilization":0,"var":0,"pgs":0,"children":[371,370]},{"id":-253,"name":"sf-sby001-hc0067-rack004","type":"host","type_id":1,"pool_weights":{},"reweight":-1,"kb":0,"kb_used":0,"kb_used_data":0,"kb_used_omap":0,"kb_used_meta":0,"kb_avail":0,"utilization":0,"var":0,"pgs":0,"children":[373,372]},{"id":-257,"name":"sf-sby001-hc0068-rack004","type":"host","type_id":1,"pool_weights":{},"reweight":-1,"kb":0,"kb_used":0,"kb_used_data":0,"kb_used_omap":0,"kb_used_meta":0,"kb_avail":0,"utilization":0,"var":0,"pgs":0,"children":[375,374]},{"id":-229,"name":"sf-sby001-hc0069-rack004","type":"host","type_id":1,"pool_weights":{},"reweight":-1,"kb":0,"kb_used":0,"kb_used_data":0,"kb_used_omap":0,"kb_used_meta":0,"kb_avail":0,"utilization":0,"var":0,"pgs":0,"children":[382,381,380,379,378,377,376,91]},{"id":-269,"name":"sf-sby001-hc0072-rack006","type":"host","type_id":1,"pool_weights":{},"reweight":-1,"kb":0,"kb_used":0,"kb_used_data":0,"kb_used_omap":0,"kb_used_meta":0,"kb_avail":0,"utilization":0,"var":0,"pgs":0,"children":[406,405,404,403,402,401,400,399]},{"id":-273,"name":"sf-sby001-hc0073-rack006","type":"host","type_id":1,"pool_weights":{},"reweight":-1,"kb":0,"kb_used":0,"kb_used_data":0,"kb_used_omap":0,"kb_used_meta":0,"kb_avail":0,"utilization":0,"var":0,"pgs":0,"children":[414,413,412,411,410,409,408,407]},{"id":-277,"name":"sf-sby001-hc0074-rack006","type":"host","type_id":1,"pool_weights":{},"reweight":-1,"kb":0,"kb_used":0,"kb_used_data":0,"kb_used_omap":0,"kb_used_meta":0,"kb_avail":0,"utilization":0,"var":0,"pgs":0,"children":[422,421,420,419,418,417,416,415]},{"id":-281,"name":"sf-sby001-hc0075-rack006","type":"host","type_id":1,"pool_weights":{},"reweight":-1,"kb":0,"kb_used":0,"kb_used_data":0,"kb_used_omap":0,"kb_used_meta":0,"kb_avail":0,"utilization":0,"var":0,"pgs":0,"children":[430,429,428,427,426,425,424,423]},{"id":-285,"name":"sf-sby001-hc0076-rack006","type":"host","type_id":1,"pool_weights":{},"reweight":-1,"kb":0,"kb_used":0,"kb_used_data":0,"kb_used_omap":0,"kb_used_meta":0,"kb_avail":0,"utilization":0,"var":0,"pgs":0,"children":[438,437,436,435,434,433,432,431]},{"id":-289,"name":"sf-sby001-hc0077-rack006","type":"host","type_id":1,"pool_weights":{},"reweight":-1,"kb":0,"kb_used":0,"kb_used_data":0,"kb_used_omap":0,"kb_used_meta":0,"kb_avail":0,"utilization":0,"var":0,"pgs":0,"children":[446,445,444,443,442,441,440,439]},{"id":-293,"name":"sf-sby001-hc0078-rack006","type":"host","type_id":1,"pool_weights":{},"reweight":-1,"kb":0,"kb_used":0,"kb_used_data":0,"kb_used_omap":0,"kb_used_meta":0,"kb_avail":0,"utilization":0,"var":0,"pgs":0,"children":[454,453,452,451,450,449,448,447]},{"id":-297,"name":"sf-sby001-hc0079-rack006","type":"host","type_id":1,"pool_weights":{},"reweight":-1,"kb":0,"kb_used":0,"kb_used_data":0,"kb_used_omap":0,"kb_used_meta":0,"kb_avail":0,"utilization":0,"var":0,"pgs":0,"children":[462,461,460,459,458,457,456,455]},{"id":-301,"name":"sf-sby001-hc0080-rack006","type":"host","type_id":1,"pool_weights":{},"reweight":-1,"kb":0,"kb_used":0,"kb_used_data":0,"kb_used_omap":0,"kb_used_meta":0,"kb_avail":0,"utilization":0,"var":0,"pgs":0,"children":[470,469,468,467,466,465,464,463]},{"id":-325,"name":"sf-sby001-hc0083-rack010","type":"host","type_id":1,"pool_weights":{},"reweight":-1,"kb":0,"kb_used":0,"kb_used_data":0,"kb_used_omap":0,"kb_used_meta":0,"kb_avail":0,"utilization":0,"var":0,"pgs":0,"children":[548,547,546,545,544,543,542,541,540,539,538,537,536,535,534,533,532,531,530,529]},{"id":-329,"name":"sf-sby001-hc0084-rack010","type":"host","type_id":1,"pool_weights":{},"reweight":-1,"kb":0,"kb_used":0,"kb_used_data":0,"kb_used_omap":0,"kb_used_meta":0,"kb_avail":0,"utilization":0,"var":0,"pgs":0,"children":[568,567,566,565,564,563,562,561,560,559,558,557,556,555,554,553,552,551,550,549]},{"id":-313,"name":"sf-sby001-hc0085-rack010","type":"host","type_id":1,"pool_weights":{},"reweight":-1,"kb":0,"kb_used":0,"kb_used_data":0,"kb_used_omap":0,"kb_used_meta":0,"kb_avail":0,"utilization":0,"var":0,"pgs":0,"children":[500,499,498,497,496,495,494,493,492,491,490,489,488,487]},{"id":-317,"name":"sf-sby001-hc0086-rack010","type":"host","type_id":1,"pool_weights":{},"reweight":-1,"kb":0,"kb_used":0,"kb_used_data":0,"kb_used_omap":0,"kb_used_meta":0,"kb_avail":0,"utilization":0,"var":0,"pgs":0,"children":[514,513,512,511,510,509,508,507,506,505,504,503,502,501]},{"id":-321,"name":"sf-sby001-hc0087-rack010","type":"host","type_id":1,"pool_weights":{},"reweight":-1,"kb":0,"kb_used":0,"kb_used_data":0,"kb_used_omap":0,"kb_used_meta":0,"kb_avail":0,"utilization":0,"var":0,"pgs":0,"children":[528,527,526,525,524,523,522,521,520,519,518,517,516,515]},{"id":-333,"name":"sf-sby001-hc0088-rack010","type":"host","type_id":1,"pool_weights":{},"reweight":-1,"kb":0,"kb_used":0,"kb_used_data":0,"kb_used_omap":0,"kb_used_meta":0,"kb_avail":0,"utilization":0,"var":0,"pgs":0,"children":[570,569]},{"id":-337,"name":"sf-sby001-hc0089-rack010","type":"host","type_id":1,"pool_weights":{},"reweight":-1,"kb":0,"kb_used":0,"kb_used_data":0,"kb_used_omap":0,"kb_used_meta":0,"kb_avail":0,"utilization":0,"var":0,"pgs":0,"children":[572,571]},{"id":-341,"name":"sf-sby001-hc0090-rack010","type":"host","type_id":1,"pool_weights":{},"reweight":-1,"kb":0,"kb_used":0,"kb_used_data":0,"kb_used_omap":0,"kb_used_meta":0,"kb_avail":0,"utilization":0,"var":0,"pgs":0,"children":[574,573]},{"id":-345,"name":"sf-sby001-hc0091-rack011","type":"host","type_id":1,"pool_weights":{},"reweight":-1,"kb":0,"kb_used":0,"kb_used_data":0,"kb_used_omap":0,"kb_used_meta":0,"kb_avail":0,"utilization":0,"var":0,"pgs":0,"children":[582,581,580,579,578,577,576,575]},{"id":-349,"name":"sf-sby001-hc0092-rack011","type":"host","type_id":1,"pool_weights":{},"reweight":-1,"kb":0,"kb_used":0,"kb_used_data":0,"kb_used_omap":0,"kb_used_meta":0,"kb_avail":0,"utilization":0,"var":0,"pgs":0,"children":[590,589,588,587,586,585,584,583]},{"id":-353,"name":"sf-sby001-hc0093-rack011","type":"host","type_id":1,"pool_weights":{},"reweight":-1,"kb":0,"kb_used":0,"kb_used_data":0,"kb_used_omap":0,"kb_used_meta":0,"kb_avail":0,"utilization":0,"var":0,"pgs":0,"children":[598,597,596,595,594,593,592,591]},{"id":-357,"name":"sf-sby001-hc0094-rack011","type":"host","type_id":1,"pool_weights":{},"reweight":-1,"kb":0,"kb_used":0,"kb_used_data":0,"kb_used_omap":0,"kb_used_meta":0,"kb_avail":0,"utilization":0,"var":0,"pgs":0,"children":[606,605,604,603,602,601,600,599]},{"id":-361,"name":"sf-sby001-hc0095-rack011","type":"host","type_id":1,"pool_weights":{},"reweight":-1,"kb":0,"kb_used":0,"kb_used_data":0,"kb_used_omap":0,"kb_used_meta":0,"kb_avail":0,"utilization":0,"var":0,"pgs":0,"children":[614,613,612,611,610,609,608,607]},{"id":-365,"name":"sf-sby001-hc0096-rack011","type":"host","type_id":1,"pool_weights":{},"reweight":-1,"kb":0,"kb_used":0,"kb_used_data":0,"kb_used_omap":0,"kb_used_meta":0,"kb_avail":0,"utilization":0,"var":0,"pgs":0,"children":[622,621,620,619,618,617,616,615]},{"id":-369,"name":"sf-sby001-hc0097-rack011","type":"host","type_id":1,"pool_weights":{},"reweight":-1,"kb":0,"kb_used":0,"kb_used_data":0,"kb_used_omap":0,"kb_used_meta":0,"kb_avail":0,"utilization":0,"var":0,"pgs":0,"children":[630,629,628,627,626,625,624,623]},{"id":-373,"name":"sf-sby001-hc0098-rack011","type":"host","type_id":1,"pool_weights":{},"reweight":-1,"kb":0,"kb_used":0,"kb_used_data":0,"kb_used_omap":0,"kb_used_meta":0,"kb_avail":0,"utilization":0,"var":0,"pgs":0,"children":[638,637,636,635,634,633,632,631]},{"id":-377,"name":"sf-sby001-hc0099-rack011","type":"host","type_id":1,"pool_weights":{},"reweight":-1,"kb":0,"kb_used":0,"kb_used_data":0,"kb_used_omap":0,"kb_used_meta":0,"kb_avail":0,"utilization":0,"var":0,"pgs":0,"children":[646,645,644,643,642,641,640,639]},{"id":-381,"name":"sf-sby001-hc0100-rack011","type":"host","type_id":1,"pool_weights":{},"reweight":-1,"kb":0,"kb_used":0,"kb_used_data":0,"kb_used_omap":0,"kb_used_meta":0,"kb_avail":0,"utilization":0,"var":0,"pgs":0,"children":[654,653,652,651,650,649,648,647]},{"id":-389,"name":"sf-sby001-hc0101-rack011","type":"host","type_id":1,"pool_weights":{},"reweight":-1,"kb":0,"kb_used":0,"kb_used_data":0,"kb_used_omap":0,"kb_used_meta":0,"kb_avail":0,"utilization":0,"var":0,"pgs":0,"children":[670,669,668,667,666,665,664,663]},{"id":-397,"name":"sf-sby001-hc0102-rack011","type":"host","type_id":1,"pool_weights":{},"reweight":-1,"kb":0,"kb_used":0,"kb_used_data":0,"kb_used_omap":0,"kb_used_meta":0,"kb_avail":0,"utilization":0,"var":0,"pgs":0,"children":[686,685,684,683,682,681,680,679]},{"id":-405,"name":"sf-sby001-hc0103-rack012","type":"host","type_id":1,"pool_weights":{},"reweight":-1,"kb":0,"kb_used":0,"kb_used_data":0,"kb_used_omap":0,"kb_used_meta":0,"kb_avail":0,"utilization":0,"var":0,"pgs":0,"children":[702,701,700,699,698,697,696,695]},{"id":-409,"name":"sf-sby001-hc0104-rack012","type":"host","type_id":1,"pool_weights":{},"reweight":-1,"kb":0,"kb_used":0,"kb_used_data":0,"kb_used_omap":0,"kb_used_meta":0,"kb_avail":0,"utilization":0,"var":0,"pgs":0,"children":[713,711,709,707,706,705,704,703]},{"id":-417,"name":"sf-sby001-hc0105-rack012","type":"host","type_id":1,"pool_weights":{},"reweight":-1,"kb":0,"kb_used":0,"kb_used_data":0,"kb_used_omap":0,"kb_used_meta":0,"kb_avail":0,"utilization":0,"var":0,"pgs":0,"children":[726,725,724,723,722,721,719,717]},{"id":-429,"name":"sf-sby001-hc0106-rack012","type":"host","type_id":1,"pool_weights":{},"reweight":-1,"kb":0,"kb_used":0,"kb_used_data":0,"kb_used_omap":0,"kb_used_meta":0,"kb_avail":0,"utilization":0,"var":0,"pgs":0,"children":[760,759,756,755,753,750,748,741]},{"id":-441,"name":"sf-sby001-hc0107-rack012","type":"host","type_id":1,"pool_weights":{},"reweight":-1,"kb":0,"kb_used":0,"kb_used_data":0,"kb_used_omap":0,"kb_used_meta":0,"kb_avail":0,"utilization":0,"var":0,"pgs":0,"children":[774,773,772,769,768,766,764,762]},{"id":-449,"name":"sf-sby001-hc0108-rack012","type":"host","type_id":1,"pool_weights":{},"reweight":-1,"kb":0,"kb_used":0,"kb_used_data":0,"kb_used_omap":0,"kb_used_meta":0,"kb_avail":0,"utilization":0,"var":0,"pgs":0,"children":[790,788,787,786,783,781,779,778]},{"id":-457,"name":"sf-sby001-hc0109-rack012","type":"host","type_id":1,"pool_weights":{},"reweight":-1,"kb":0,"kb_used":0,"kb_used_data":0,"kb_used_omap":0,"kb_used_meta":0,"kb_avail":0,"utilization":0,"var":0,"pgs":0,"children":[812,809,807,805,802,801,798,796]},{"id":-473,"name":"sf-sby001-hc0110-rack012","type":"host","type_id":1,"pool_weights":{},"reweight":-1,"kb":0,"kb_used":0,"kb_used_data":0,"kb_used_omap":0,"kb_used_meta":0,"kb_avail":0,"utilization":0,"var":0,"pgs":0,"children":[838,837,836,835,834,833,832,831]},{"id":-469,"name":"sf-sby001-hc0111-rack012","type":"host","type_id":1,"pool_weights":{},"reweight":-1,"kb":0,"kb_used":0,"kb_used_data":0,"kb_used_omap":0,"kb_used_meta":0,"kb_avail":0,"utilization":0,"var":0,"pgs":0,"children":[830,829,827,826,825,822,821,820]},{"id":-465,"name":"sf-sby001-hc0112-rack012","type":"host","type_id":1,"pool_weights":{},"reweight":-1,"kb":0,"kb_used":0,"kb_used_data":0,"kb_used_omap":0,"kb_used_meta":0,"kb_avail":0,"utilization":0,"var":0,"pgs":0,"children":[828,824,823,819,818,817,816,815]},{"id":-461,"name":"sf-sby001-hc0113-rack012","type":"host","type_id":1,"pool_weights":{},"reweight":-1,"kb":0,"kb_used":0,"kb_used_data":0,"kb_used_omap":0,"kb_used_meta":0,"kb_avail":0,"utilization":0,"var":0,"pgs":0,"children":[814,813,811,810,808,806,804,803]},{"id":-453,"name":"sf-sby001-hc0114-rack013","type":"host","type_id":1,"pool_weights":{},"reweight":-1,"kb":0,"kb_used":0,"kb_used_data":0,"kb_used_omap":0,"kb_used_meta":0,"kb_avail":0,"utilization":0,"var":0,"pgs":0,"children":[800,799,797,795,794,793,792,791]},{"id":-445,"name":"sf-sby001-hc0115-rack013","type":"host","type_id":1,"pool_weights":{},"reweight":-1,"kb":0,"kb_used":0,"kb_used_data":0,"kb_used_omap":0,"kb_used_meta":0,"kb_avail":0,"utilization":0,"var":0,"pgs":0,"children":[789,785,784,782,780,777,776,775]},{"id":-437,"name":"sf-sby001-hc0116-rack013","type":"host","type_id":1,"pool_weights":{},"reweight":-1,"kb":0,"kb_used":0,"kb_used_data":0,"kb_used_omap":0,"kb_used_meta":0,"kb_avail":0,"utilization":0,"var":0,"pgs":0,"children":[771,770,767,765,763,761,758,757]},{"id":-433,"name":"sf-sby001-hc0117-rack013","type":"host","type_id":1,"pool_weights":{},"reweight":-1,"kb":0,"kb_used":0,"kb_used_data":0,"kb_used_omap":0,"kb_used_meta":0,"kb_avail":0,"utilization":0,"var":0,"pgs":0,"children":[754,752,751,749,747,746,744,742]},{"id":-425,"name":"sf-sby001-hc0118-rack013","type":"host","type_id":1,"pool_weights":{},"reweight":-1,"kb":0,"kb_used":0,"kb_used_data":0,"kb_used_omap":0,"kb_used_meta":0,"kb_avail":0,"utilization":0,"var":0,"pgs":0,"children":[745,743,740,739,738,737,736,735]},{"id":-421,"name":"sf-sby001-hc0119-rack013","type":"host","type_id":1,"pool_weights":{},"reweight":-1,"kb":0,"kb_used":0,"kb_used_data":0,"kb_used_omap":0,"kb_used_meta":0,"kb_avail":0,"utilization":0,"var":0,"pgs":0,"children":[734,733,732,731,730,729,728,727]},{"id":-413,"name":"sf-sby001-hc0120-rack013","type":"host","type_id":1,"pool_weights":{},"reweight":-1,"kb":0,"kb_used":0,"kb_used_data":0,"kb_used_omap":0,"kb_used_meta":0,"kb_avail":0,"utilization":0,"var":0,"pgs":0,"children":[720,718,716,715,714,712,710,708]},{"id":-401,"name":"sf-sby001-hc0121-rack013","type":"host","type_id":1,"pool_weights":{},"reweight":-1,"kb":0,"kb_used":0,"kb_used_data":0,"kb_used_omap":0,"kb_used_meta":0,"kb_avail":0,"utilization":0,"var":0,"pgs":0,"children":[694,693,692,691,690,689,688,687]},{"id":-393,"name":"sf-sby001-hc0122-rack013","type":"host","type_id":1,"pool_weights":{},"reweight":-1,"kb":0,"kb_used":0,"kb_used_data":0,"kb_used_omap":0,"kb_used_meta":0,"kb_avail":0,"utilization":0,"var":0,"pgs":0,"children":[678,677,676,675,674,673,672,671]},{"id":-385,"name":"sf-sby001-hc0123-rack013","type":"host","type_id":1,"pool_weights":{},"reweight":-1,"kb":0,"kb_used":0,"kb_used_data":0,"kb_used_omap":0,"kb_used_meta":0,"kb_avail":0,"utilization":0,"var":0,"pgs":0,"children":[662,661,660,659,658,657,656,655]},{"id":-477,"name":"sf-sby001-hc0124-rack013","type":"host","type_id":1,"pool_weights":{},"reweight":-1,"kb":0,"kb_used":0,"kb_used_data":0,"kb_used_omap":0,"kb_used_meta":0,"kb_avail":0,"utilization":0,"var":0,"pgs":0,"children":[846,845,844,843,842,841,840,839]},{"id":-82,"name":"sf-sby001-hyperconverge024-rack004","type":"host","type_id":1,"pool_weights":{},"reweight":-1,"kb":35163095040,"kb_used":16209003552,"kb_used_data":16161894244,"kb_used_omap":63266,"kb_used_meta":47041624,"kb_avail":18954091488,"utilization":46.09663493376037,"var":1.2744964032969961,"pgs":0,"children":[851,850,849,848,847,59]},{"id":59,"device_class":"general","name":"osd.59","type":"osd","type_id":0,"crush_weight":5.4579925537109375,"depth":3,"pool_weights":{},"reweight":1,"kb":5860515840,"kb_used":2936376960,"kb_used_data":2927939408,"kb_used_omap":9123,"kb_used_meta":8428252,"kb_avail":2924138880,"utilization":50.104411286771644,"var":1.3853048506917252,"pgs":119,"status":"up"},{"id":847,"device_class":"general","name":"osd.847","type":"osd","type_id":0,"crush_weight":5.4579925537109375,"depth":3,"pool_weights":{},"reweight":1,"kb":5860515840,"kb_used":2403963436,"kb_used_data":2396738200,"kb_used_omap":10822,"kb_used_meta":7214393,"kb_avail":3456552404,"utilization":41.019655976222055,"var":1.134126256315656,"pgs":94,"status":"up"},{"id":848,"device_class":"general","name":"osd.848","type":"osd","type_id":0,"crush_weight":5.4579925537109375,"depth":3,"pool_weights":{},"reweight":1,"kb":5860515840,"kb_used":2832633912,"kb_used_data":2825055692,"kb_used_omap":10618,"kb_used_meta":7567557,"kb_avail":3027881928,"utilization":48.334207932112676,"var":1.3363616293077976,"pgs":113,"status":"up"},{"id":849,"device_class":"general","name":"osd.849","type":"osd","type_id":0,"crush_weight":5.4579925537109375,"depth":3,"pool_weights":{},"reweight":1,"kb":5860515840,"kb_used":2203805668,"kb_used_data":2196570588,"kb_used_omap":13704,"kb_used_meta":7221367,"kb_avail":3656710172,"utilization":37.604295051269752,"var":1.0396971245348272,"pgs":101,"status":"up"},{"id":850,"device_class":"general","name":"osd.850","type":"osd","type_id":0,"crush_weight":5.4579925537109375,"depth":3,"pool_weights":{},"reweight":1,"kb":5860515840,"kb_used":3285132288,"kb_used_data":3276240824,"kb_used_omap":8412,"kb_used_meta":8883043,"kb_avail":2575383552,"utilization":56.055343551464574,"var":1.5498383742019299,"pgs":124,"status":"up"},{"id":851,"device_class":"general","name":"osd.851","type":"osd","type_id":0,"crush_weight":5.4579925537109375,"depth":3,"pool_weights":{},"reweight":1,"kb":5860515840,"kb_used":2547091288,"kb_used_data":2539349532,"kb_used_omap":10587,"kb_used_meta":7727012,"kb_avail":3313424552,"utilization":43.461895804721514,"var":1.2016501847300403,"pgs":108,"status":"up"},{"id":-481,"name":"sf-sby001-hyperconverge025-rack004","type":"host","type_id":1,"pool_weights":{},"reweight":-1,"kb":35163095040,"kb_used":17831618376,"kb_used_data":17783191380,"kb_used_omap":69358,"kb_used_meta":48353804,"kb_avail":17331476664,"utilization":50.711174189062511,"var":1.4020808504525535,"pgs":0,"children":[857,856,855,854,853,852]},{"id":852,"device_class":"general","name":"osd.852","type":"osd","type_id":0,"crush_weight":5.4579925537109375,"depth":3,"pool_weights":{},"reweight":1,"kb":5860515840,"kb_used":3134450652,"kb_used_data":3125368724,"kb_used_omap":9226,"kb_used_meta":9072693,"kb_avail":2726065188,"utilization":53.484210905229801,"var":1.4787507706331549,"pgs":119,"status":"up"},{"id":853,"device_class":"general","name":"osd.853","type":"osd","type_id":0,"crush_weight":5.4579925537109375,"depth":3,"pool_weights":{},"reweight":1,"kb":5860515840,"kb_used":3423711304,"kb_used_data":3414862256,"kb_used_omap":14782,"kb_used_meta":8830721,"kb_avail":2436804536,"utilization":58.419965024785256,"var":1.6152162823125038,"pgs":130,"status":"up"},{"id":854,"device_class":"general","name":"osd.854","type":"osd","type_id":0,"crush_weight":5.4579925537109375,"depth":3,"pool_weights":{},"reweight":1,"kb":5860515840,"kb_used":2746453364,"kb_used_data":2738976100,"kb_used_omap":8463,"kb_used_meta":7468784,"kb_avail":3114062476,"utilization":46.863679563060444,"var":1.295703930107055,"pgs":115,"status":"up"},{"id":855,"device_class":"general","name":"osd.855","type":"osd","type_id":0,"crush_weight":5.4579925537109375,"depth":3,"pool_weights":{},"reweight":1,"kb":5860515840,"kb_used":2598646556,"kb_used_data":2591063316,"kb_used_omap":13204,"kb_used_meta":7570027,"kb_avail":3261869284,"utilization":44.341601097011967,"var":1.2259725942203776,"pgs":117,"status":"up"},{"id":856,"device_class":"general","name":"osd.856","type":"osd","type_id":0,"crush_weight":5.4579925537109375,"depth":3,"pool_weights":{},"reweight":1,"kb":5860515840,"kb_used":2896285972,"kb_used_data":2888516288,"kb_used_omap":9305,"kb_used_meta":7760358,"kb_avail":2964229868,"utilization":49.420324952146188,"var":1.3663909847603484,"pgs":126,"status":"up"},{"id":857,"device_class":"general","name":"osd.857","type":"osd","type_id":0,"crush_weight":5.4579925537109375,"depth":3,"pool_weights":{},"reweight":1,"kb":5860515840,"kb_used":3032070528,"kb_used_data":3024404696,"kb_used_omap":14378,"kb_used_meta":7651221,"kb_avail":2828445312,"utilization":51.737263592141403,"var":1.4304505406818817,"pgs":121,"status":"up"},{"id":-485,"name":"sf-sby001-hyperconverge026-rack004","type":"host","type_id":1,"pool_weights":{},"reweight":-1,"kb":35163095040,"kb_used":16315972244,"kb_used_data":16276091580,"kb_used_omap":76262,"kb_used_meta":39803604,"kb_avail":18847122796,"utilization":46.40084220527136,"var":1.2829072357569939,"pgs":0,"children":[863,862,861,860,859,858]},{"id":858,"device_class":"general","name":"osd.858","type":"osd","type_id":0,"crush_weight":5.4579925537109375,"depth":3,"pool_weights":{},"reweight":1,"kb":5860515840,"kb_used":2847062096,"kb_used_data":2839333620,"kb_used_omap":15616,"kb_used_meta":7712831,"kb_avail":3013453744,"utilization":48.580401004427621,"var":1.3431684642455954,"pgs":123,"status":"up"},{"id":859,"device_class":"general","name":"osd.859","type":"osd","type_id":0,"crush_weight":5.4579925537109375,"depth":3,"pool_weights":{},"reweight":1,"kb":5860515840,"kb_used":2839734464,"kb_used_data":2831630692,"kb_used_omap":11098,"kb_used_meta":8092645,"kb_avail":3020781376,"utilization":48.455367096149679,"var":1.3397114816129283,"pgs":127,"status":"up"},{"id":860,"device_class":"general","name":"osd.860","type":"osd","type_id":0,"crush_weight":5.4579925537109375,"depth":3,"pool_weights":{},"reweight":1,"kb":5860515840,"kb_used":3049452744,"kb_used_data":3042203360,"kb_used_omap":13579,"kb_used_meta":7235700,"kb_avail":2811063096,"utilization":52.033862329770614,"var":1.4386510096504748,"pgs":134,"status":"up"},{"id":861,"device_class":"general","name":"osd.861","type":"osd","type_id":0,"crush_weight":5.4579925537109375,"depth":3,"pool_weights":{},"reweight":1,"kb":5860515840,"kb_used":2541202852,"kb_used_data":2535302908,"kb_used_omap":10169,"kb_used_meta":5889734,"kb_avail":3319312988,"utilization":43.361419393416398,"var":1.198872176638808,"pgs":106,"status":"up"},{"id":862,"device_class":"general","name":"osd.862","type":"osd","type_id":0,"crush_weight":5.4579925537109375,"depth":3,"pool_weights":{},"reweight":1,"kb":5860515840,"kb_used":2110936824,"kb_used_data":2106142256,"kb_used_omap":12402,"kb_used_meta":4781581,"kb_avail":3749579016,"utilization":36.019641984279666,"var":0.99588406448706934,"pgs":106,"status":"up"},{"id":863,"device_class":"general","name":"osd.863","type":"osd","type_id":0,"crush_weight":5.4579925537109375,"depth":3,"pool_weights":{},"reweight":1,"kb":5860515840,"kb_used":2927583264,"kb_used_data":2921478744,"kb_used_omap":13398,"kb_used_meta":6091113,"kb_avail":2932932576,"utilization":49.954361423584174,"var":1.3811562179070884,"pgs":106,"status":"up"},{"id":-110,"name":"rack005","type":"rack","type_id":3,"pool_weights":{},"reweight":-1,"kb":0,"kb_used":0,"kb_used_data":0,"kb_used_omap":0,"kb_used_meta":0,"kb_avail":0,"utilization":0,"var":0,"pgs":0,"children":[-197,-169,-177,-189,-153,-185,-173,-109,-157]},{"id":-157,"name":"sf-sby001-hc0035-rack005","type":"host","type_id":1,"pool_weights":{},"reweight":-1,"kb":0,"kb_used":0,"kb_used_data":0,"kb_used_omap":0,"kb_used_meta":0,"kb_avail":0,"utilization":0,"var":0,"pgs":0,"children":[254,249,243,236,229,222,215,208]},{"id":-109,"name":"sf-sby001-hc0036-rack005","type":"host","type_id":1,"pool_weights":{},"reweight":-1,"kb":0,"kb_used":0,"kb_used_data":0,"kb_used_omap":0,"kb_used_meta":0,"kb_avail":0,"utilization":0,"var":0,"pgs":0,"children":[154,152,150,148,146,144,142,140]},{"id":-173,"name":"sf-sby001-hc0037-rack005","type":"host","type_id":1,"pool_weights":{},"reweight":-1,"kb":0,"kb_used":0,"kb_used_data":0,"kb_used_omap":0,"kb_used_meta":0,"kb_avail":0,"utilization":0,"var":0,"pgs":0,"children":[341,337,333,329,325,321,317,313,308,303,298,292,286,281]},{"id":-185,"name":"sf-sby001-hc0038-rack005","type":"host","type_id":1,"pool_weights":{},"reweight":-1,"kb":0,"kb_used":0,"kb_used_data":0,"kb_used_omap":0,"kb_used_meta":0,"kb_avail":0,"utilization":0,"var":0,"pgs":0,"children":[344,340,336,332,328,324,320,316,312,307,302,297,293,287]},{"id":-153,"name":"sf-sby001-hc0039-rack005","type":"host","type_id":1,"pool_weights":{},"reweight":-1,"kb":0,"kb_used":0,"kb_used_data":0,"kb_used_omap":0,"kb_used_meta":0,"kb_avail":0,"utilization":0,"var":0,"pgs":0,"children":[275,271,267,263,259,255,250,244,237,230,223,216,209,203]},{"id":-189,"name":"sf-sby001-hc0040-rack005","type":"host","type_id":1,"pool_weights":{},"reweight":-1,"kb":0,"kb_used":0,"kb_used_data":0,"kb_used_omap":0,"kb_used_meta":0,"kb_avail":0,"utilization":0,"var":0,"pgs":0,"children":[345,342,338,334,330,326,322,318,314,309,304,299,294,288]},{"id":-177,"name":"sf-sby001-hc0041-rack005","type":"host","type_id":1,"pool_weights":{},"reweight":-1,"kb":0,"kb_used":0,"kb_used_data":0,"kb_used_omap":0,"kb_used_meta":0,"kb_avail":0,"utilization":0,"var":0,"pgs":0,"children":[289,283]},{"id":-169,"name":"sf-sby001-hc0042-rack005","type":"host","type_id":1,"pool_weights":{},"reweight":-1,"kb":0,"kb_used":0,"kb_used_data":0,"kb_used_omap":0,"kb_used_meta":0,"kb_avail":0,"utilization":0,"var":0,"pgs":0,"children":[282,279]},{"id":-197,"name":"sf-sby001-hc0043-rack005","type":"host","type_id":1,"pool_weights":{},"reweight":-1,"kb":0,"kb_used":0,"kb_used_data":0,"kb_used_omap":0,"kb_used_meta":0,"kb_avail":0,"utilization":0,"var":0,"pgs":0,"children":[349,347]},{"id":-118,"name":"rack006","type":"rack","type_id":3,"pool_weights":{},"reweight":-1,"kb":0,"kb_used":0,"kb_used_data":0,"kb_used_omap":0,"kb_used_meta":0,"kb_avail":0,"utilization":0,"var":0,"pgs":0,"children":[-309,-305,-265,-261,-201,-205,-193,-145,-141,-117,-129,-165,-137]},{"id":-137,"name":"sf-sby001-hc0044-rack006","type":"host","type_id":1,"pool_weights":{},"reweight":-1,"kb":0,"kb_used":0,"kb_used_data":0,"kb_used_omap":0,"kb_used_meta":0,"kb_avail":0,"utilization":0,"var":0,"pgs":0,"children":[239,232,225,218,212,206,201,198]},{"id":-165,"name":"sf-sby001-hc0045-rack006","type":"host","type_id":1,"pool_weights":{},"reweight":-1,"kb":0,"kb_used":0,"kb_used_data":0,"kb_used_omap":0,"kb_used_meta":0,"kb_avail":0,"utilization":0,"var":0,"pgs":0,"children":[310,305,300,295,290,284,280,278]},{"id":-129,"name":"sf-sby001-hc0046-rack006","type":"host","type_id":1,"pool_weights":{},"reweight":-1,"kb":0,"kb_used":0,"kb_used_data":0,"kb_used_omap":0,"kb_used_meta":0,"kb_avail":0,"utilization":0,"var":0,"pgs":0,"children":[183,182,181,180,179,178,177,176,173,171,169,167,165,163]},{"id":-117,"name":"sf-sby001-hc0047-rack006","type":"host","type_id":1,"pool_weights":{},"reweight":-1,"kb":0,"kb_used":0,"kb_used_data":0,"kb_used_omap":0,"kb_used_meta":0,"kb_avail":0,"utilization":0,"var":0,"pgs":0,"children":[161,160,159,158,157,156,155,153,151,149,147,145,143,141]},{"id":-141,"name":"sf-sby001-hc0048-rack006","type":"host","type_id":1,"pool_weights":{},"reweight":-1,"kb":0,"kb_used":0,"kb_used_data":0,"kb_used_omap":0,"kb_used_meta":0,"kb_avail":0,"utilization":0,"var":0,"pgs":0,"children":[274,270,266,262,258,253,248,241,233,226,219,211,205,200]},{"id":-145,"name":"sf-sby001-hc0049-rack006","type":"host","type_id":1,"pool_weights":{},"reweight":-1,"kb":0,"kb_used":0,"kb_used_data":0,"kb_used_omap":0,"kb_used_meta":0,"kb_avail":0,"utilization":0,"var":0,"pgs":0,"children":[273,269,265,261,256,251,245,238,231,224,217,210,204,199]},{"id":-193,"name":"sf-sby001-hc0050-rack006","type":"host","type_id":1,"pool_weights":{},"reweight":-1,"kb":0,"kb_used":0,"kb_used_data":0,"kb_used_omap":0,"kb_used_meta":0,"kb_avail":0,"utilization":0,"var":0,"pgs":0,"children":[348,346]},{"id":-205,"name":"sf-sby001-hc0051-rack006","type":"host","type_id":1,"pool_weights":{},"reweight":-1,"kb":0,"kb_used":0,"kb_used_data":0,"kb_used_omap":0,"kb_used_meta":0,"kb_avail":0,"utilization":0,"var":0,"pgs":0,"children":[353,352]},{"id":-201,"name":"sf-sby001-hc0052-rack006","type":"host","type_id":1,"pool_weights":{},"reweight":-1,"kb":0,"kb_used":0,"kb_used_data":0,"kb_used_omap":0,"kb_used_meta":0,"kb_avail":0,"utilization":0,"var":0,"pgs":0,"children":[351,350]},{"id":-261,"name":"sf-sby001-hc0070-rack004","type":"host","type_id":1,"pool_weights":{},"reweight":-1,"kb":0,"kb_used":0,"kb_used_data":0,"kb_used_omap":0,"kb_used_meta":0,"kb_avail":0,"utilization":0,"var":0,"pgs":0,"children":[390,389,388,387,386,385,384,383]},{"id":-265,"name":"sf-sby001-hc0071-rack006","type":"host","type_id":1,"pool_weights":{},"reweight":-1,"kb":0,"kb_used":0,"kb_used_data":0,"kb_used_omap":0,"kb_used_meta":0,"kb_avail":0,"utilization":0,"var":0,"pgs":0,"children":[398,397,396,395,394,393,392,391]},{"id":-305,"name":"sf-sby001-hc0081-rack006","type":"host","type_id":1,"pool_weights":{},"reweight":-1,"kb":0,"kb_used":0,"kb_used_data":0,"kb_used_omap":0,"kb_used_meta":0,"kb_avail":0,"utilization":0,"var":0,"pgs":0,"children":[478,477,476,475,474,473,472,471]},{"id":-309,"name":"sf-sby001-hc0082-rack006","type":"host","type_id":1,"pool_weights":{},"reweight":-1,"kb":0,"kb_used":0,"kb_used_data":0,"kb_used_omap":0,"kb_used_meta":0,"kb_avail":0,"utilization":0,"var":0,"pgs":0,"children":[486,485,484,483,482,481,480,479]},{"id":-77,"name":"rack007","type":"rack","type_id":3,"pool_weights":{},"reweight":-1,"kb":0,"kb_used":0,"kb_used_data":0,"kb_used_omap":0,"kb_used_meta":0,"kb_avail":0,"utilization":0,"var":0,"pgs":0,"children":[-217,-209,-213,-76,-161,-133,-181,-125,-149]},{"id":-149,"name":"sf-sby001-hc0053-rack007","type":"host","type_id":1,"pool_weights":{},"reweight":-1,"kb":0,"kb_used":0,"kb_used_data":0,"kb_used_omap":0,"kb_used_meta":0,"kb_avail":0,"utilization":0,"var":0,"pgs":0,"children":[246,240,234,227,220,213,207,202]},{"id":-125,"name":"sf-sby001-hc0054-rack007","type":"host","type_id":1,"pool_weights":{},"reweight":-1,"kb":0,"kb_used":0,"kb_used_data":0,"kb_used_omap":0,"kb_used_meta":0,"kb_avail":0,"utilization":0,"var":0,"pgs":0,"children":[175,174,172,170,168,166,164,162]},{"id":-181,"name":"sf-sby001-hc0055-rack007","type":"host","type_id":1,"pool_weights":{},"reweight":-1,"kb":0,"kb_used":0,"kb_used_data":0,"kb_used_omap":0,"kb_used_meta":0,"kb_avail":0,"utilization":0,"var":0,"pgs":0,"children":[343,339,335,331,327,323,319,315,311,306,301,296,291,285]},{"id":-133,"name":"sf-sby001-hc0056-rack007","type":"host","type_id":1,"pool_weights":{},"reweight":-1,"kb":0,"kb_used":0,"kb_used_data":0,"kb_used_omap":0,"kb_used_meta":0,"kb_avail":0,"utilization":0,"var":0,"pgs":0,"children":[197,196,195,194,193,192,191,190,189,188,187,186,185,184]},{"id":-161,"name":"sf-sby001-hc0057-rack007","type":"host","type_id":1,"pool_weights":{},"reweight":-1,"kb":0,"kb_used":0,"kb_used_data":0,"kb_used_omap":0,"kb_used_meta":0,"kb_avail":0,"utilization":0,"var":0,"pgs":0,"children":[277,276,272,268,264,260,257,252,247,242,235,228,221,214]},{"id":-76,"name":"sf-sby001-hc0058-rack007","type":"host","type_id":1,"pool_weights":{},"reweight":-1,"kb":0,"kb_used":0,"kb_used_data":0,"kb_used_omap":0,"kb_used_meta":0,"kb_avail":0,"utilization":0,"var":0,"pgs":0,"children":[139,138,137,136,135,134,133,132,131,130,129,128,127,126]},{"id":-213,"name":"sf-sby001-hc0059-rack007","type":"host","type_id":1,"pool_weights":{},"reweight":-1,"kb":0,"kb_used":0,"kb_used_data":0,"kb_used_omap":0,"kb_used_meta":0,"kb_avail":0,"utilization":0,"var":0,"pgs":0,"children":[357,356]},{"id":-209,"name":"sf-sby001-hc0060-rack007","type":"host","type_id":1,"pool_weights":{},"reweight":-1,"kb":0,"kb_used":0,"kb_used_data":0,"kb_used_omap":0,"kb_used_meta":0,"kb_avail":0,"utilization":0,"var":0,"pgs":0,"children":[355,354]},{"id":-217,"name":"sf-sby001-hc0061-rack007","type":"host","type_id":1,"pool_weights":{},"reweight":-1,"kb":0,"kb_used":0,"kb_used_data":0,"kb_used_omap":0,"kb_used_meta":0,"kb_avail":0,"utilization":0,"var":0,"pgs":0,"children":[359,358]}],"stray":[],"summary":{"total_kb":832193175552,"total_kb_used":300991865560,"total_kb_used_data":300215105980,"total_kb_used_omap":6776576,"total_kb_used_meta":769922047,"total_kb_avail":531201309992,"average_utilization":36.168509235893438,"min_var":0.58043622090868996,"max_var":1.6152162823125038,"dev":6.8424446021299987}}
